Workbook

Sheet Data Summary
A1: CURRENT STATISTICS
A2: Table 1: SEBI Registered Market Intermediaries/Institutions
A3: Table 2: Company-Wise Capital Raised through Public and Rights Issues (Equity)
A4: Table 3: Offers closed during the month under SEBI (SAST), 2011
A5: Table 4: Trends in Offers closed under SEBI (Substantial Acquisition of Shares and Takeover) Regulations, 2011
A6: Table 5: Consolidated Resource Mobilisation through Primary Market
A7: Table 6: Capital Raised from the Primary Market through Public and Rights Issues (Equity and Debt)
A8: Table 7: Industry-wise Classification of Capital Raised through Public and Rights Issues (Equity)
A9: Table 8: Sector-wise and Region-wise Distribution of Capital Mobilised through Public and Rights Issues (Equity)
A10: Table 9: Size-wise Classification of Capital Raised through Public and Rights Issues (Equity)
A11: Table 10: Capital Raised by Listed Companies from the Primary Market through QIPs
A12: Table 11: Preferential Allotments Listed at BSE, NSE and MSEI
... A75: Table 74: Macro Economic Indicators

Sheet 1
A1: Table 1: SEBI Registered Market Intermediaries/Institutions
A2: Market Intermediaries | B2: 2023-24 | C2: 45504
A3: Stock Exchanges (Cash Segment) | B3: 3 | C3: 3
A4: Stock Exchanges (Equity Derivatives Segment) | B4: 3 | C4: 3
A5: Stock Exchanges (Currency Derivatives Segment) | B5: 3 | C5: 3
A6: Stock Exchanges (Commodity Derivatives Segment) | B6: 4 | C6: 4
A7: Brokers (Cash Segment)
A8: BSE | B8: 1269 | C8: 1228
A9: NSE | B9: 1212 | C9: 1217
A10: MSEI | B10: 295 | C10: 290
A11: Brokers (Equity Derivatives Segment)
A12: BSE | B12: 903 | C12: 880
A13: NSE | B13: 1138 | C13: 1147
A14: MSEI | B14: 274 | C14: 269
A15: Brokers (Currency Derivatives Segment)
A16: BSE | B16: 560 | C16: 555
A17: NSE | B17: 754 | C17: 757
A18: MSEI | B18: 470 | C18: 465
A19: Brokers (Debt Segment)
A20: BSE | B20: 280 | C20: 282
A21: NSE | B21: 271 | C21: 277
A22: MSEI | B22: 14 | C22: 14
A23: Brokers (Commodity Derivatives Segment)
A24: MCX | B24: 546 | C24: 540
A25: NCDEX | B25: 250 | C25: 239
A26: ICEX | B26: 98 | C26: 98
A27: BSE | B27: 288 | C27: 290
A28: NSE | B28: 352 | C28: 365
A29: Corporate Brokers(Cash Segment)
A30: BSE | B30: 1092 | C30: 1070
A31: NSE | B31: 1093 | C31: 1098
A32: MSEI | B32: 270 | C32: 265
A33: Foreign Portfolio Investors (FPIs) | B33: 11219 | C33: 11483
A34: Custodians | B34: 17 | C34: 17
A35: Designated Depositories Participants (DDPs) | B35: 17 | C35: 17
A36: Depositories | B36: 2 | C36: 2
A37: Depository Participants
A38: NSDL | B38: 281 | C38: 285
A39: CDSL | B39: 580 | C39: 572
A40: Merchant Bankers | B40: 220 | C40: 225
A41: Bankers to an Issue | B41: 57 | C41: 57
A42: Debenture Trustees | B42: 25 | C42: 25
A43: Credit Rating Agencies | B43: 7 | C43: 7
A44: KYC Registration Agencies (KRA) | B44: 5 | C44: 5
A45: Registrars to an Issue & Share Transfer Agents | B45: 75 | C45: 74
A46: Venture Capital Funds | B46: 167 | C46: 166
A47: Foreign Venture Capital Investors | B47: 279 | C47: 278
A48: Alternative Investment Funds | B48: 1283 | C48: 1345
A49: Portfolio Managers | B49: 420 | C49: 435
... A60: STP Service Providers | B60: 3 | C60: 3
A61: Source: SEBI, NSDL, CDSL.

Sheet 2
A1: Table 2: Company-Wise Capital Raised through Public and Rights Issues (Equity) (During the month of July 2024)
A2: Sl.No. | B2: Name of the Issuer/Company | C2: Date of Listing | D2: Type of Issue | E2: Number of Shares issued | F2: Face Value (₹ ) | G2: Premium Value (₹ ) | H2: Issue Price (₹ ) | I2: Amount raised (in crores) | L2: Oversubscribed (no. of times) | M2: Allocation in Net offer to public & Others (No. of shares) | Q2: Net offer to public*
I3: Fresh | J3: OFS | K3: Total | M3: QIB | N3: NII | O3: RII | P3: Others, if any (Market Maker & Reservation)
A4: 1 | B4: Mason Infratech Limited | C4: 45474 | D4: NSE SME IPO | E4: 4760000 | F4: 10 | G4: 54 | H4: 64 | I4: 30.464 | J4: 0 | K4: 30.464 | L4: 30.662 | M4: 2256000 | N4: 680000 | O4: 1584000 | P4: 240000 | Q4: 4520000
A5: 2 | B5: Shivalic Power Control Limited | C5: 45474 | D5: NSE SME IPO | E5: 6432000 | F5: 10 | G5: 90 | H5: 100 | I5: 64.32 | J5: 0 | K5: 64.32 | L5: 238.63 | M5: 3048000 | N5: 914400 | O5: 2133600 | P5: 336000 | Q5: 6096000
A6: 3 | B6: Sylvan Plyboard (India) Limited | C6: 45474 | D6: NSE SME IPO | E6: 5100000 | F6: 10 | G6: 45 | H6: 55 | I6: 28.05 | J6: 0 | K6: 28.05 | L6: 93.1 | M6: 0 | N6: 2222000 | O6: 2622000 | P6: 256000 | Q6: 4844000
A7: 4 | B7: Visaman Global Sales Limited | C7: 45474 | D7: NSE SME IPO | E7: 3732000 | F7: 10 | G7: 33 | H7: 43 | I7: 16.0476 | J7: 0 | K7: 16.0476 | L7: 37.48 | M7: 0 | N7: 1251000 | O7: 2289000 | P7: 192000 | Q7: 3540000
A8: 5 | B8: Akiko Global Services Limited | C8: 45475 | D8: NSE SME IPO | E8: 3001600 | F8: 10 | G8: 67 | H8: 77 | I8: 23.11232 | J8: 0 | K8: 23.11232 | L8: 35.25 | M8: 1424000 | N8: 428800 | O8: 998400 | P8: 150400 | Q8: 2851200
A9: 6 | B9: Divine Power Energy Limited | C9: 45475 | D9: NSE SME IPO | E9: 5688000 | F9: 10 | G9: 30 | H9: 40 | I9: 22.752 | J9: 0 | K9: 22.752 | L9: 472.44 | M9: 2700000 | N9: 810000 | O9: 1890000 | P9: 288000 | Q9: 5400000
A10: 7 | B10: Petro Carbon and Chemicals Limited | C10: 45475 | D10: NSE SME IPO | E10: 6617600 | F10: 10 | G10: 161 | H10: 171 | I10: 0 | J10: 113.16096 | K10: 113.16096 | L10: 93.55 | M10: 3092000 | N10: 928800 | O10: 2166400 | P10: 430400 | Q10: 6187200
A11: 8 | B11: Allied Blenders and Distillers Limited | C11: 45475 | D11: IPO | E11: 53390079 | F11: 2 | G11: 279 | H11: 281 | I11: 1000.2613 | J11: 499.99996 | K11: 1500.2612 | L11: 25.61 | M11: 26644795 | N11: 7993439 | O11: 18651357 | P11: 100488 | Q11: 53289591
A12: 9 | B12: Diensten Tech Limited | C12: 45476 | D12: NSE SME IPO | E12: 2208000 | F12: 10 | G12: 90 | H12: 100 | I12: 22.08 | J12: 0 | K12: 22.08 | L12: 50.47 | M12: 1047600 | N12: 315600 | O12: 734400 | P12: 110400 | Q12: 2097600
A13: 10 | B13: Vraj Iron and Steel Limited | C13: 45476 | D13: IPO | E13: 8260869 | F13: 10 | G13: 197 | H13: 207 | I13: 170.99999 | J13: 0 | K13: 170.99999 | L13: 133.9 | M13: 4130433 | N13: 1239131 | O13: 2891305 | P13: 0 | Q13: 8260869
A14: 11 | B14: Nephro Care India Limited | C14: 45478 | D14: NSE SME IPO | E14: 4584000 | F14: 10 | G14: 80 | H14: 90 | I14: 41.256 | J14: 0 | K14: 41.256 | L14: 712.36 | M14: 2145600 | N14: 644800 | O14: 1504000 | P14: 289600 | Q14: 4294400
A15: 12 | B15: Integra Essentia Limited | C15: 45478 | D15: Rights | E15: 153624538 | F15: 1 | G15: 2.25 | H15: 3.25 | I15: 49.92 | J15: 0 | K15: 49.92 | L15: 1.1907 | M15: 0 | N15: 0 | O15: 0 | P15: 0 | Q15: 0
... A45: 42 | B45: Srestha Finvest Limited | C45: 45504 | D45: Rights | E45: 240000000 | F45: 2 | G45: 0 | H45: 2 | I45: 48 | J45: 0 | K45: 48 | L45: 1.093 | M45: 0 | N45: 0 | O45: 0 | P45: 0 | Q45: 0
A47: *Shares issued by the Company are partly paid up but the information is provided considering the same as fully paid up.
A48: Net offer to Public = QIB (Including anchor) + RII + NII (Excluding Employee Reservation +Shareholder Reservation + Market maker)
A49: Source: SEBI

Sheet 3
A1: Table 3: Offers closed during July 2024 under SEBI (Substantial Acquisition of Shares and Takeover) Regulations, 2011
A2: Sl.No | B2: Target Company | C2: Acquirers/PACs | D2: Public Announcement Date | E2: Offer Opening Date | F2: Offer Closing Date | G2: Offer Size | I2: Offer Price (₹ ) per share | J2: Offer Size (₹ crore)
G3: No. of Shares | H3: Percent of Equity Capital
A4: 1 | B4: Consecutive Investments & Trading Company Limited | C4: M/s Birford Enterprises Private Limited | D4: 45322 | E4: 45471 | F4: 45484 | G4: 2081950 | H4: 26 | I4: 20 | J4: 4.1639
A5: 2 | B5: RKD Agri & Retail Limited | C5: Nilesh Malshi Savla and Meena Nilesh Savla | D5: 45344 | E5: 45474 | F5: 45485 | G5: 12889500 | H5: 26 | I5: 1.12 | J5: 1.443624
A6: 3 | B6: Continental Controls Limited | C6: Onelife Capital Advisors Limited | D6: 45357 | E6: 45474 | F6: 45485 | G6: 1598027 | H6: 26 | I6: 4 | J6: 0.6392108
A7: 4 | B7: Bangalore Fort Farms Limited | C7: Genesis Trade-Links Private Limited, Mr. Vikash Singh and Mrs. Nitu Singh | D7: 45364 | E7: 45474 | F7: 45485 | G7: 1247844 | H7: 26 | I7: 28.5 | J7: 3.5563554
A8: 5 | B8: Agro Tech Foods Limited | C8: ZEST HOLDING INVESTMENTS LIMITED, ZEST INVESTMENTS LIMITED, SAMARA CAPITAL PARTNERS FUND III LIMITED, INFINITY HOLDINGS, INFINITY HOLDINGS SIDECAR 1 | D8: 45351 | E8: 45484 | F8: 45498 | G8: 6336009 | H8: 26 | I8: 578.03 | J8: 366.24033
A9: 6 | B9: SOMA PAPERS AND INDUSTRIES LIMITED | C9: Mr. Narasimharao Anumala , Mr. Anumala Ramesh Choudary , Ms. Anupama Anumala | D9: 45364 | E9: 45484 | F9: 45498 | G9: 364559 | H9: 26 | I9: 12 | J9: 0.4374708
A10: 7 | B10: Ahmedabad Steelcraft Limited | C10: Mr. Rohit Pandey and Mr. Sunil Dutt Pandey | D10: 45415 | E10: 45485 | F10: 45499 | G10: 1063920 | H10: 26 | I10: 54 | J10: 5.745168
A11: 8 | B11: S&S Power Switchgear Limited | C11: Hamilton & Company Limited (“Acquirer”) and Sushil Kumar Jalan, Rekha Jalan, Ashish Jalan, Snehal Jalan, Ananya Jalan, Ashish Jalan Family Trust and Sushil K Jalan HUF (PACs). | D11: 45318 | E11: 45489 | F11: 45503 | G11: 3088947 | H11: 25.03 | I11: 155 | J11: 47.878678
A12: 9 | B12: Swadeshi Industries and Leasing Ltd. | C12: Mrs. Jayshree Radheshyam Sharma | D12: 45343 | E12: 45489 | F12: 45503 | G12: 2812667 | H12: 26 | I12: 2 | J12: 0.5625334
A13: 10 | B13: Trimurthi Limited | C13: Srinidhi Fine-Chemicals LLP and Mr. Vupparapalli Chandrasekhar Reddy | D13: 45356 | E13: 45489 | F13: 45503 | G13: 2652000 | H13: 26.65 | I13: 10 | J13: 2.652
A14: 11 | B14: Vikalp Securities Limited | C14: Deepakbhai Patel, Kamuben Patel | D14: 45397 | E14: 45489 | F14: 45503 | G14: 793500 | H14: 26 | I14: 25 | J14: 1.98375
A15: 12 | B15: Suncity Synthetics Limited | C15: Sumita Mishra | D15: 45398 | E15: 45489 | F15: 45503 | G15: 1285908 | H15: 26 | I15: 7 | J15: 0.9001356
A16: 13 | B16: Integra Switchgear Limited | C16: Northvale Capital Partners Private Limited | D16: 45334 | E16: 45489 | F16: 45503 | G16: 749216 | H16: 26 | I16: 12 | J16: 0.8990592
A18: Source: SEBI.

Sheet 4
A1: Table 4: Trends in Offers closed under SEBI (Substantial Acquisition of Shares and Takeover) Regulations, 2011
A2: Year / Month | B2: Open Offers
B3: Objectives | H3: Total
B4: Change in Control of Management | D4: Consolidation of Holdings | F4: Substantial Acquisition | H4: No. of Offers | I4: Amount (₹ crore)
B5: No. of Offers | C5: Amount (₹ crore) | D5: No. of Offers | E5: Amount (₹ crore) | F5: No. of Offers | G5: Amount (₹ crore)
A6: 2023-24 | B6: 1 | C6: 4.36 | D6: 1 | E6: 3.27 | F6: 71 | G6: 10243.92 | H6: 73 | I6: 10251.55
A7: 2024-25# | B7: =SUM(B8:B11) -> 21 | C7: =SUM(C8:C11) -> 477.4571 | D7: =SUM(D8:D11) -> 1 | E7: =SUM(E8:E11) -> 5.61 | F7: =SUM(F8:F11) -> 0 | G7: =SUM(G8:G11) -> 0 | H7: =SUM(H8:H11) -> 22 | I7: =SUM(I8:I11) -> 483.0671
A8: 45383 | B8: 4 | C8: 25.34 | D8: 1 | E8: 5.61 | F8: 0 | G8: 0 | H8: =SUM(B8,D8,F8) -> 5 | I8: =SUM(C8,E8,G8) -> 30.95
A9: =EOMONTH(A8,1) -> 45443 | B9: 1 | C9: 4.98 | D9: 0 | E9: 0 | F9: 0 | G9: 0 | H9: 1 | I9: 4.98
A10: =EOMONTH(A9,1) -> 45473 | B10: 3 | C10: 10.0371 | D10: 0 | E10: 0 | F10: 0 | G10: 0 | H10: =SUM(B10,D10,F10) -> 3 | I10: =SUM(C10,E10,G10) -> 10.0371
A11: =EOMONTH(A10,1) -> 45504 | B11: 13 | C11: 437.1 | D11: 0 | E11: 0 | F11: 0 | G11: 0 | H11: =SUM(B11,D11,F11) -> 13 | I11: =SUM(C11,E11,G11) -> 437.1
A12: ="# indicates as on "&TEXT('1'!$C$2,"mmmm dd, yyyy") -> # indicates as on July 31, 2024
A13: *In instances where offers have more than one objective, the issue is classified only under one of the same.
A14: Data is compiled based on offer closing date
A15: Source: SEBI.

Sheet 5
A1: Table 5: Consolidated Resource Mobilisation through Primary markets | U1: =U6+S6 -> 1957.28
A2: Modes of Fund Raising | B2: 2023-24 | F2: ="2024-25 (upto "&TEXT('1'!$C$2,"mmmm dd, yyyy")&")" -> 2024-25 (upto July 31, 2024) | J2: 45412 | N2: =EOMONTH(J2,1) -> 45443 | R2: =EOMONTH(N2,1) -> 45473 | V2: =EOMONTH(R2,1) -> 45504
B3: Financial Sector | D3: Non-Financial Sector | F3: Financial Sector | H3: Non-Financial Sector | J3: Financial Sector | L3: Non-Financial Sector | N3: Financial Sector | P3: Non-Financial Sector | R3: Financial Sector | T3: Non-Financial Sector | V3: Financial Sector | X3: Non-Financial Sector
B4: No. of Issues | C4: Amount (Rs.crore) | D4: No. of Issues | E4: Amount (Rs.crore) | F4: No. of Issues | G4: Amount (Rs.crore) | H4: No. of Issues | I4: Amount (Rs.crore) | J4: No. of Issues | K4: Amount (Rs.crore) | L4: No. of Issues | M4: Amount (Rs.crore) | N4: No. of Issues | O4: Amount (Rs.crore) | P4: No. of Issues | Q4: Amount (Rs.crore) | R4: No. of Issues | S4: Amount (Rs.crore) | T4: No. of Issues | U4: Amount (Rs.crore) | V4: No. of Issues | W4: Amount (Rs.crore) | X4: No. of Issues | Y4: Amount (Rs.crore)
A5: Equity Issues
A6: A. IPOs (Main Board) | B6: 9 | C6: 7506.2741 | D6: 67 | E6: 54353.573 | F6: 3 | G6: 5746.6459 | H6: 15 | I6: 15749.873 | J6: 0 | K6: 0 | L6: 3 | M6: 5054.67 | N6: 2 | O6: 5614.6459 | P6: 3 | Q6: 3991.4846 | R6: 1 | S6: 132 | T6: 4 | U6: 1825.28 | V6: 0 | W6: 0 | X6: 5 | Y6: =SUM(Y7:Y8) -> 4878.4382
A7: i) OFS Component | B7: - | C7: 2942.2088 | D7: - | E7: 30160.031 | F7: - | G7: 3489.6458 | H7: - | I7: 10273.338 | J7: - | K7: 0 | L7: - | M7: 4624.4737 | N7: - | O7: 3489.6458 | P7: - | Q7: 2703.4941 | R7: - | S7: 0 | T7: - | U7: 1180.2934 | V7: - | W7: 0 | X7: - | Y7: 1765.0769
A8: ii) Fresh Capital Raising Component | B8: - | C8: 4564.8985 | D8: - | E8: 24200.779 | F8: - | G8: 2257.5513 | H8: - | I8: 5477.6259 | J8: - | K8: 0 | L8: - | M8: 430.19997 | N8: - | O8: 2125.5513 | P8: - | Q8: 1288.9614 | R8: - | S8: 132 | T8: - | U8: 645.10323 | V8: - | W8: 0 | X8: - | Y8: 3113.3612
A9: B. IPO (SME) | B9: 3 | C9: 121.60544 | D9: 193 | E9: 5973.8595 | F9: 1 | G9: 32.52 | H9: 85 | I9: 2912.7608 | J9: 0 | K9: 0 | L9: 23 | M9: 672.70852 | N9: 0 | O9: 0 | P9: 21 | Q9: 527.21852 | R9: 1 | S9: 32.52 | T9: 16 | U9: 530.818 | V9: 0 | W9: 0 | X9: 25 | Y9: =SUM(Y10:Y11) -> 1182.0157
A10: i) OFS Component | B10: - | C10: 6.08 | D10: - | E10: 322.28525 | F10: - | G10: 9.288 | H10: - | I10: 212.01756 | J10: - | K10: 0 | L10: - | M10: 0 | N10: - | O10: 0 | P10: - | Q10: 6.5988 | R10: - | S10: 9.288 | T10: - | U10: 48.536 | V10: - | W10: 0 | X10: - | Y10: 156.88276
A11: ii) Fresh Capital Raising Component | B11: - | C11: 115.52356 | D11: - | E11: 5651.7001 | F11: - | G11: 23.232 | H11: - | I11: 2700.7885 | J11: - | K11: 0 | L11: - | M11: 672.72668 | N11: - | O11: 0 | P11: - | Q11: 520.62464 | R11: - | S11: 23.232 | T11: - | U11: 482.3042 | V11: - | W11: 0 | X11: - | Y11: 1025.133
A12: C. IPO (Total) [A+B] | B12: 12 | C12: 7627.8795 | D12: 260 | E12: 60327.433 | F12: 4 | G12: 5779.1659 | H12: 100 | I12: 18662.634 | J12: =J9+J6 -> 0 | K12: =K9+K6 -> 0 | L12: =L9+L6 -> 26 | M12: =M9+M6 -> 5727.3785 | N12: =N9+N6 -> 2 | O12: =O9+O6 -> 5614.6459 | P12: =P9+P6 -> 24 | Q12: =Q9+Q6 -> 4518.7031 | ... Y12: =Y9+Y6 -> 6060.4539
A13: i) OFS Component (Total) | B13: - | C13: 2948.2888 | D13: - | E13: 30482.317 | F13: - | G13: 3498.9338 | H13: - | I13: 10485.356 | J13: - | K13: =K7+K10 -> 0 | L13: - | M13: =M7+M10 -> 4624.4737 | N13: - | O13: =O7+O10 -> 3489.6458 | P13: - | Q13: =Q7+Q10 -> 2710.0929 | R13: - | S13: =S7+S10 -> 9.288 | T13: - | U13: =U7+U10 -> 1228.8294 | V13: - | W13: =W7+W10 -> 0 | X13: - | Y13: =Y7+Y10 -> 1921.9597
A14: ii) Fresh Capital Raising Component (Total) | B14: - | C14: 4680.422 | D14: - | E14: 29852.479 | F14: - | G14: 2280.7833 | H14: - | I14: 8178.4143 | J14: - | K14: =K8+K11 -> 0 | L14: - | M14: =M11+M8 -> 1102.9267 | N14: - | O14: =O8+O11 -> 2125.5513 | P14: - | Q14: =Q11+Q8 -> 1809.5861 | R14: - | S14: =S8+S11 -> 155.232 | T14: - | U14: =U11+U8 -> 1127.4074 | V14: - | W14: =W8+W11 -> 0 | X14: - | Y14: =Y11+Y8 -> 4138.4942
A15: D. FPO in the Main Board | B15: 0 | C15: 0 | D15: 0 | E15: 0 | F15: 0 | G15: 0 | H15: 2 | I15: 18149.992 | J15: =J16+J17 -> 0 | K15: =K16+K17 -> 0 | L15: 1 | M15: 18000 | N15: =N16+N17 -> 0 | O15: =O16+O17 -> 0 | P15: =P16+P17 -> 0 | Q15: =Q16+Q17 -> 0 | R15: =R16+R17 -> 0 | S15: =S16+S17 -> 0 | T15: =T16+T17 -> 0 | U15: =U16+U17 -> 0 | ... Y15: =Y16+Y17 -> 149.9925
A16: i) OFS Component | B16: 0 | C16: 0 | D16: 0 | E16: 0 | F16: 0 | G16: 0 | H16: 0 | I16: 0 | J16: 0 | K16: 0 | L16: 0 | M16: 0 | N16: 0 | O16: 0 | P16: 0 | Q16: 0 | R16: 0 | S16: 0 | T16: 0 | U16: 0 | V16: 0 | W16: 0 | X16: 0 | Y16: 0
A17: ii) Fresh Capital Raising Component | B17: 0 | C17: 0 | D17: 0 | E17: 0 | F17: 0 | G17: 0 | H17: 2 | I17: 18149.992 | J17: 0 | K17: 0 | L17: 1 | M17: 18000 | N17: 0 | O17: 0 | P17: 0 | Q17: 0 | R17: 0 | S17: 0 | T17: 0 | U17: 0 | V17: 0 | W17: 0 | X17: 1 | Y17: 149.9925
A18: E. FPO in the SME Segment | B18: 0 | C18: 0 | D18: 1 | E18: 27 | F18: 0 | G18: 0 | H18: 0 | I18: 0 | J18: =J19+J20 -> 0 | K18: =K19+K20 -> 0 | L18: =L19+L20 -> 0 | M18: =M19+M20 -> 0 | N18: =N19+N20 -> 0 | O18: =O19+O20 -> 0 | P18: =P19+P20 -> 0 | Q18: =Q19+Q20 -> 0 | ... Y18: =Y19+Y20 -> 0
A19: i) OFS Component | B19: 0 | C19: 0 | D19: 0 | E19: 0 | F19: 0 | G19: 0 | H19: 0 | I19: 0 | J19: 0 | K19: 0 | L19: 0 | M19: 0 | N19: 0 | O19: 0 | P19: 0 | Q19: 0 | R19: 0 | S19: 0 | T19: 0 | U19: 0 | V19: 0 | W19: 0 | X19: 0 | Y19: 0
A20: ii) Fresh Capital Raising Component | B20: 0 | C20: 0 | D20: 1 | E20: 27 | F20: 0 | G20: 0 | H20: 0 | I20: 0 | J20: 0 | K20: 0 | L20: 0 | M20: 0 | N20: 0 | O20: 0 | P20: 0 | Q20: 0 | R20: 0 | S20: 0 | T20: 0 | U20: 0 | V20: 0 | W20: 0 | X20: 0 | Y20: 0
A21: F. FPO (Total) [D+E] | B21: 0 | C21: 0 | D21: 1 | E21: 27 | F21: 0 | G21: 0 | H21: 2 | I21: 18149.992 | J21: =J18+J15 -> 0 | K21: =K18+K15 -> 0 | L21: =L18+L15 -> 1 | M21: =M18+M15 -> 18000 | N21: =N18+N15 -> 0 | O21: =O18+O15 -> 0 | P21: =P18+P15 -> 0 | Q21: =Q18+Q15 -> 0 | ... Y21: =Y18+Y15 -> 149.9925
A22: i) OFS Component | B22: 0 | C22: 0 | D22: 0 | E22: 0 | F22: 0 | G22: 0 | H22: 0 | I22: 0 | J22: =J16+J19 -> 0 | K22: =K16+K19 -> 0 | L22: =L16+L19 -> 0 | M22: =M16+M19 -> 0 | N22: =N16+N19 -> 0 | O22: =O16+O19 -> 0 | P22: =P16+P19 -> 0 | Q22: =Q16+Q19 -> 0 | ... Y22: =Y16+Y19 -> 0
A23: ii) Fresh Capital Raising Component | B23: 0 | C23: 0 | D23: 1 | E23: 27 | F23: 0 | G23: 0 | H23: 2 | I23: 18149.992 | J23: =J20+J17 -> 0 | K23: =K20+K17 -> 0 | L23: =L20+L17 -> 1 | M23: =M20+M17 -> 18000 | N23: =N20+N17 -> 0 | O23: =O20+O17 -> 0 | P23: =P20+P17 -> 0 | Q23: =Q20+Q17 -> 0 | ... Y23: =Y20+Y17 -> 149.9925
A24: G. Total Public Issues in equity (C+F) | B24: =B12+B21 -> 12 | C24: =C12+C21 -> 7627.8795 | D24: =D12+D21 -> 261 | E24: =E12+E21 -> 60354.433 | F24: 4 | G24: 5779.1659 | H24: 102 | I24: 36812.626 | J24: =J12+J21 -> 0 | K24: =K12+K21 -> 0 | L24: =L12+L21 -> 27 | M24: =M12+M21 -> 23727.379 | N24: =N12+N21 -> 2 | O24: =O12+O21 -> 5614.6459 | P24: =P12+P21 -> 24 | Q24: =Q12+Q21 -> 4518.7031 | ... Y24: =Y12+Y21 -> 6210.4464
A25: i) OFS Component (Total) | B25: - | C25: =C13+C22 -> 2948.2888 | D25: - | E25: =E13+E22 -> 30482.317 | F25: - | G25: 3498.9338 | H25: - | I25: 10485.356 | J25: - | K25: =K13+K22 -> 0 | L25: - | M25: =M13+M22 -> 4624.4737 | N25: - | O25: =O13+O22 -> 3489.6458 | P25: - | Q25: =Q13+Q22 -> 2710.0929 | R25: - | S25: =S13+S22 -> 9.288 | T25: - | U25: =U13+U22 -> 1228.8294 | V25: - | W25: =W13+W22 -> 0 | X25: - | Y25: =Y13+Y22 -> 1921.9597
A26: ii) Fresh Capital Raising Component (Total) | B26: - | C26: =C14+C23 -> 4680.422 | D26: - | E26: =E14+E23 -> 29879.479 | F26: - | G26: 2280.7833 | H26: - | I26: 26328.407 | J26: - | K26: =K14+K23 -> 0 | L26: - | M26: =M14+M23 -> 19102.927 | N26: - | O26: =O14+O23 -> 2125.5513 | P26: - | Q26: =Q14+Q23 -> 1809.5861 | R26: - | S26: =S14+S23 -> 155.232 | T26: - | U26: =U14+U23 -> 1127.4074 | V26: - | W26: =W14+W23 -> 0 | X26: - | Y26: =Y14+Y23 -> 4288.4867
A27: H. Rights Issue | B27: 9 | C27: 7241.9913 | D27: 58 | E27: 7868.2127 | F27: 6 | G27: 2594.4881 | H27: 41 | I27: 5045.4625 | J27: =SUM(J28:J29) -> 2 | K27: =SUM(K28:K29) -> 1184.13 | L27: =SUM(L28:L29) -> 6 | M27: =SUM(M28:M29) -> 459.05831 | N27: =SUM(N28:N29) -> 1 | O27: =SUM(O28:O29) -> 1271.8281 | P27: =SUM(P28:P29) -> 11 | Q27: =SUM(Q28:Q29) -> 883.40641 | ... Y27: =SUM(Y28:Y29) -> 2742.9477
A28: i)MainBoard Companies | B28: 8 | C28: 7215.1313 | D28: 50 | E28: 7661.5576 | F28: 6 | G28: 2594.4881 | H28: 32 | I28: 4234.7065 | J28: 2 | K28: 1184.13 | L28: 4 | M28: 425.20831 | N28: 1 | O28: 1271.8281 | P28: 9 | Q28: 454.31841 | R28: 2 | S28: 90.53 | T28: 12 | U28: 949.5 | V28: 1 | W28: 48 | X28: 7 | Y28: 2405.6798
A29: ii) SME / IGP Companies | B29: 1 | C29: 26.86 | D29: 8 | E29: 206.65512 | F29: 0 | G29: 0 | H29: 9 | I29: 810.75595 | J29: 0 | K29: 0 | L29: 2 | M29: 33.85 | N29: 0 | O29: 0 | P29: 2 | Q29: 429.088 | R29: 0 | S29: 0 | T29: 2 | U29: 10.55 | V29: 0 | W29: 0 | X29: 3 | Y29: 337.26795
A30: I. Preferential Issue | B30: 69 | C30: 7021.1733 | D30: 620 | E30: 38134.004 | F30: 46 | G30: 8282.4075 | H30: 299 | I30: 35732.382 | J30: =J31+J32 -> 8 | K30: =K31+K32 -> 120.31 | L30: =L31+L32 -> 99 | M30: =M31+M32 -> 7581.8799 | N30: =N31+N32 -> 15 | O30: =O31+O32 -> 2614.4275 | P30: =P31+P32 -> 99 | Q30: =Q31+Q32 -> 22378.766 | ... Y30: =Y31+Y32 -> 976.80252
A31: i)MainBoard Companies | B31: 69 | C31: 7021.1733 | D31: 564 | E31: 37516.552 | F31: 45 | G31: 8268.3975 | H31: 262 | I31: 35130.317 | J31: 8 | K31: 120.31 | L31: 85 | M31: 7298.8208 | N31: 15 | O31: 2614.4275 | P31: 92 | Q31: 22307.354 | R31: 12 | S31: 2186.25 | T31: 42 | U31: 4664.8296 | V31: 10 | W31: 3347.41 | X31: 43 | Y31: 859.31226
A32: ii) SME / IGP Companies | B32: 0 | C32: 0 | D32: 56 | E32: 617.45168 | F32: 1 | G32: 14.01 | H32: 37 | I32: 602.06513 | J32: 0 | K32: 0 | L32: 14 | M32: 283.05913 | N32: 0 | O32: 0 | P32: 7 | Q32: 71.41169 | R32: 1 | S32: 14.01 | T32: 6 | U32: 130.10405 | X32: 10 | Y32: 117.49026
A33: J. QIPs/IPPs | B33: 15 | C33: 40320.47 | D33: 46 | E33: 28651.001 | F33: 3 | G33: 2599.9998 | H33: 27 | I33: 28385.677 | J33: =J34+J35 -> 2 | K33: =K34+K35 -> 2099.9999 | L33: =L34+L35 -> 9 | M33: =M34+M35 -> 9371.7329 | N33: =N34+N35 -> 0 | O33: =O34+O35 -> 0 | P33: =P34+P35 -> 2 | Q33: =Q34+Q35 -> 3039.9999 | ... Y33: =Y34+Y35 -> 13699.105
A34: i)MainBoard Companies | B34: 15 | C34: 40320.47 | D34: 44 | E34: 28534.464 | F34: 3 | G34: 2599.9998 | H34: 26 | I34: 28360.837 | J34: 2 | K34: 2099.9999 | L34: 9 | M34: 9371.7329 | N34: 0 | O34: 0 | P34: 2 | Q34: 3039.9999 | R34: 1 | S34: 499.9999 | T34: 4 | U34: 2249.9997 | V34: 0 | W34: 0 | X34: 11 | Y34: 13699.105
A35: ii) SME / IGP Companies | B35: 0 | C35: 0 | D35: 2 | E35: 116.53785 | F35: 0 | G35: 0 | H35: 1 | I35: 24.84 | J35: 0 | K35: 0 | L35: 0 | M35: 0 | N35: 0 | O35: 0 | P35: 0 | Q35: 0 | R35: 0 | S35: 0 | T35: 1 | U35: 24.84 | V35: 0 | W35: 0 | X35: 0 | Y35: 0
A36: K. OFS through Exchanges | B36: 4 | C36: 1652.728 | D36: 47 | E36: 22881.828 | F36: 0 | G36: 0 | H36: 6 | I36: 1186.0239 | J36: =J37+J38 -> 0 | K36: =K37+K38 -> 0 | L36: =L37+L38 -> 1 | M36: =M37+M38 -> 14.312002 | N36: =N37+N38 -> 0 | O36: =O37+O38 -> 0 | P36: =P37+P38 -> 1 | Q36: =Q37+Q38 -> 219.95773 | ... Y36: =Y37+Y38 -> 860.74329
A37: i)Mainboard companies | B37: 4 | C37: 1652.728 | D37: 47 | E37: 22881.828 | F37: 0 | G37: 0 | H37: 6 | I37: 1186.0239 | J37: 0 | K37: 0 | L37: 1 | M37: 14.312002 | N37: 0 | O37: 0 | P37: 1 | Q37: 219.95773 | R37: 0 | S37: 0 | T37: 1 | U37: 91.01092 | V37: 0 | W37: 0 | X37: 3 | Y37: 860.74329
A38: ii)SME/IGP companies | B38: 0 | C38: 0 | D38: 0 | E38: 0 | F38: 0 | G38: 0 | H38: 0 | I38: 0 | J38: 0 | K38: 0 | L38: 0 | M38: 0 | N38: 0 | O38: 0 | P38: 0 | Q38: 0 | R38: 0 | S38: 0 | T38: 0 | U38: 0 | V38: 0 | W38: 0 | X38: 0 | Y38: 0
A39: L. Total Equity raised | B39: =B24+B27+B30+B33+B36 -> 109 | C39: =C24+C27+C30+C33+C36 -> 63864.242 | D39: =D24+D27+D30+D33+D36 -> 1032 | E39: =E24+E27+E30+E33+E36 -> 157889.48 | F39: 59 | G39: 19256.061 | H39: 475 | I39: 107162.17 | J39: =J24+J27+J30+J33+J36 -> 12 | K39: =K24+K27+K30+K33+K36 -> 3404.4399 | L39: =L24+L27+L30+L33+L36 -> 142 | M39: =M24+M27+M30+M33+M36 -> 41154.362 | N39: =N24+N27+N30+N33+N36 -> 18 | O39: =O24+O27+O30+O33+O36 -> 9500.9015 | P39: =P24+P27+P30+P33+P36 -> 137 | Q39: =Q24+Q27+Q30+Q33+Q36 -> 31040.833 | ... Y39: =Y24+Y27+Y30+Y33+Y36 -> 24490.045
A40: i) OFS Component (Total) G(i)+K | B40: - | C40: =C25+C36 -> 4601.0168 | D40: - | E40: =E25+E36 -> 53364.145 | F40: - | G40: 3498.9338 | H40: - | I40: 11671.38 | J40: - | K40: =K25+K36 -> 0 | L40: - | M40: =M25+M36 -> 4638.7857 | N40: - | O40: =O25+O36 -> 3489.6458 | P40: - | Q40: =Q25+Q36 -> 2930.0506 | R40: - | S40: =S25+S36 -> 9.288 | T40: - | U40: =U25+U36 -> 1319.8403 | V40: - | W40: =W25+W36 -> 0 | X40: - | Y40: =Y25+Y36 -> 2782.703
A41: ii) Fresh Capital Raising Component (Total) G(ii)+H+I+J | B41: - | C41: =C33+C30+C27+C26 -> 59264.057 | D41: - | E41: =E33+E30+E27+E26 -> 104532.7 | F41: - | G41: 15757.679 | H41: - | I41: 95491.928 | J41: - | K41: =K33+K30+K27+K26 -> 3404.4399 | L41: - | M41: =M33+M30+M27+M26 -> 36515.598 | N41: - | O41: =O33+O30+O27+O26 -> 6011.8069 | P41: - | Q41: =Q33+Q30+Q27+Q26 -> 28111.758 | R41: - | S41: =S33+S30+S27+S26 -> 2946.0219 | T41: - | U41: =U33+U30+U27+U26 -> 9157.2307 | V41: - | W41: =W33+W30+W27+W26 -> 3395.41 | X41: - | Y41: =Y33+Y30+Y27+Y26 -> 21707.342
A42: Bond Market
A43: M. Fund mobilized through Private Placement in Corporate Bond Market (CBM) | B43: 1120 | C43: 664316.13 | D43: 227 | E43: 173440.81 | F43: 413 | G43: 211894.79 | H43: 77 | I43: 38181.959 | J43: 86 | K43: 25739.756 | L43: 15 | M43: 4768.2443 | N43: 112 | O43: 58075.973 | P43: 11 | Q43: 3151.2303 | R43: 105 | S43: 54569.275 | T43: 26 | U43: 9727.8818 | V43: 110 | W43: 73509.788 | X43: 25 | Y43: 20534.603
A44: N. Fund mobilized through public issue in CBM | B44: 45 | C44: 19166.31 | D44: 0 | E44: 0 | F44: 12 | G44: 2715.96 | H44: 0 | I44: 0 | J44: 4 | K44: 686.75 | L44: 0 | M44: 0 | N44: 3 | O44: 1206.96 | P44: 0 | Q44: 0 | R44: 3 | S44: 560.25 | T44: 0 | U44: 0 | V44: 2 | W44: 262 | X44: 0 | Y44: 0
A45: O. Total fund Mobilized in CBM (M+N) | B45: =B43+B44 -> 1165 | C45: =C43+C44 -> 683482.44 | D45: =D43+D44 -> 227 | E45: =E43+E44 -> 173440.81 | F45: 425 | G45: 214610.75 | H45: 77 | I45: 38181.959 | J45: =J43+J44 -> 90 | K45: =K43+K44 -> 26426.506 | L45: =L43+L44 -> 15 | M45: =M43+M44 -> 4768.2443 | N45: =N43+N44 -> 115 | O45: =O43+O44 -> 59282.933 | P45: =P43+P44 -> 11 | Q45: =Q43+Q44 -> 3151.2303 | ... Y45: =Y43+Y44 -> 20534.603
A46: Business trusts
A47: P. Total funds mobilized by REITs | B47: 0 | C47: 0 | D47: 3 | E47: 5905 | F47: 0 | G47: 0 | H47: 1 | I47: 1228 | J47: 0 | K47: 0 | L47: 0 | M47: 0 | N47: 0 | O47: 0 | P47: 0 | Q47: 0 | R47: 0 | S47: 0 | T47: 1 | U47: 1228 | V47: 0 | W47: 0 | X47: 0 | Y47: 0
A48: Q. Total fund mobilized by InvITs | B48: 0 | C48: 0 | D48: 14 | E48: 33118.6 | F48: 0 | G48: 0 | H48: 2 | I48: 1622.5 | J48: 0 | K48: 0 | L48: 0 | M48: 0 | N48: 0 | O48: 0 | P48: 0 | Q48: 0 | T48: 1 | U48: 102.5 | V48: 0 | W48: 0 | X48: 1 | Y48: 1520
A49: R. Total fund mobilized by REITs & InvITs (P+Q) | B49: =SUM(B47:B48) -> 0 | C49: =SUM(C47:C48) -> 0 | D49: =SUM(D47:D48) -> 17 | E49: =SUM(E47:E48) -> 39023.6 | F49: 0 | G49: 0 | H49: 3 | I49: 2850.5 | J49: =SUM(J47:J48) -> 0 | K49: =SUM(K47:K48) -> 0 | L49: =SUM(L47:L48) -> 0 | M49: =SUM(M47:M48) -> 0 | N49: =SUM(N47:N48) -> 0 | O49: =SUM(O47:O48) -> 0 | P49: =SUM(P47:P48) -> 0 | Q49: =SUM(Q47:Q48) -> 0 | ... Y49: =SUM(Y47:Y48) -> 1520
A50: Notes:
A51: 1. Data includes funds raised through public issue, private placement, preferential issue, institutional placement, rights issue
A52: 2. IPOs are classified based on listing date and public debt issues on the basis of closing date of the issue.
A53: 3. The data in Table 5 is segregated into Financial and Non Financial Sector.
A54: 4. Since, some issue have components of both fresh issues as well as OFS, the number of issues with fresh issues and OFS is not given
A55: 5. The amount raised through fresh issues and OFS are obtained by multiplying the respective number of shares issued with the issue price.
A56: Source: SEBI.

Sheet 6
A1: Table 6: Capital Raised from the Primary Market through Public and Rights Issues
A2: Year / Month | B2: Total (Equity+Debt) | D2: Equity | N2: Debt
D3: IPOs (Mainboard) | F3: IPOs (SME issues) | H3: IPOs (Total) | J3: Rights | L3: FPOs | N3: Public issues
B4: No. of issues | C4: Amount ( ₹ crore) | D4: No. of issues | E4: Amount ( ₹ crore) | F4: No. of issues | G4: Amount ( ₹ crore) | H4: No. of issues | I4: Amount ( ₹ crore) | J4: No. of issues | K4: Amount ( ₹ crore) | L4: No. of issues | M4: Amount ( ₹ crore) | N4: No. of issues | O4: Amount ( ₹ crore)
A5: 2023-24 | B5: 385 | C5: 102259.42 | D5: 76 | E5: 61859.847 | F5: 196 | G5: 6095.4649 | H5: 272 | I5: 67955.312 | J5: 67 | K5: 15110.204 | L5: 1 | M5: 27 | N5: 45 | O5: 19166.9
A6: 2024-25# | B6: =SUM(B7:B10) -> 165 | C6: =SUM(C7:C10) -> 52947.409 | D6: =SUM(D7:D10) -> 18 | E6: =SUM(E7:E10) -> 21496.26 | F6: =SUM(F7:F10) -> 86 | G6: =SUM(G7:G10) -> 2945.2718 | H6: =D6+F6 -> 104 | I6: =E6+G6 -> 24441.532 | J6: =SUM(J7:J10) -> 47 | K6: =SUM(K7:K10) -> 7639.927 | L6: =SUM(L7:L10) -> 2 | M6: =SUM(M7:M10) -> 18149.99 | N6: =SUM(N7:N10) -> 12 | O6: =SUM(O7:O10) -> 2715.96
A7: 45383 | B7: =H7+J7+L7+N7 -> 39 | C7: =I7+K7+M7+O7 -> 26057.317 | D7: 3 | E7: 5054.67 | F7: 23 | G7: 672.70852 | H7: =D7+F7 -> 26 | I7: =E7+G7 -> 5727.3785 | J7: 8 | K7: 1643.1883 | L7: 1 | M7: 18000 | N7: 4 | O7: 686.75
A8: 45443 | B8: =H8+J8+L8+N8 -> 41 | C8: =I8+K8+M8+O8 -> 13495.543 | D8: 5 | E8: 9606.1304 | F8: 21 | G8: 527.21852 | H8: =D8+F8 -> 26 | I8: =E8+G8 -> 10133.349 | J8: 12 | K8: 2155.2345 | L8: 0 | M8: 0 | N8: 3 | O8: 1206.96
A9: 45473 | B9: =H9+J9+L9+N9 -> 41 | C9: =I9+K9+M9+O9 -> 4131.448 | D9: 5 | E9: 1957.28 | F9: 17 | G9: 563.338 | H9: =D9+F9 -> 22 | I9: =E9+G9 -> 2520.618 | J9: 16 | K9: 1050.58 | L9: 0 | M9: 0 | N9: 3 | O9: 560.25
A10: 45504 | B10: =H10+J10+L10+N10 -> 44 | C10: =I10+K10+M10+O10 -> 9263.1009 | D10: 5 | E10: 4878.18 | F10: 25 | G10: 1182.0067 | H10: =D10+F10 -> 30 | I10: =E10+G10 -> 6060.1867 | J10: 11 | K10: 2790.9242 | L10: 1 | M10: 149.99 | N10: 2 | O10: 262
A11: Notes:
A12: 1. Equity data on IPO issues are categorised based on the listing date .
A13: 2. Debt issues are classified based on closing date of the issue
A14: ="# indicates as on "&TEXT('1'!$C$2,"mmmm dd, yyyy") -> # indicates as on July 31, 2024
A15: Source: SEBI.

Sheet 7
A1: Table 7: Industry-wise Classification of Capital Raised through Public and Rights Issues (Equity)
A2: Macro Economic Sector | B2: Sector | C2: Industry | D2: 2023-24 | F2: 2024-25 (Till July-24) | H2: 45383 | J2: =EOMONTH(H2,1) -> 45443 | L2: =EOMONTH(J2,1) -> 45473 | N2: =EOMONTH(L2,1) -> 45504
D3: No. of issues | E3: Amount ( ₹ crore) | F3: No. of issues | G3: Amount ( ₹ crore) | H3: No. of issues | I3: Amount ( ₹ crore) | J3: No. of issues | K3: Amount ( ₹ crore) | L3: No. of issues | M3: Amount ( ₹ crore) | N3: No. of issues | O3: Amount ( ₹ crore)
A4: Commodities | B4: Chemicals | C4: Chemicals & Petrochemicals | D4: 7 | E4: 615.83574 | F4: 5 | G4: 209.7716 | H4: 0 | I4: 0 | J4: 2 | K4: 60.4916 | L4: 3 | M4: 149.28 | N4: 0 | O4: 0
C5: Fertilizers & Agrochemicals | D5: 2 | E5: 170.5403 | F5: 1 | G5: 44.676 | H5: 0 | I5: 0 | J5: 0 | K5: 0 | L5: 0 | M5: 0 | N5: 1 | O5: 44.676
B6: Construction Materials | C6: Cement & Cement Products | D6: 2 | E6: 4447.0124 | F6: 1 | G6: 400 | H6: 0 | I6: 0 | J6: 1 | K6: 400 | L6: 0 | M6: 0 | N6: 0 | O6: 0
C7: Other Construction Materials | D7: 1 | E7: 49.98 | F7: 0 | G7: 0 | H7: 0 | I7: 0 | J7: 0 | K7: 0 | L7: 0 | M7: 0 | N7: 0 | O7: 0
B8: Metals & Mining | C8: Ferrous Metals | D8: 1 | E8: 42.69264 | F8: 1 | G8: 170.99999 | H8: 0 | I8: 0 | J8: 0 | K8: 0 | L8: 0 | M8: 0 | N8: 1 | O8: 170.99999
C9: Non - Ferrous Metals | D9: 0 | E9: 0 | F9: 0 | G9: 0 | H9: 0 | I9: 0 | J9: 0 | K9: 0 | L9: 0 | M9: 0 | N9: 0 | O9: 0
C10: Diversified Metals | D10: 0 | E10: 0 | F10: 0 | G10: 0 | H10: 0 | I10: 0 | J10: 0 | K10: 0 | L10: 0 | M10: 0 | N10: 0 | O10: 0
C11: Minerals & Mining | D11: 0 | E11: 0 | F11: 1 | G11: 113.16096 | H11: 0 | I11: 0 | J11: 0 | K11: 0 | L11: 0 | M11: 0 | N11: 1 | O11: 113.16096
C12: Metals & Minerals Trading | D12: 1 | E12: 37.533577 | F12: 0 | G12: 0 | H12: 0 | I12: 0 | J12: 0 | K12: 0 | L12: 0 | M12: 0 | N12: 0 | O12: 0
B13: Forest Materials | C13: Paper, Forest & Jute Products | D13: 2 | E13: 77.48 | F13: 2 | G13: 84.927345 | H13: 0 | I13: 0 | J13: 1 | K13: 45.107345 | L13: 0 | M13: 0 | N13: 1 | O13: 39.82
A14: Consumer Discretionary | B14: Automobile and Auto Components | C14: Automobiles | D14: 1 | E14: 601.55 | F14: 1 | G14: 115.64 | H14: 0 | I14: 0 | J14: 0 | K14: 0 | L14: 0 | M14: 0 | N14: 1 | O14: 115.64
C15: Auto Components | D15: 3 | E15: 914.20792 | F15: 2 | G15: 79.1356 | H15: 1 | I15: 53.89 | J15: 1 | K15: 25.2456 | L15: 0 | M15: 0 | N15: 0 | O15: 0
B16: Consumer Durables | C16: Consumer Durables | D16: 22 | E16: 4644.4649 | F16: 11 | G16: 817.74036 | H16: 5 | I16: 141.13037 | J16: 1 | K16: 15 | L16: 4 | M16: 633.56 | N16: 1 | O16: 28.05
B17: Textiles | C17: Textiles & Apparels | D17: 14 | E17: 279.0674 | F17: 7 | G17: 199.92131 | H17: 1 | I17: 44.741308 | J17: 2 | K17: 28.87 | L17: 3 | M17: 76.39 | N17: 1 | O17: 49.92
B18: Media, Entertainment & Publication | C18: Media | D18: 5 | E18: 555.205 | F18: 1 | G18: 8.4816 | H18: 0 | I18: 0 | J18: 1 | K18: 8.4816 | L18: 0 | M18: 0 | N18: 0 | O18: 0
C19: Entertainment | D19: 6 | E19: 240.97613 | F19: 1 | G19: 14.25152 | H19: 1 | I19: 14.25152 | J19: 0 | K19: 0 | L19: 0 | M19: 0 | N19: 0 | O19: 0
C20: Printing & Publication | D20: 0 | E20: 0 | F20: 1 | G20: 45.9 | H20: 0 | I20: 0 | J20: 0 | K20: 0 | L20: 0 | M20: 0 | N20: 1 | O20: 45.9
B21: Realty | C21: Realty | D21: 6 | E21: 1256.2571 | F21: 2 | G21: 2029.484 | H21: 0 | I21: 0 | J21: 0 | K21: 0 | L21: 0 | M21: 0 | N21: 2 | O21: 2029.484
B22: Consumer Services | C22: Leisure Services | D22: 5 | E22: 4895.93 | F22: 4 | G22: 2316.5109 | H22: 1 | I22: 16.4736 | J22: 1 | K22: 1550.8093 | L22: 2 | M22: 749.228 | N22: 0 | O22: 0
C23: Other Consumer Services | D23: 7 | E23: 215.69184 | F23: 1 | G23: 6.81 | H23: 0 | I23: 0 | J23: 0 | K23: 0 | L23: 1 | M23: 6.81 | N23: 0 | O23: 0
C24: Retailing | D24: 12 | E24: 3584.8556 | F24: 1 | G24: 13.53 | H24: 0 | I24: 0 | J24: 1 | K24: 13.53 | L24: 0 | M24: 0 | N24: 0 | O24: 0
A25: Energy | B25: Oil, Gas & Consumable Fuels | C25: Gas | D25: 2 | E25: 558.4 | F25: 0 | G25: 0 | H25: 0 | I25: 0 | J25: 0 | K25: 0 | L25: 0 | M25: 0 | N25: 0 | O25: 0
C26: Oil | D26: 0 | E26: 0 | F26: 0 | G26: 0 | H26: 0 | I26: 0 | J26: 0 | K26: 0 | L26: 0 | M26: 0 | N26: 0 | O26: 0
C27: Petroleum Products | D27: 2 | E27: 520.93 | F27: 1 | G27: 6.3 | H27: 1 | I27: 6.3 | J27: 0 | K27: 0 | L27: 0 | M27: 0 | N27: 0 | O27: 0
C28: Consumable Fuels | D28: 0 | E28: 0 | F28: 0 | G28: 0 | H28: 0 | I28: 0 | J28: 0 | K28: 0 | L28: 0 | M28: 0 | N28: 0 | O28: 0
A29: Fast Moving Consumer Goods | B29: Fast Moving Consumer Goods | C29: Agricultural Food & other Products | D29: 8 | E29: 324.42033 | F29: 8 | G29: 778.04512 | H29: 2 | I29: 76.0656 | J29: 2 | K29: 54.7 | L29: 2 | M29: 86.12952 | N29: 2 | O29: 561.15
C30: Beverages | D30: 1 | E30: 48.9433 | F30: 2 | G30: 1521.78 | H30: 1 | I30: 21.78 | J30: 0 | K30: 0 | L30: 0 | M30: 0 | N30: 1 | O30: 1500
C31: Cigarettes & Tobacco Products | D31: 1 | E31: 16.07 | F31: 0 | G31: 0 | H31: 0 | I31: 0 | J31: 0 | K31: 0 | L31: 0 | M31: 0 | N31: 0 | O31: 0
C32: Food Products | D32: 13 | E32: 1596.7931 | F32: 7 | G32: 166.284 | H32: 2 | I32: 32.1 | J32: 2 | K32: 44.324 | L32: 2 | M32: 77.14 | N32: 1 | O32: 12.72
C33: Personal Products | D33: 1 | E33: 1701.44 | F33: 1 | G33: 19.464 | H33: 0 | I33: 0 | J33: 0 | K33: 0 | L33: 0 | M33: 0 | N33: 1 | O33: 19.464
C34: Household Products | D34: 2 | E34: 1793 | F34: 1 | G34: 24.54 | H34: 0 | I34: 0 | J34: 0 | K34: 0 | L34: 0 | M34: 0 | N34: 1 | O34: 24.54
C35: Diversified FMCG | D35: 0 | E35: 0 | F35: 0 | G35: 0 | H35: 0 | I35: 0 | J35: 0 | K35: 0 | L35: 0 | M35: 0 | N35: 0 | O35: 0
A36: Financial Services | B36: Financial Services | C36: Finance | D36: 12 | E36: 12826.93 | F36: 11 | G36: 4710.9324 | H36: 1 | I36: 33.13 | J36: 2 | K36: 4271.8281 | L36: 4 | M36: 255.05 | N36: 4 | O36: 150.92432
C37: Banks | D37: 4 | E37: 2057.21 | F37: 1 | G37: 1151 | H37: 1 | I37: 1151 | J37: 0 | K37: 0 | L37: 0 | M37: 0 | N37: 0 | O37: 0
C38: Capital Markets | D38: 4 | E38: 914.39506 | F38: 0 | G38: 0 | H38: 0 | I38: 0 | J38: 0 | K38: 0 | L38: 0 | M38: 0 | N38: 0 | O38: 0
C39: Insurance | D39: 1 | E39: 1171.58 | F39: 1 | G39: 2614.6459 | H39: 0 | I39: 0 | J39: 1 | K39: 2614.6459 | L39: 0 | M39: 0 | N39: 0 | O39: 0
C40: Financial Technology (Fintech) | D40: 1 | E40: 49.96544 | F40: 0 | G40: 0 | H40: 0 | I40: 0 | J40: 0 | K40: 0 | L40: 0 | M40: 0 | N40: 0 | O40: 0
A41: Healthcare | B41: Healthcare | C41: Pharmaceuticals & Biotechnology | D41: 18 | E41: 8849.0514 | F41: 5 | G41: 2467.7511 | H41: 1 | I41: 12.07 | J41: 1 | K41: 43.16112 | L41: 2 | M41: 460.49 | N41: 1 | O41: 1952.03
C42: Healthcare Equipment & Supplies | D42: 3 | E42: 88.7672 | F42: 1 | G42: 12.6 | H42: 0 | I42: 0 | J42: 1 | K42: 12.6 | L42: 0 | M42: 0 | N42: 0 | O42: 0
C43: Healthcare Services | D43: 10 | E43: 2250.5 | F43: 2 | G43: 1883.006 | H43: 0 | I43: 0 | J43: 1 | K43: 1841.75 | L43: 0 | M43: 0 | N43: 1 | O43: 41.256
A44: Industrials | B44: Construction | C44: Construction | D44: 12 | E44: 770.89712 | F44: 9 | G44: 981.56148 | H44: 4 | I44: 565.13648 | J44: 1 | K44: 23.364 | L44: 0 | M44: 0 | N44: 4 | O44: 393.061
B45: Capital Goods | C45: Aerospace & Defense | D45: 2 | E45: 653.04 | F45: 0 | G45: 0 | H45: 0 | I45: 0 | J45: 0 | K45: 0 | L45: 0 | M45: 0 | N45: 0 | O45: 0
C46: Agricultural, Commercial & Construction Vehicles | D46: 0 | E46: 0 | F46: 1 | G46: 49.07 | H46: 0 | I46: 0 | J46: 0 | K46: 0 | L46: 1 | M46: 49.07 | N46: 0 | O46: 0
C47: Electrical Equipment | D47: 16 | E47: 3342.4781 | F47: 4 | G47: 322.26547 | H47: 0 | I47: 0 | J47: 1 | K47: 174.63107 | L47: 1 | M47: 30.7944 | N47: 2 | O47: 116.84
C48: Industrial Manufacturing | D48: 13 | E48: 2010.2532 | F48: 10 | G48: 1351.0497 | H48: 3 | I48: 666.32 | J48: 2 | K48: 51.0916 | L48: 2 | M48: 505.02728 | N48: 3 | O48: 128.61085
C49: Industrial Products | D49: 43 | E49: 6129.4286 | F49: 12 | G49: 1095.1606 | H49: 3 | I49: 134.092 | J49: 3 | K49: 59.558 | L49: 2 | M49: 100.356 | N49: 4 | O49: 801.15459
A50: Information Technology | B50: Information Technology | C50: IT - Software | D50: 10 | E50: 302.713 | F50: 2 | G50: 93.44196 | H50: 2 | I50: 93.44196 | J50: 0 | K50: 0 | L50: 0 | M50: 0 | N50: 0 | O50: 0
C51: IT - Services | D51: 15 | E51: 4756.0069 | F51: 3 | G51: 82.62 | H51: 0 | I51: 0 | J51: 1 | K51: 49.4 | L51: 2 | M51: 33.22 | N51: 0 | O51: 0
C52: IT - Hardware | D52: 5 | E52: 1311.634 | F52: 2 | G52: 35.18 | H52: 0 | I52: 0 | J52: 2 | K52: 35.18 | L52: 0 | M52: 0 | N52: 0 | O52: 0
A53: Services | B53: Services | C53: Engineering Services | D53: 0 | E53: 0 | F53: 0 | G53: 0 | H53: 0 | I53: 0 | J53: 0 | K53: 0 | L53: 0 | M53: 0 | N53: 0 | O53: 0
C54: Transport Services | D54: 13 | E54: 1336.111 | F54: 3 | G54: 142.2458 | H54: 1 | I54: 5.6 | J54: 2 | K54: 136.6458 | L54: 0 | M54: 0 | N54: 0 | O54: 0
C55: Transport Infrastructure | D55: 1 | E55: 2800 | F55: 1 | G55: 28 | H55: 0 | I55: 0 | J55: 1 | K55: 28 | L55: 0 | M55: 0 | N55: 0 | O55: 0
C56: Commercial Services & Supplies | D56: 19 | E56: 1437.8788 | F56: 13 | G56: 1096.9083 | H56: 2 | I56: 28.044 | J56: 4 | K56: 700.16847 | L56: 4 | M56: 269.4696 | N56: 3 | O56: 99.22619
C57: Public Services | D57: 0 | E57: 0 | F57: 0 | G57: 0 | H57: 0 | I57: 0 | J57: 0 | K57: 0 | L57: 0 | M57: 0 | N57: 0 | O57: 0
A58: Telecommunication | B58: Telecommunication | C58: Telecom - Services | D58: 4 | E58: 134.93 | F58: 4 | G58: 22724.99 | H58: 2 | I58: 22275 | J58: 0 | K58: 0 | L58: 0 | M58: 0 | N58: 2 | O58: 449.99
C59: Telecom - Equipment & Accessories | D59: 0 | E59: 0 | F59: 0 | G59: 0 | H59: 0 | I59: 0 | J59: 0 | K59: 0 | L59: 0 | M59: 0 | N59: 0 | O59: 0
A60: Utilities | B60: Power | C60: Power | D60: 3 | E60: 273.99879 | F60: 0 | G60: 0 | H60: 0 | I60: 0 | J60: 0 | K60: 0 | L60: 0 | M60: 0 | N60: 0 | O60: 0
B61: Utilities | C61: Other Utilities | D61: 4 | E61: 435.47 | F61: 4 | G61: 194.70616 | H61: 0 | I61: 0 | J61: 0 | K61: 0 | L61: 2 | M61: 82.2232 | N61: 2 | O61: 112.48296
A62: Diversified | B62: Diversified | C62: Diversified | D62: 0 | E62: 0 | F62: 1 | G62: 6.96 | H62: 0 | I62: 0 | J62: 0 | K62: 0 | L62: 1 | M62: 6.96 | N62: 0 | O62: 0
C63: Total | D63: =SUM(D4:D62) -> 340 | E63: =SUM(E4:E62) -> 83092.516 | F63: 153 | G63: 50231.449 | H63: =SUM(H4:H62) -> 35 | I63: =SUM(I4:I62) -> 25370.567 | J63: =SUM(J4:J62) -> 38 | K63: =SUM(K4:K62) -> 12288.583 | L63: =SUM(L4:L62) -> 38 | M63: =SUM(M4:M62) -> 3571.198 | N63: 42 | O63: 9001.1009
A65: Note: The industrial classification is based on SEBI 4 tier industry classification
A66: Source: SEBI

Sheet 8
A1: Table 8: Sector-wise and Region-wise Distribution of Capital Mobilised through Public and Rights Issues (Equity)
A2: Year / Month | B2: Total | D2: Sector-wise | H2: Region-wise
D3: Private | F3: Public | H3: Northern | J3: Eastern | L3: Western | N3: Southern | P3: Central
B4: No. of issues | C4: Amount ( ₹ crore) | D4: No. of issues | E4: Amount ( ₹ crore) | F4: No. of issues | G4: Amount ( ₹ crore) | H4: No. of issues | I4: Amount ( ₹ crore) | J4: No. of issues | K4: Amount ( ₹ crore) | L4: No. of issues | M4: Amount ( ₹ crore) | N4: No. of issues | O4: Amount ( ₹ crore) | P4: No. of issues | Q4: Amount ( ₹ crore)
A5: 2023-24 | B5: 340 | C5: 83091.976 | D5: 337 | E5: 80426.092 | F5: 2 | G5: 2639.41 | H5: 72 | I5: 32405.594 | J5: 16 | K5: 2306.4181 | L5: 195 | M5: 37193.108 | N5: 50 | O5: 10340.569 | P5: 7 | Q5: 846.28728
A6: 2024-25# | B6: =SUM(H6,J6,L6,N6,P6) -> 153 | C6: =SUM(I6,K6,M6,O6,Q6) -> 50231.449 | D6: =SUM(D7:D10) -> 153 | E6: =SUM(E7:E10) -> 50231.348 | F6: =SUM(F7:F10) -> 0 | G6: =SUM(G7:G10) -> 0 | H6: =SUM(H7:H10) -> 35 | I6: =SUM(I7:I10) -> 9782.3164 | J6: =SUM(J7:J10) -> 10 | K6: =SUM(K7:K10) -> 714.31996 | ... Q6: =SUM(Q7:Q10) -> 327.14495
A7: 45383 | B7: =SUM(H7,J7,L7,N7,P7) -> 35 | C7: =SUM(I7,K7,M7,O7,Q7) -> 25370.567 | D7: 35 | E7: 25370.567 | F7: 0 | G7: 0 | H7: 10 | I7: 4644.9489 | L7: 22 | M7: 19527.236 | N7: 3 | O7: 1198.3815
A8: =EOMONTH(A7,1) -> 45443 | B8: =SUM(H8,J8,L8,N8,P8) -> 38 | C8: =SUM(I8,K8,M8,O8,Q8) -> 12288.583 | D8: 38 | E8: 12288.583 | F8: 0 | G8: 0 | H8: 6 | I8: 2234.415 | J8: 3 | K8: 426.588 | L8: 22 | M8: 4558.1944 | N8: 6 | O8: 5026.225 | P8: 1 | Q8: 43.16112
A9: =EOMONTH(A8,1) -> 45473 | B9: =SUM(H9,J9,L9,N9,P9) -> 38 | C9: =SUM(I9,K9,M9,O9,Q9) -> 3571.198 | D9: 38 | E9: 3571.198 | F9: 0 | G9: 0 | H9: 7 | I9: 1299.5532 | J9: 3 | K9: 87.91 | L9: 25 | M9: 1581.0904 | N9: 2 | O9: 571.85 | P9: 1 | Q9: 30.7944
A10: =EOMONTH(A9,1) -> 45504 | B10: =SUM(H10,J10,L10,N10,P10) -> 42 | C10: =SUM(I10,K10,M10,O10,Q10) -> 9001.1009 | D10: 42 | E10: 9001 | F10: 0 | G10: 0 | H10: 12 | I10: 1603.3993 | J10: 4 | K10: 199.82196 | L10: 19 | M10: 4648.3602 | N10: 4 | O10: 2296.33 | P10: 3 | Q10: 253.18943
A11: Notes - From April 2020 onwards, data on IPO issues are categorised based on the listing date .
A12: ="# indicates as on "&TEXT('1'!$C$2,"mmmm dd, yyyy") -> # indicates as on July 31, 2024
A13: Source: SEBI.

Sheet 9
A1: Table 9: Size-wise Classification of Capital Raised through Public and Rights Issues (Equity)
A2: Year / Month | B2: Total | D2: < 5 crore | F2: ≥ 5crore - < 10crore | H2: ≥ 10 crore - < 50 crore | J2: ≥ 50 crore - < 100 crore | L2: ≥ 100 crore -<500 crore | N2: >=₹500 crore
B3: No. of issues | C3: Amount ( ₹ crore) | D3: No. of issues | E3: Amount ( ₹ crore) | F3: No. of issues | G3: Amount ( ₹ crore) | H3: No. of issues | I3: Amount ( ₹ crore) | J3: No. of issues | K3: Amount ( ₹ crore) | L3: No. of issues | M3: Amount ( ₹ crore) | N3: No. of issues | O3: Amount ( ₹ crore)
A4: 2023-24 | B4: 340 | C4: 83091.976 | D4: 3 | E4: 9.462 | F4: 28 | G4: 218.70822 | H4: 187 | I4: 5420.5137 | J4: 38 | K4: 2473.5783 | L4: 29 | M4: 8297.8354 | N4: 55 | O4: 66671.879
A5: 2024-25# | B5: =SUM(B6:B9) -> 153 | C5: =SUM(C6:C9) -> 50231.449 | D5: =SUM(D6:D9) -> 2 | E5: =SUM(E6:E9) -> 8.35 | F5: =SUM(F6:F9) -> 14 | G5: =SUM(G6:G9) -> 102.5336 | H5: =SUM(H6:H9) -> 89 | I5: =SUM(I6:I9) -> 2664.6198 | ... O5: =SUM(O6:O9) -> 42936.749
A6: 45383 | B6: =D6+F6+H6+J6+L6+N6 -> 35 | C6: =E6+G6+I6+K6+M6+O6 -> 25370.567 | D6: 1 | E6: 4.76 | F6: 3 | G6: 21.8 | H6: 20 | I6: 513.18407 | J6: 5 | K6: 275.15276 | L6: 2 | M6: 480.2 | N6: 4 | O6: 24075.47
A7: =EOMONTH(A6,1) -> 45443 | B7: =D7+F7+H7+J7+L7+N7 -> 38 | C7: =E7+G7+I7+K7+M7+O7 -> 12288.583 | D7: 0 | E7: 0 | F7: 4 | G7: 30.3656 | H7: 25 | I7: 709.34326 | J7: 1 | K7: 96.285 | L7: 2 | M7: 574.63107 | N7: 6 | O7: 10877.959
A8: =EOMONTH(A7,1) -> 45473 | B8: =D8+F8+H8+J8+L8+N8 -> 38 | C8: =E8+G8+I8+K8+M8+O8 -> 3571.198 | D8: 1 | E8: 3.59 | F8: 6 | G8: 41.368 | H8: 22 | I8: 736.90672 | J8: 2 | K8: 182.27328 | L8: 5 | M8: 1329.94 | N8: 2 | O8: 1277.12
A9: =EOMONTH(A8,1) -> 45504 | B9: =D9+F9+H9+J9+L9+N9 -> 42 | C9: =E9+G9+I9+K9+M9+O9 -> 9001.1009 | D9: 0 | E9: 0 | F9: 1 | G9: 9 | H9: 22 | I9: 705.18572 | J9: 7 | K9: 405.7052 | L9: 7 | M9: 1175.0099 | N9: 5 | O9: 6706.2
A10: Notes - From April 2020 onwards, data on IPO issues are categorised based on the listing date .
A11: ="# indicates as on "&TEXT('1'!$C$2,"mmmm dd, yyyy") -> # indicates as on July 31, 2024
A12: Source: SEBI.

Sheet 10
A1: Table 10: Capital Raised by Listed Companies from the Primary Market through QIPs
A2: Year / Month | B2: Only BSE | D2: Only NSE | F2: Only MSEI | H2: Common | J2: Total
B3: No. of issues | C3: Amount ( ₹ crore) | D3: No. of issues | E3: Amount ( ₹ crore) | F3: No. of issues | G3: Amount ( ₹ crore) | H3: No. of issues | I3: Amount ( ₹ crore) | J3: No. of issues | K3: Amount ( ₹ crore)
A4: 2023-24 | B4: 0 | C4: 0 | D4: 3 | E4: 266.53776 | F4: 0 | G4: 0 | H4: 58 | I4: 68704.954 | J4: 61 | K4: 68971.491
A5: 2024-25# | B5: =SUM(B6:B9) -> 0 | C5: =SUM(C6:C9) -> 0 | D5: =SUM(D6:D9) -> 1 | E5: =SUM(E6:E9) -> 24.84 | F5: =SUM(F6:F9) -> 0 | G5: =SUM(G6:G9) -> 0 | H5: =SUM(H6:H9) -> 29 | I5: =SUM(I6:I9) -> 30960.832 | ... K5: =SUM(K6:K9) -> 30985.672
A6: 45383 | B6: 0 | C6: 0 | D6: 0 | E6: 0 | F6: 0 | G6: 0 | H6: 11 | I6: 11471.733 | J6: =SUM(B6,D6,F6,H6) -> 11 | K6: =SUM(C6,E6,G6,I6) -> 11471.733
A7: =EOMONTH(A6,1) -> 45443 | B7: 0 | C7: 0 | D7: 0 | E7: 0 | F7: 0 | G7: 0 | H7: 2 | I7: 3039.9999 | J7: =SUM(B7,D7,F7,H7) -> 2 | K7: =SUM(C7,E7,G7,I7) -> 3039.9999
A8: =EOMONTH(A7,1) -> 45473 | B8: 0 | C8: 0 | D8: 1 | E8: 24.84 | F8: 0 | G8: 0 | H8: 5 | I8: 2749.9996 | J8: =SUM(B8,D8,F8,H8) -> 6 | K8: =SUM(C8,E8,G8,I8) -> 2774.8396
A9: =EOMONTH(A8,1) -> 45504 | B9: 0 | C9: 0 | D9: 0 | E9: 0 | F9: 0 | G9: 0 | H9: 11 | I9: 13699.1 | J9: =SUM(B9,D9,F9,H9) -> 11 | K9: =SUM(C9,E9,G9,I9) -> 13699.1
A10: Notes: 1. The above data includes both "no. of issues" and "Amount" raised on conversion of convertible securities issued on QIP basis.
A11: ="# indicates as on "&TEXT('1'!$C$2,"mmmm dd, yyyy") -> # indicates as on July 31, 2024
A12: Source: BSE, NSE and MSEI.

Sheet 11
A1: Table 11: Preferential Allotments Listed at BSE, NSE and MSEI
A2: Year/Month | B2: Only BSE | D2: Only NSE | F2: Only MSEI | H2: Common# | J2: Total
B3: No. of issues | C3: Amount ( ₹ crore) | D3: No. of issues | E3: Amount ( ₹ crore) | F3: No. of issues | G3: Amount ( ₹ crore) | H3: No. of issues | I3: Amount ( ₹ crore) | J3: No. of issues | K3: Amount ( ₹ crore)
A4: 2023-24 | B4: 354 | C4: 10393.32 | D4: 73 | E4: 1010.7464 | F4: 5 | G4: 41.44 | H4: 257 | I4: 33709.596 | J4: 689 | K4: 45155.102
A5: 2024-25# | B5: =SUM(B6:B9) -> 165 | C5: =SUM(C6:C9) -> 3538.91 | D5: =SUM(D6:D9) -> 58 | E5: =SUM(E6:E9) -> 698.09301 | F5: =SUM(F6:F9) -> 1 | G5: =SUM(G6:G9) -> 5.02 | H5: =SUM(H6:H9) -> 121 | I5: =SUM(I6:I9) -> 39772.764 | ... K5: =SUM(K6:K9) -> 44014.787
A6: 45383 | B6: 51 | C6: 1387.31 | D6: 13 | E6: 206.12993 | F6: 1 | G6: 5.02 | H6: 42 | I6: 6103.73 | J6: =B6+D6+F6+H6 -> 107 | K6: =C6+E6+G6+I6 -> 7702.1899
A7: =EOMONTH(A6,1) -> 45443 | B7: 56 | C7: 839.5 | D7: 20 | E7: 185.11948 | F7: 0 | G7: 0 | H7: 38 | I7: 23968.574 | J7: =B7+D7+F7+H7 -> 114 | K7: =C7+E7+G7+I7 -> 24993.193
A8: =EOMONTH(A7,1) -> 45473 | B8: 26 | C8: 822.4 | D8: 13 | E8: 187.0436 | F8: 0 | G8: 0 | H8: 22 | I8: 5985.75 | J8: =B8+D8+F8+H8 -> 61 | K8: =C8+E8+G8+I8 -> 6995.1936
A9: =EOMONTH(A8,1) -> 45504 | B9: 32 | C9: 489.7 | D9: 12 | E9: 119.8 | F9: 0 | G9: 0 | H9: 19 | I9: 3714.71 | J9: =B9+D9+F9+H9 -> 63 | K9: =C9+E9+G9+I9 -> 4324.21
A10: #Listed at any two or three exchanges.
A11: ="# indicates as on "&TEXT('1'!$C$2,"mmmm dd, yyyy") -> # indicates as on July 31, 2024
A12: Source: BSE, NSE and MSEI.

Sheet 12
A1: Table 12: Private Placement of Corporate Debt listed at BSE and NSE
A2: Year/Month | B2: Only NSE | D2: Only BSE | F2: Both NSE and BSE | H2: Total
B3: No. of issues | C3: Amount ( ₹ crore) | D3: No. of issues | E3: Amount ( ₹ crore) | F3: No. of issues | G3: Amount ( ₹ crore) | H3: No. of issues | I3: Amount ( ₹ crore)
A4: 2023-24 | B4: 288 | C4: 255227.82 | D4: 945 | E4: 297407.27 | F4: 114 | G4: 285120.45 | H4: 1347 | I4: 837755.55
A5: 2024-25# | B5: =SUM(B6:B9) -> 93 | C5: =SUM(C6:C9) -> 80767.334 | D5: =SUM(D6:D9) -> 355 | E5: =SUM(E6:E9) -> 96382.75 | F5: =SUM(F6:F9) -> 42 | G5: =SUM(G6:G9) -> 72924.671 | H5: =SUM(H6:H9) -> 490 | I5: =SUM(I6:I9) -> 250074.75
A6: 45383 | B6: 11 | C6: 9221.6 | D6: 83 | E6: 14558 | F6: 7 | G6: 6728 | H6: =SUM(B6,D6,F6) -> 101 | I6: =SUM(C6,E6,G6) -> 30507.6
A7: =EOMONTH(A6,1) -> 45443 | B7: 25 | C7: 20114 | D7: 89 | E7: 30261 | F7: 9 | G7: 10852 | H7: 123 | I7: 61227
A8: =EOMONTH(A7,1) -> 45473 | B8: 27 | C8: 18962.734 | D8: 95 | E8: 22087.75 | F8: 9 | G8: 23246.671 | H8: =SUM(B8,D8,F8) -> 131 | I8: =SUM(C8,E8,G8) -> 64297.155
A9: =EOMONTH(A8,1) -> 45504 | B9: 30 | C9: 32469 | D9: 88 | E9: 29476 | F9: 17 | G9: 32098 | H9: =SUM(B9,D9,F9) -> 135 | I9: =SUM(C9,E9,G9) -> 94043
A10: ="# indicates as on "&TEXT('1'!$C$2,"mmmm dd, yyyy") -> # indicates as on July 31, 2024
A11: Source: BSE and NSE

Sheet 13(Old)
A1: Table 13: Trends in Settled Trades in the Corporate Debt Market
A2: Year / Month | B2: ICCL | D2: NSCCL | F2: MSE Clearing | H2: Total
B3: No. of Trades | C3: Value (₹ crore) | D3: No. of Trades | E3: Value (₹ crore) | F3: No. of Trades | G3: Value (₹ crore) | H3: No. of Trades | I3: Value (₹ crore)
A4: 2023-24 | B4: 129879 | C4: 204122.94 | D4: 83338 | E4: 1113679.3 | F4: 0 | G4: 0 | H4: 213217 | I4: 1317802.3
A5: 2024-25# | B5: =SUM(B6:B9) -> 46686 | C5: =SUM(C6:C9) -> 130624.89 | D5: =SUM(D6:D9) -> 48725 | E5: =SUM(E6:E9) -> 338280.2 | F5: =SUM(F6:F9) -> 0 | G5: =SUM(G6:G9) -> 0 | H5: =SUM(H6:H9) -> 95411 | I5: =SUM(I6:I9) -> 468905.09
A6: 45383 | B6: 12695 | C6: 81929.179 | D6: 10338 | E6: 12366.45 | F6: 0 | G6: 0 | H6: =SUM(B6+D6+F6) -> 23033 | I6: =SUM(C6+E6+G6) -> 94295.629
A7: 45413 | B7: 11147 | C7: 16078.74 | D7: 12473 | E7: 107641 | F7: 0 | G7: 0 | H7: =SUM(B7+D7+F7) -> 23620 | I7: =SUM(C7+E7+G7) -> 123719.74
A8: 45444 | B8: 10097 | C8: 16453.703 | D8: 12153 | E8: 97991.476 | F8: 0 | G8: 0 | H8: 22250 | I8: 114445.18
A9: 45474 | B9: 12747 | C9: 16163.268 | D9: 13761 | E9: 120281.27 | F9: 0 | G9: 0 | H9: =SUM(B9,D9) -> 26508 | I9: =SUM(C9,E9) -> 136444.54
A11: This table has been revised to include only settled trades (OTC+RFQ trades) through exchange platform.
A12: ="# indicates as on "&TEXT('1'!$C$2,"mmmm dd, yyyy") -> # indicates as on July 31, 2024
A13: Source: ICCL, NSCCL and MSE Clearing.

Sheet 13 
A1: Table 13: Trends in Settled Trades in the Corporate Debt Market
A2: Year / Month | B2: BSE/ICCL [Trades executed on OTC+RFQ+anonymous platforms and settled through ICCL] | F2: NSE/NSCCL [Trades executed on OTC+RFQ+anonymous platforms and settled through NSCCL] | J2: MCX-SX/MSE Clearing | L2: Off Market Settled Trades | P2: Total Trades Settled
B3: Listed Corporate Bonds | D3: Unlisted Corporate Bonds | F3: Listed Corporate Bonds | H3: Unlisted Corporate Bonds | L3: Listed Corporate Bonds | N3: Unlisted Corporate Bonds
B4: No. of Trades Settled | C4: Amount (₹ crore) | D4: No. of Trades Settled | E4: Amount (₹ crore) | F4: No. of Trades Settled | G4: Amount (₹ crore) | H4: No. of Trades Settled | I4: Amount (₹ crore) | J4: No. of Trades Settled | K4: Amount (₹ crore) | L4: No. of Trades Settled | M4: Amount (₹ crore) | N4: No. of Trades Settled | O4: Amount (₹ crore) | P4: No. of Trades Settled | Q4: Amount (₹ crore)
A5: 2023-24 | B5: 339906 | C5: 140568.51 | D5: 22123 | E5: 66811.26 | F5: 751149 | G5: 1078970.8 | H5: 10683 | I5: 39274.17 | J5: 0 | K5: 0 | L5: 132578 | M5: 18900.33 | N5: 34998 | O5: 28868.97 | P5: 1291437 | Q5: 1373394
A6: 2024-25# | B6: =SUM(B7:B10) -> 105807 | C6: =SUM(C7:C10) -> 38701.545 | D6: =SUM(D7:D10) -> 7992 | E6: =SUM(E7:E10) -> 23637.759 | F6: =SUM(F7:F10) -> 243625 | G6: =SUM(G7:G10) -> 393355.68 | H6: =SUM(H7:H10) -> 2188 | I6: =SUM(I7:I10) -> 16584.408 | ... Q6: =SUM(Q7:Q10) -> 487972.69
A7: 45383 | B7: 25903 | C7: 7415.307 | D7: 1977 | E7: 5249.342 | F7: 64127 | G7: 78200.87 | H7: 610 | I7: 4241.988 | J7: 0 | K7: 0 | L7: 2555 | M7: 1011.408 | N7: 2836 | O7: 2708.523 | P7: 98008 | Q7: 98827.44
A8: 45413 | B8: 27094 | C8: 10486.48 | D8: 2124 | E8: 5852.266 | F8: 61350 | G8: 101645.8 | H8: 582 | I8: 6548.765 | J8: 0 | K8: 0 | L8: 2280 | M8: 915.9349 | N8: 2479 | O8: 4802.771 | P8: 95909 | Q8: 130252
A9: 45444 | B9: 24202 | C9: 11080.92 | D9: 1708 | E9: 5762.829 | F9: 54517 | G9: 95480.17 | H9: 474 | I9: 3057.867 | J9: 0 | K9: 0 | L9: 1669 | M9: 733.383 | N9: 2562 | O9: 2355.499 | P9: 85132 | Q9: 118470.7
A10: 45474 | B10: 28608 | C10: 9718.8383 | D10: 2183 | E10: 6773.3219 | F10: 63631 | G10: 118028.84 | H10: 522 | I10: 2735.7883 | J10: 0 | K10: 0 | L10: 1949 | M10: 940.16476 | N10: 3130 | O10: 2225.5903 | P10: 100023 | Q10: 140422.55
A11: # indicates as on July 31, 2024
A12: Source: ICCL, NSCCL, MSE Clearing, NSDL and CDSL.

Sheet 14
A1: Table 14: Ratings Assigned for Long-term Corporate Debt Securities (Maturity ≥ 1 year)
A2: Grade | B2: Investment Grade | J2: Non-Investment Grade | L2: Total
B3: Highest Safety (AAA) | D3: High Safety (AA) | F3: Adequate Safety (A) | H3: Moderate Safety (BBB)
A4: Period | B4: No. of issues | C4: Amount ( ₹ crore) | D4: No. of issues | E4: Amount ( ₹ crore) | F4: No. of issues | G4: Amount ( ₹ crore) | H4: No. of issues | I4: Amount ( ₹ crore) | J4: No. of issues | K4: Amount ( ₹ crore) | L4: No. of issues | M4: Amount ( ₹ crore)
A5: 2022-23 | B5: 266 | C5: 2019875.8 | D5: 409 | E5: 372534.52 | F5: 372 | G5: 61654.9 | H5: 200 | I5: 18194.87 | J5: 72 | K5: 17535.12 | L5: 1319 | M5: 2489794.7
A6: 2023-24$ | B6: =SUM(B7:B10) -> 127 | C6: =SUM(C7:C10) -> 1269289.9 | D6: =SUM(D7:D10) -> 165 | E6: =SUM(E7:E10) -> 153963.38 | F6: =SUM(F7:F10) -> 129 | G6: =SUM(G7:G10) -> 20557.36 | H6: =SUM(H7:H10) -> 62 | I6: =SUM(I7:I10) -> 20601.65 | ... M6: =SUM(M7:M10) -> 1470285.3
A7: Apr-23 | B7: 16 | C7: 96343.84 | D7: 21 | E7: 8364.25 | F7: 25 | G7: 920.49 | H7: 10 | I7: 1702.58 | J7: 3 | K7: 554 | L7: 75 | M7: 107885.16
A8: May-23 | B8: 29 | C8: 188112.1 | D8: 44 | E8: 27924.79 | F8: 20 | G8: 2802.42 | H8: 24 | I8: 1864.45 | J8: 10 | K8: 4900 | L8: 127 | M8: 225603.76
A9: Jun-23 | B9: 40 | C9: 292428.78 | D9: 64 | E9: 71403.79 | F9: 50 | G9: 9645.95 | H9: 19 | I9: 16207.8 | J9: 2 | K9: 275 | L9: 175 | M9: 389961.32
A10: Jul-23 | B10: 42 | C10: 692405.2 | D10: 36 | E10: 46270.55 | F10: 34 | G10: 7188.5 | H10: 9 | I10: 826.82 | J10: 4 | K10: 144 | L10: 125 | M10: 746835.07
A11: $ indicates upto July 31, 2023
A12: This data is provisonal
A13: Note: Data in the table may include ratings of a single company from multiple credit rating agencies across rating categories.
A14: Source: Credit Rating Agencies.

Sheet 15
A1: Table 15: Review of Accepted Ratings of Corporate Debt Securities (Maturity ≥ 1 year)
A2: Grade | B2: Upgraded | D2: Downgraded | F2: Reaffirmed | H2: Rating Watch | J2: Withdrawn/ Suspended
A3: Period | B3: No. of issues | C3: Amount ( ₹ crore) | D3: No. of issues | E3: Amount ( ₹ crore) | F3: No. of issues | G3: Amount ( ₹ crore) | H3: No. of issues | I3: Amount ( ₹ crore) | J3: No. of issues | K3: Amount ( ₹ crore)
A4: 2022-23 | B4: 460 | C4: 269687.23 | D4: 251 | E4: 107880.65 | F4: 7153 | G4: 18110493 | H4: 135 | I4: 34838.31 | J4: 1041 | K4: 454662.93
A5: 2023-24$ | B5: =SUM(B6:B9) -> 266 | C5: =SUM(C6:C9) -> 120177.51 | D5: =SUM(D6:D9) -> 70 | E5: =SUM(E6:E9) -> 24472.11 | F5: =SUM(F6:F9) -> 2671 | G5: =SUM(G6:G9) -> 8792511.6 | H5: =SUM(H6:H9) -> 58 | I5: =SUM(I6:I9) -> 18517.46 | J5: =SUM(J6:J9) -> 465 | K5: 846860.18
A6: Apr-23 | B6: 17 | C6: 6525.88 | D6: 16 | E6: 4839.68 | F6: 563 | G6: 1938191.2 | H6: 36 | I6: 13100 | J6: 77 | K6: 48942.77
A7: May-23 | B7: 101 | C7: 67452.92 | D7: 21 | E7: 8500.23 | F7: 584 | G7: 2215716.1 | H7: 12 | I7: 2298 | J7: 96 | K7: 41223.2
A8: Jun-23 | B8: 113 | C8: 30889.09 | D8: 12 | E8: 3333 | F8: 878 | G8: 2381727.5 | H8: 3 | I8: 850 | J8: 150 | K8: 65287.715
A9: Jul-23 | B9: 35 | C9: 15309.62 | D9: 21 | E9: 7799.2 | F9: 646 | G9: 2256876.7 | H9: 7 | I9: 2269.46 | J9: 142 | K9: 691406.49#
A10: $ indicates upto July 31, 2023
A11: This data is provisonal
A12: # The increase in the amount for rated quantum for withdrawals from previous trends is due to merger of Housing Development Finance Corporation Limited (HDFC) and HDFC Bank Limited (HDFC Bank) where the instruments of HDFC were withdrawn post-merger and the same were transferred to HDFC Bank.
A13: Note: Data in the table may include ratings of a single company from multiple credit rating agencies across rating categories.
A14: Source: Credit Rating Agencies.

Sheet 16
A1: Table 16: Distribution of Turnover on Cash Segments of Stock Exchanges (`crore)
A2: Stock Exchanges | B2: 2023-24 | C2: 2024-25$ | D2: July-24
A3: BSE | B3: 1629038.3 | C3: 784509.36 | D3: 235148.12
A4: MSEI | B4: 29.33808 | C4: 2.0832373 | D4: 0.51822155
A5: NSE | B5: 20103439 | C5: 10554940 | D5: 3061576.7
A7: Includes exchange traded turnnover in corporate bonds
A8: ="$ indicates as on "&TEXT('1'!$C$2,"mmmm dd, yyyy") -> $ indicates as on July 31, 2024
A9: Source: BSE, NSE and MSEI.

Sheet 17
A1: Table 17: Trends in Cash Segment of BSE
A2: Year / Month | B2: No. of Companies Listed | C2: No. of Companies Permitted | D2: No. of Companies Traded | E2: No. of Trading Days | F2: No. of Trades (Lakh) | G2: Traded Quantity (Lakh) | H2: Turnover (` crore) | I2: Average Daily Turnover (` crore) | J2: Average Trade Size (`) | K2: Demat Securities Traded (Lakh) | L2: Demat Turnover (` crore) | M2: Market Capitalisation (` crore) | N2: S&P BSE Sensex
N3: High | O3: Low | P3: Close
A4: 2023-24 | B4: 5252 | C4: 25 | D4: 4295 | E4: 246 | F4: 8263.45 | G4: 2120712.3 | H4: 1629038.3 | I4: 6622.1071 | J4: 19713.78 | K4: 2120712.3 | L4: 1629038.2 | M4: 38697100 | N4: 74245.17 | O4: 58793.08 | P4: 73651.35
A5: 2024-25$ | B5: =INDEX(B6:B17,COUNT(B6:B17)) -> 5307 | C5: =INDEX(C6:C17,COUNT(C6:C17)) -> 26 | D5: 4265 | E5: =SUM(E6:E17) -> 83 | F5: =SUM(F6:F17) -> 3928.19 | G5: =SUM(G6:G17) -> 808654.08 | H5: =SUM(H6:H17) -> 784509.36 | I5: =H5/E5 -> 9451.92 | J5: =H5/F5*100 -> 19971.268 | K5: =SUM(K6:K17) -> 808654.08 | L5: =SUM(L6:L17) -> 784509.32 | M5: =INDEX(M6:M17,COUNT(M6:M17)) -> 46238008 | N5: =MAX(N6:N17) -> 81908.43 | O5: =MIN(O6:O17) -> 70234.43 | P5: =INDEX(P6:P17,COUNT(P6:P17)) -> 81741.34
A6: 45383 | B6: 5264 | C6: 26 | D6: 4153 | E6: 20 | F6: 766.49 | G6: 188397.56 | H6: 152767.43 | I6: 7638.3715 | J6: 19930.779 | K6: 188397.56 | L6: 152767.43 | M6: 40655852 | N6: 75111.39 | O6: 74346.4 | P6: 74482.78
A7: 45413 | B7: 5274 | C7: 26 | D7: 4170 | E7: 22 | F7: 871.14 | G7: 176258.29 | H7: 169592.24 | I7: 7708.7382 | J7: 19467.851 | K7: 176258.29 | L7: 169592.23 | M7: 41212881 | N7: 76009.68 | O7: 71866.01 | P7: 73961.31
A8: 45444 | B8: 5293 | C8: 26 | D8: 4200 | E8: 19 | F8: 1080.27 | G8: 201461 | H8: 227001.57 | I8: =H8/E8 -> 11947.451 | J8: =100*H8/F8 -> 21013.411 | K8: 201461 | L8: 227001.56 | M8: 43924744 | N8: 79671.58 | O8: 70234.43 | P8: 79032.73
A9: 45474 | B9: 5307 | C9: 26 | D9: 4208 | E9: 22 | F9: 1210.29 | G9: 242537.23 | H9: 235148.12 | I9: 10688.551 | J9: 19429.072 | K9: 242537.23 | L9: 235148.1 | M9: 46238008 | N9: 81908.43 | O9: 78971.79 | P9: 81741.34
A10: 45505
A11: 45536
A12: 45566
A13: 45597
A14: 45627
A15: 45658
A16: 45689
A17: 45717
A19: Note : No. of Companies Listed with BSE includes count of both active and suspended companies.
A20: No.of trades and turnover details inclusive of exchange traded corporate bonds
A21: Source: BSE
A22: ="$ indicates as on "&TEXT('1'!$C$2,"mmmm dd, yyyy") -> $ indicates as on July 31, 2024

Sheet 18
A1: Table 18: Trends in Cash Segment of NSE
A2: Year / Month | B2: No. of Companies Listed | C2: No. of Companies Permitted | D2: No. of companies Traded# | E2: No. of Trading Days | F2: No. of Trades (Lakh) | G2: Traded Quantity (Lakh) | H2: Turnover (` crore) | I2: Average Daily Turnover (` crore) | J2: Average Trade Size (`) | K2: Demat Securities Traded (Lakh) | L2: Demat Turnover (` crore) | M2: Market Capitalisation (` crore) | N2: Nifty 50 Index
N3: High | O3: Low | P3: Close
A4: 2023-24 | B4: 2439 | C4: 3 | D4: 2985 | E4: 246 | F4: 68124.68 | G4: 10179861 | H4: 20103439 | I4: 81721.298 | J4: 29509.774 | K4: 10179861 | L4: 20103439 | M4: 38421668 | N4: 22526.6 | O4: 17312.75 | P4: 22326.9
A5: 2024-25$ | B5: =INDEX(B6:B17,COUNT(B6:B17)) -> 2529 | C5: =INDEX(C6:C17,COUNT(C6:C17)) -> 3 | D5: 3294 | E5: =SUM(E6:E17) -> 83 | F5: =SUM(F6:F17) -> 33050.75 | G5: =SUM(G6:G17) -> 4258187.4 | H5: =SUM(H6:H17) -> 10554940 | I5: =H5/E5 -> 127167.95 | J5: =H5/F5*100 -> 31935.554 | K5: =SUM(K6:K17) -> 4258187.4 | L5: =SUM(L6:L17) -> 10554940 | M5: =INDEX(M6:M17,COUNT(M6:M17)) -> 45865878 | N5: =MAX(N6:N17) -> 24999 | O5: =MIN(O6:O17) -> 21281.45 | P5: =INDEX(P6:P17,COUNT(P6:P17)) -> 24951
A6: 45383 | B6: 2464 | C6: 3 | D6: 2625 | E6: 20 | F6: 6810.19 | G6: 990584.38 | H6: 2120195.5 | I6: 106009.78 | J6: 31132.69 | K6: 990584.38 | L6: 2120195.5 | M6: 40304406 | N6: 22526.6 | O6: 21710.2 | P6: 22604.85
A7: 45413 | B7: 2482 | C7: 3 | D7: 2995 | E7: 22 | F7: 7680.33 | G7: 924888.14 | H7: 2467941.4 | I7: 112179.16 | J7: 32133.27 | K7: 924888.14 | L7: 2467941.4 | M7: 40880530 | N7: 23110.8 | O7: 21821.05 | P7: 22530.7
A8: 45444 | B8: 2499 | C8: 3 | D8: 2998 | E8: 19 | F8: 8709.81 | G8: 1157608.4 | H8: 2905226.5 | I8: 152906.66 | J8: 33355.8 | K8: 1157608.4 | L8: 2905226.5 | M8: 43573919 | N8: 24174 | O8: 21281.45 | P8: 24010.6
A9: 45474 | B9: 2529 | C9: 3 | D9: 3093 | E9: 22 | F9: 9850.42 | G9: 1185106.6 | H9: 3061576.7 | I9: 139162.58 | J9: 31080.67 | K9: 1185106.6 | L9: 3061576.7 | M9: 45865878 | N9: 24999 | O9: 23992 | P9: 24951
A10: 45505
A11: 45536
A12: 45566
A13: 45597
A14: 45627
A15: 45658
A16: 45689
A17: 45717
A19: Turnover Data compiled for all markets except auction market
A20: No.of trades and turnover details inclusive of exchange traded corporate bonds
A21: #Data for No. of companies traded includes Government securities, Corporate bonds, REITs, InvITs, NSE listed companies as well as “Permitted to Trade” companies but excludes ETFs & Mutual Funds
A22: Source: NSE
A23: $ indicates as on July 31, 2024

Sheet 19
A1: Table 19: Trends in Cash Segment of MSEI
A2: Year/Month | B2: No. of Companies Listed | C2: No. of Companies Permitted # | D2: No. of Companies Traded | E2: No. of Trading Days | F2: No. of Trades (Lakh) | G2: Traded Quantity (Lakh) | H2: Turnover (₹ crore) | I2: Average Daily Turnover (₹ crore) | J2: Average Trade Size (₹) | K2: Demat Securities Traded (Lakh) | L2: Demat Turnover (₹ crore) | M2: Market Capitalisation (₹ crore) | N2: SX 40 Index
N3: High | O3: Low | P3: Close
A4: 2023-24 | B4: 266 | C4: 1705 | D4: 10 | E4: 246 | F4: 0.00351 | G4: 20.22445 | H4: 29.33808 | I4: 0.11926049 | J4: 835842.73 | K4: NA | L4: NA | M4: 38356305 | N4: 42685.19 | O4: 33552.3 | P4: 42417.24
A5: 2024-25$ | B5: =INDEX(B6:B17,COUNT(B6:B17)) -> 266 | C5: 1771 | D5: 6 | E5: =SUM(E6:E17) -> 83 | F5: =SUM(F6:F17) -> 0.00148 | G5: =SUM(G6:G17) -> 7.63158 | H5: =SUM(H6:H17) -> 2.0832373 | I5: =H5/E5 -> 0.025099245 | J5: =H5/F5*100 -> 140759.28 | K5: NA | L5: NA | M5: =INDEX(M6:M17,COUNT(M6:M17)) -> 47610230 | N5: =MAX(N6:N17) -> 47309.14 | O5: =MIN(O6:O17) -> 41588.01 | P5: =INDEX(P6:P17,COUNT(P6:P17)) -> 47309.14
A6: 45383 | B6: 266 | C6: 1704 | D6: 1 | E6: 20 | F6: 0.00023 | G6: 0.76 | H6: 0.56713575 | I6: 0.028356787 | J6: 246580.76 | K6: NA | L6: NA | M6: 40187325 | N6: 43265.36 | O6: 41843.95 | P6: 42994.7
A7: 45413 | B7: 266 | C7: 1771 | D7: 2 | E7: 22 | F7: 0.00036 | G7: 0.96832 | H7: 0.7316605 | I7: 0.033257295 | J7: 203239.03 | K7: NA | L7: NA | M7: 41477460 | N7: 43643.65 | O7: 41779.14 | P7: 42784.29
A8: 45444 | B8: 266 | C8: 1840 | D8: 5 | E8: 19 | F8: 0.00062 | G8: 0.8376 | H8: 0.2662195 | I8: 0.014011553 | J8: 42938.629 | K8: NA | L8: NA | M8: 45649188 | N8: 45764.87 | O8: 41588.01 | P8: 45686.35
A9: 45474 | B9: 266 | C9: 1837 | D9: 5 | E9: 22 | F9: 0.00027 | G9: 5.06566 | H9: 0.51822155 | I9: 0.023555525 | J9: 191933.91 | K9: NA | L9: NA | M9: 47610230 | N9: 47309.14 | O9: 45686.35 | P9: 47309.14
A10: 45505
A11: 45536
A12: 45566
A13: 45597
A14: 45627
A15: 45658
A16: 45689
A17: 45717
A19: Note: Data of the Market Capitalisation is provided for all listed as well as permitted companies
A20: # Details of no. of companies in "permitted to trade" category which are active.
A21: Source: MSEI
A22: $ indicates as on July 31, 2024

Sheet 20
A1: Table 20: City-wise Distribution of Turnover on Cash Segments of BSE and NSE
A2: (Percentage share in Turnover)
A3: S.No | B3: City | C3: BSE | E3: NSE | G3: MSEI*
C4: 2024-25$ | D4: Jul-24 | E4: 2024-25$ | F4: Jul-24 | G4: 2024-25$ | H4: Jul-24
A5: 1 | B5: Ahmedabad | C5: 25.58827 | D5: 26.062039 | E5: 16.51 | F5: 16.95 | G5: 0 | H5: 0
A6: 2 | B6: Bengaluru | C6: 0.44146043 | D6: 0.6119869 | E6: 2.56 | F6: 3.17 | G6: 0 | H6: 0
A7: 3 | B7: Vadodara | C7: 0.28246984 | D7: 0.23485625 | E7: 0.1 | F7: 0.11 | G7: 0 | H7: 0
A8: 4 | B8: Bhubneshwar | C8: 0.0040490916 | D8: 0.0056969959 | E8: 0 | F8: 0 | G8: 0 | H8: 0
A9: 5 | B9: Chennai | C9: 0.30266644 | D9: 0.33330778 | E9: 1.11 | F9: 1.2 | G9: 0 | H9: 0
A10: 6 | B10: Ernakulam | C10: 0.035699145 | D10: 0.020602842 | E10: 0.29 | F10: 0.28 | G10: 0 | H10: 0
A11: 7 | B11: Coimbatore | C11: 0.011945768 | D11: 0.012294046 | E11: 0.05 | F11: 0.05 | G11: 0 | H11: 0
A12: 8 | B12: New Delhi | C12: 0.9405318 | D12: 0.92907138 | E12: 2.24 | F12: 2.2 | G12: 47.2 | H12: 37.7
A13: 9 | B13: Guwahati | C13: 0.023607484 | D13: 0.024401052 | E13: 0 | F13: 0 | G13: 0 | H13: 0
A14: 10 | B14: Hyderabad | C14: 0.11772091 | D14: 0.1153468 | E14: 2.77 | F14: 2.72 | G14: 0 | H14: 0
A15: 11 | B15: Indore | C15: 0.30734199 | D15: 0.30110064 | E15: 0.2 | F15: 0.19 | G15: 0 | H15: 0
A16: 12 | B16: Jaipur | C16: 0.4207859 | D16: 0.31172268 | E16: 0.17 | F16: 0.15 | G16: 0 | H16: 0
... A25: 21 | B25: Others | C25: 36.754612 | D25: 37.549904 | E25: 7.71 | F25: 7.76 | G25: 52.8 | H25: 62.3
B26: Total | C26: =SUM(C5:C25) -> 100 | D26: =SUM(D5:D25) -> 100 | E26: =SUM(E5:E25) -> 100 | F26: =SUM(F5:F25) -> 99.91 | G26: =SUM(G5:G25) -> 100 | H26: =SUM(H5:H25) -> 100
A28: Notes:
A29: *The city-wise distribution of turnover is based on the cities uploaded in the UCC database of the Exchange for clientele trades and members registered office city for proprietary trades.
A30: Source: BSE, NSE and MSEI.
A31: $ indicates as on July 31, 2024

Sheet 21
A1: Table 21: Category-wise Share of Turnover in Cash Segment of BSE
A2: Year / Month | B2: Percentage Share in Turnover
B3: Proprietary | C3: FPIs | D3: Mutual Funds | E3: Banks | F3: Others
A4: 2023-24 | B4: 34.431982 | C4: 13.019998 | D4: 3.2849059 | E4: 0.13515121 | F4: 49.127962
A5: 2024-25$ | B5: 37.815799 | C5: 6.2775898 | D5: 3.3773526 | E5: 0.0573724 | F5: 52.471886
A6: 45383 | B6: 38.581507 | C6: 6.1647818 | D6: 2.7451591 | E6: 0.0056915566 | F6: 52.50286
A7: 45413 | B7: 38.793481 | C7: 6.4085656 | D7: 3.7494118 | E7: 0.16447709 | F7: 50.884064
A8: 45444 | B8: 37.024267 | C8: 7.8948549 | D8: 2.9717587 | E8: 0.037713593 | F8: 52.071406
A9: 45474 | B9: 37.377336 | C9: 4.6951793 | D9: 3.9112742 | E9: 0.032679896 | F9: 53.983531
A10: 45505
A11: 45536
A12: 45566
A13: 45597
A14: 45627
A15: 45658
A16: 45689
A17: 45717
A19: Source: BSE.
A20: $ indicates as on July 31, 2024

Sheet 22
A1: Table 22: Category-wise Share of Turnover in Cash Segment of NSE
A2: Year /Month | B2: Percentage Share in Turnover
B3: Proprietary | C3: FPIs | D3: Mutual Funds | E3: Banks | F3: Others
A4: 2023-24 | B4: 28.24 | C4: 14.43 | D4: 7.78 | E4: 0.24 | F4: 49.31
A5: 2024-25$ | B5: 29.46 | C5: 13.5 | D5: 8.48 | E5: 0.18 | F5: 48.38
A6: 45383 | B6: 29.27 | C6: 13.71 | D6: 8.48 | E6: 0.16 | F6: 48.39
A7: 45413 | B7: 29.15 | C7: 16.1 | D7: 8.55 | E7: 0.19 | F7: 46.01
A8: 45444 | B8: 30.07 | C8: 13.22 | D8: 8.71 | E8: 0.18 | F8: 47.82
A9: 45474 | B9: 29.26 | C9: 11.53 | D9: 8.19 | E9: 0.2 | F9: 50.82
A10: 45505
A11: 45536
A12: 45566
A13: 45597
A14: 45627
A15: 45658
A16: 45689
A17: 45717
A19: Source: NSE.
A20: $ indicates as on July 31, 2024

Sheet 23
A1: Table 23: Category-wise Share of Turnover in Cash Segment of MSEI
A2: Year / Month | B2: Percentage Share in Turnover
B3: Proprietary | C3: FPIs | D3: Mutual Funds | E3: Banks | F3: Others
A4: 2023-24 | B4: 0 | C4: 0 | D4: 0 | E4: 0 | F4: 100
A5: 2024-25$ | B5: 0.4178677 | C5: 0 | D5: 0 | E5: 0 | F5: 99.653214
A6: 45383 | B6: 0 | C6: 0 | D6: 0 | E6: 0 | F6: 100
A7: 45413 | B7: 0.74177163 | C7: 0 | D7: 0 | E7: 0 | F7: 99.258228
A8: 45444 | B8: 0 | C8: 0 | D8: 0 | E8: 0 | F8: 100
A9: 45474 | B9: 0 | C9: 0 | D9: 0 | E9: 0 | F9: 100
A10: $ indicates as on July 31, 2024
A11: Source: MSEI.

Sheet 24
A1: Table 24: Component Stocks: S&P BSE Sensex during July, 2024
A2: Sl.No | B2: Name of Security | C2: Issued Capital (₹ crore) | D2: Free Float Market Capitalisation (₹ crore) | E2: Weightage (Percent) | F2: Beta | G2: R 2 | H2: Daily Volatility (Percent) | I2: Monthly Return (Percent) | J2: Impact Cost (Percent)
A3: 1 | B3: BAJFINANCE | C3: 123.8 | D3: 189648.15 | E3: 2.0306336 | F3: 1.09 | G3: 0.328091 | H3: 1.55 | I3: -4.318589 | J3: 1.19
A4: 2 | B4: STATE BANK | C4: 892.46 | D4: 334925.07 | E4: 3.5861679 | F4: 1.48 | G4: 0.453003 | H4: 1.78 | I4: 2.815574 | J4: 1.46
A5: 3 | B5: TITAN | C5: 88.78 | D5: 144282.05 | E5: 1.5448818 | F5: 0.66 | G5: 0.148538 | H5: 1.39 | I5: 1.519332 | J5: 1.19
A6: 4 | B6: HDFC BANK | C6: 761.41 | D6: 1217170.1 | E6: 13.032695 | F6: 1.09 | G6: 0.435418 | H6: 1.34 | I6: -3.949986 | J6: 1.53
A7: 5 | B7: INFOSYS LTD | C7: 2076.01 | D7: 674707.3 | E7: 7.2243431 | F7: 0.74 | G7: 0.200246 | H7: 1.33 | I7: 19.215673 | J7: 1.31
A8: 6 | B8: JSWSL | C8: 244.55 | D8: 88482.028 | E8: 0.94741013 | F8: 1.34 | G8: 0.467592 | H8: 1.58 | I8: -0.39723 | J8: 0.94
A9: 7 | B9: KOTAK MAH.BK | C9: 994.06 | D9: 265770.67 | E9: 2.8457059 | F9: 0.92 | G9: 0.275123 | H9: 1.42 | I9: 0.20244 | J9: 1.33
A10: 8 | B10: RELIANCE | C10: 6765.81 | D10: 1018321.1 | E10: 10.903544 | F10: 1.17 | G10: 0.519921 | H10: 1.31 | I10: -3.882689 | J10: 1.48
A11: 9 | B11: TATA STEEL | C11: 1248.34 | D11: 136233.06 | E11: 1.4586983 | F11: 1.49 | G11: 0.450118 | H11: 1.8 | I11: -4.971264 | J11: 1.34
A12: 10 | B12: LARSEN & TOU | C12: 274.97 | D12: 445512.06 | E12: 4.7702641 | F12: 1.41 | G12: 0.462487 | H12: 1.68 | I12: 7.413929 | J12: 1.45
A13: 11 | B13: MAH & MAH | C13: 621.76 | D13: 256678.31 | E13: 2.7483506 | F13: 1.11 | G13: 0.249827 | H13: 1.8 | I13: 1.359737 | J13: 1.34
A14: 12 | B14: TATA MOTORS | C14: 664.93 | D14: 203700.5 | E14: 2.1810973 | F14: 0.93 | G14: 0.209369 | H14: 1.64 | I14: 16.791233 | J14: 1.63
... A32: 30 | B32: BAJAJ FINSE | C32: 159.67 | D32: 79134.659 | E32: 0.84732436 | F32: 0.97 | G32: 0.355815 | H32: 1.31 | I32: 4.125204 | J32: 1.07
A34: 1. Beta & R2 are calculated for the trailing 12 months .Beta measures the degree to which any portfolio of stocks is affected as compared to the effect on the market as a whole.
A35: 2. The coefficient of determination (R2) measures the strength of relationship between two variables the return on a security versus that of the market.
A36: 3. Volatility is the standard deviation of the daily returns for the trailing 12 months.
A37: 4. Impact cost is calculated as the difference between actual buy price and ideal buy price, divided by ideal buy price, multiplied by 100. Hence ideal price is calculated as (best buy + best sell)/2.
A38: 5. The above is calculated for a month for the portfolio size of Rs. 5 lakh. It is calculated for the current month.
A39: Source: BSE.

Sheet 25
A1: Table 25: Component Stocks: Nifty 50 Index during July, 2024
A2: Sl. No | B2: Name of Security | C2: Issued Capital (₹ crore) | D2: Free Float Market Capitalisation (₹ crore) | E2: Weightage (Percent) | F2: Beta | G2: R 2 | H2: Daily Volatility (Percent) | I2: Monthly Return (Percent) | J2: Impact Cost (Percent)
A3: 1 | B3: Adani Enterprises Ltd. | C3: 114 | D3: 83101.75 | E3: 0.75 | F3: 2.08 | G3: 0.4 | H3: 1.22 | I3: -0.24 | J3: 0.02
A4: 2 | B4: Adani Ports and Special Economic Zone Ltd. | C4: 432.03 | D4: 115300.87 | E4: 1.05 | F4: 2.09 | G4: 0.43 | H4: 1.3 | I4: 6.21 | J4: 0.03
A5: 3 | B5: Apollo Hospitals Enterprise Ltd. | C5: 71.89 | D5: 66582.5 | E5: 0.6 | F5: 0.58 | G5: 0.11 | H5: 1.23 | I5: 6.95 | J5: 0.01
A6: 4 | B6: Asian Paints Ltd. | C6: 95.92 | D6: 139054.09 | E6: 1.26 | F6: 0.55 | G6: 0.15 | H6: 1.19 | I6: 5.74 | J6: 0.02
A7: 5 | B7: Axis Bank Ltd. | C7: 618.01 | D7: 331503.69 | E7: 3.01 | F7: 1.13 | G7: 0.36 | H7: 1.36 | I7: -7.84 | J7: 0.02
A8: 6 | B8: Bajaj Auto Ltd. | C8: 279.18 | D8: 107921.96 | E8: 0.98 | F8: 0.51 | G8: 0.08 | H8: 1.17 | I8: 1.71 | J8: 0.03
A9: 7 | B9: Bajaj Finance Ltd. | C9: 123.8 | D9: 189606.47 | E9: 1.72 | F9: 1.09 | G9: 0.32 | H9: 1.31 | I9: -4.34 | J9: 0.02
A10: 8 | B10: Bajaj Finserv Ltd. | C10: 159.67 | D10: 89662.32 | E10: 0.81 | F10: 0.97 | G10: 0.35 | H10: 1.05 | I10: 4 | J10: 0.03
A11: 9 | B11: Bharat Petroleum Corporation Ltd. | C11: 4338.51 | D11: 68341.22 | E11: 0.62 | F11: 1.46 | G11: 0.29 | H11: 1.84 | I11: 15.17 | J11: 0.03
A12: 10 | B12: Bharti Airtel Ltd. | C12: 2845.44 | D12: 398946.43 | E12: 3.62 | F12: 0.88 | G12: 0.27 | H12: 1.4 | I12: 3.29 | J12: 0.02
A13: 11 | B13: Britannia Industries Ltd. | C13: 24.09 | D13: 68271.24 | E13: 0.62 | F13: 0.28 | G13: 0.04 | H13: 0.97 | I13: 5.64 | J13: 0.02
A14: 12 | B14: Cipla Ltd. | C14: 161.5 | D14: 81058.25 | E14: 0.73 | F14: 0.29 | G14: 0.02 | H14: 1.39 | I14: 4.29 | J14: 0.02
... A52: 50 | B52: Wipro Ltd. | C52: 1045.99 | D52: 73710.83 | E52: 0.67 | F52: 1.04 | G52: 0.25 | H52: 2.64 | I52: 1.39 | J52: 0.02
A54: Notes: 1. Beta & R2 are calculated for the the trailing 12 months. Beta measures the degree to which any portfolio of stocks is affected as compared to the effect on the market as a whole.
A55: 2. The coefficient of determination (R2) measures the strength of relationship between two variables the return on a security versus that of the market.
A56: 3. Volatility is the standard deviation of the daily returns for the the trailing 12 months.
A57: 4. Impact cost is calculated as the difference between actual buy price and ideal buy price, divided by ideal buy price, multiplied by 100. Hence ideal price is calculated as (best buy + best sell)/2.
A58: 5. Impact Cost for Nifty 50 is for a portfolio of ₹50 lakh and is weighted average impact cost.
A59: 6. Shriram Finance Ltd replaced UPL Ltd in the benchmark Nifty50 index, effective from March 28
A60: Source: NSE.

Sheet 26
A1: Table 26: Component Stocks: SX40 Index during July, 2024
A2: S.No. | B2: Name of Security | C2: Issued Capital (₹ crore) | D2: Free Float Market Capitalisation (₹ crore) | E2: Weightage (Percent) | F2: Beta | G2: R2 | H2: Daily Volatility (Percent) | I2: Monthly Return (Percent) | J2: Impact Cost (Percent) *
A3: 1 | B3: HDFCBANK | C3: 761.41207 | D3: 1263275.8 | E3: 11.837484 | F3: 1.07 | G3: 0.42 | H3: - | I3: - | J3: -
A4: 2 | B4: RELIANCE | C4: 6765.8156 | D4: 1032443.4 | E4: 9.6744766 | F4: 1.15 | G4: 0.51 | H4: - | I4: - | J4: -
A5: 3 | B5: ICICIBANK | C5: 1407.7169 | D5: 840302.99 | E5: 7.8740311 | F5: 1.01 | G5: 0.45 | H5: - | I5: - | J5: -
A6: 4 | B6: INFY | C6: 2076.0142 | D6: 656708.66 | E6: 6.1536665 | F6: 0.74 | G6: 0.19 | H6: - | I6: - | J6: -
A7: 5 | B7: ITC | C7: 1249.5879 | D7: 611173.42 | E7: 5.7269802 | F7: 0.65 | G7: 0.2 | H7: - | I7: - | J7: -
A8: 6 | B8: LT | C8: 274.96962 | D8: 502831.46 | E8: 4.7117654 | F8: 1.4 | G8: 0.45 | H8: - | I8: - | J8: -
A9: 7 | B9: TCS | C9: 361.80875 | D9: 437487.98 | E9: 4.0994665 | F9: 0.58 | G9: 0.14 | H9: - | I9: - | J9: -
A10: 8 | B10: BHARTIARTL | C10: 2846.1457 | D10: 400557.03 | E10: 3.7534062 | F10: 0.85 | G10: 0.26 | H10: - | I10: - | J10: -
A11: 9 | B11: AXISBANK | C11: 618.2026 | D11: 330393.58 | E11: 3.095942 | F11: 1.13 | G11: 0.36 | H11: - | I11: - | J11: -
A12: 10 | B12: SBIN | C12: 892.46119 | D12: 325736.21 | E12: 3.0523003 | F12: 1.44 | G12: 0.44 | H12: - | I12: - | J12: -
A13: 11 | B13: M&M | C13: 621.76442 | D13: 279656.38 | E13: 2.6205108 | F13: 1.13 | G13: 0.25 | H13: - | I13: - | J13: -
A14: 12 | B14: KOTAKBANK | C14: 994.06001 | D14: 265717.55 | E14: 2.4898974 | F14: 0.89 | G14: 0.26 | H14: - | I14: - | J14: -
... A42: 40 | B42: WIPRO | C42: 1046.1077 | D42: 71411.02 | E42: 0.66915458 | F42: 1.06 | G42: 0.26 | H42: - | I42: - | J42: -
A44: Notes:
A45: 1. Market Cap, Beta & R2 as on the last day of the month
A46: 2. Beta & R2 are calculated for the trailing 12 months
A47: 3. Volatility for the current month
A48: 4. *Since there is no trading in the SX40 constituents, the Impact Cost for the given stocks is NIL.
A49: #Jio Financial Services Limited was included in SX 40 on account of adjustment for Reliance Industries Ltd (RELIANCE) due to scheme of demerger. The same was excluded w.e.f. Sep 01, 2023
A50: Source: MSEI.

Sheet 27
A1: Table 27: Advances/Declines in Cash Segment of BSE, NSE and MSEI
A2: Year/ Month | B2: BSE | E2: NSE | H2: MSEI
B3: Advances | C3: Declines | D3: Advance/Decline Ratio | E3: Advances | F3: Declines | G3: Advance/Decline Ratio | H3: Advances | I3: Declines | J3: Advance/Decline Ratio
A4: 2023-24 | B4: 2772 | C4: 1284 | D4: 2.1588785 | E4: 1768 | F4: 690 | G4: 2.5623188 | H4: 3 | I4: 0 | J4: 0
A5: 2024-25$ | B5: 3182 | C5: 1006 | D5: 3.1630219 | E5: 1902 | F5: 456 | G5: =IFERROR(E5/F5,"-") -> 4.1710526 | H5: 1 | I5: - | J5: =IFERROR(H5/I5,"0") -> 0
A6: 45383 | B6: 2840 | C6: 1246 | D6: 2.2792937 | E6: 2081 | F6: 608 | G6: 3.42 | H6: 1 | I6: - | J6: -
A7: 45413 | B7: 1955 | C7: 2146 | D7: 0.9109972 | E7: 1388 | F7: 1330 | G7: 1.04 | H7: - | I7: 1 | J7: -
A8: 45444 | B8: 2343 | C8: 1785 | D8: 1.312605 | E8: 1939 | F8: 1082 | G8: 1.79 | H8: 1 | I8: 1 | J8: 1
A9: 45474 | B9: 2975 | C9: 1175 | D9: 2.5319149 | E9: 2322 | F9: 746 | G9: 3.11 | H9: 2 | I9: 1 | J9: 2
A11: Note: Advance/Decline ratio is calculated based on the average price methodology.
A12: $ indicates as on July 31, 2024
A13: Source: BSE, NSE and MSEI.

Sheet 28
A1: Table 28: Trading Frequency in Cash Segment of BSE, NSE and MSEI
A2: Month | B2: BSE | E2: NSE | H2: MSEI
B3: No. of Companies Listed | C3: No. of Companies Traded | D3: Percent of Traded to Listed | E3: No. of Companies Listed | F3: No. of Companies Traded# | G3: Percent of Traded to Listed | H3: No. of Companies Listed | I3: No. of Companies Traded | J3: Percent of Traded to Listed
A4: 2023-24 | B4: 5252 | C4: 4295 | D4: 81.77837 | E4: 2439 | F4: 2985 | G4: 122.38622 | H4: 266 | I4: 7 | J4: 2.6315789
A5: 2024-25$ | B5: =INDEX(B6:B9,COUNT(B6:B9)) -> 5307 | C5: 4265 | D5: =C5/B5*100 -> 80.365555 | E5: =INDEX(E6:E9,COUNT(E6:E9)) -> 2529 | F5: 3294 | G5: =F5/E5*100 -> 130.24911 | H5: =INDEX(H6:H9,COUNT(H6:H9)) -> 266 | I5: 7 | J5: =I5/H5*100 -> 2.6315789
A6: 45383 | B6: 5264 | C6: 4153 | D6: =C6/B6*100 -> 78.894377 | E6: 2464 | F6: 2625 | G6: =F6/E6*100 -> 106.53409 | H6: 266 | I6: 1 | J6: 0.37593985
A7: 45413 | B7: 5274 | C7: 4170 | D7: =C7/B7*100 -> 79.067122 | E7: 2482 | F7: 2995 | G7: =F7/E7*100 -> 120.66882 | H7: 266 | I7: 2 | J7: 0.7518797
A8: 45444 | B8: 5293 | C8: 4200 | D8: =C8/B8*100 -> 79.350085 | E8: 2499 | F8: 2998 | G8: =F8/E8*100 -> 119.96799 | H8: 266 | I8: 5 | J8: 1.8796992
A9: 45474 | B9: 5307 | C9: 4208 | D9: =C9/B9*100 -> 79.291502 | E9: 2529 | F9: 3093 | G9: =F9/E9*100 -> 122.3013 | H9: 266 | I9: 5 | J9: 1.8796992
A11: #Data for No. of companies traded includes Government securities, Corporate bonds, REITs, InvITs, NSE listed companies as well as “Permitted to Trade” companies but excludes ETFs & Mutual Funds
A12: $ indicates as on July 31, 2024
A13: Source: BSE, NSE and MSEI.

Sheet 29
A1: Table 29: Daily Volatility of Major Indices (percent)
A2: Year / Month | B2: BSE Sensex | C2: BSE 100 | D2: BSE 500 | E2: Nifty 50 | F2: Nifty Next 50 | G2: Nifty 500 | H2: SX40
A3: 2023-24 | B3: 0.62412709 | C3: 0.6175061 | D3: 0.64135556 | E3: 0.61679638 | F3: 0.82938324 | G3: 0.6406067 | H3: 0.54
A4: 2024-25$ | B4: 1.0268883 | C4: 1.0595855 | D4: 1.1162489 | E4: 1.0292113 | F4: 1.5468953 | G4: 1.1136788 | H4: 1.03
A5: 45383 | B5: 0.66487891 | C5: 0.59553522 | D5: 0.57968754 | E5: 0.61078348 | F5: 0.72036026 | G5: 0.57071034 | H5: 0.7
A6: 45413 | B6: 0.65549977 | C6: 0.66922923 | D6: 0.71596298 | E6: 0.65017636 | F6: 1.0234396 | G6: 0.70526607 | H6: 0.66
A7: 45444 | B7: 1.8513595 | C7: 1.9434366 | D7: 2.0676516 | E7: 1.8279768 | F7: 2.7769182 | G7: 2.0178004 | H7: 1.85
A8: 45474 | B8: 0.52294816 | C8: 0.56192092 | D8: 0.57765306 | E8: 0.53408935 | F8: 0.91207242 | G8: 0.56506094 | H8: 0.53
A10: Note: Volatility is calculated as the standard deviation of the natural log of daily returns in indices for the respective period.
A11: Source: BSE, MSEI and NSE.
A12: $ indicates as on July 31, 2024

Sheet 30
A1: Table 30: Percentage Share of Top ‘N’ Securities/Members in Turnover of Cash Segment (percent)
A2: Year/ Month | B2: BSE | G2: NSE | L2: MSEI
A3: Top | B3: 5 | C3: 10 | D3: 25 | E3: 50 | F3: 100 | G3: 5 | H3: 10 | I3: 25 | J3: 50 | K3: 100 | L3: 5 | M3: 10 | N3: 25 | O3: 50 | P3: 100
A4: Securities
A5: 2023-24 | B5: 6.886 | C5: 12.1078 | D5: 22.8741 | E5: 33.898 | F5: 47.016 | G5: 10.41 | H5: 15.69 | I5: 26.18 | J5: 37.52 | K5: 53.16 | L5: 100 | M5: 100 | N5: 100 | O5: 100 | P5: 100
A6: 2024-25$ | B6: 8.0129 | C6: 12.8899 | D6: 24.5524 | E6: 36.3828 | F6: 49.7232 | G6: 8.09 | H6: 13.84 | I6: 26.38 | J6: 39.4 | K6: 55.04 | L6: 100 | M6: 100 | N6: 100 | O6: 100 | P6: 100
A7: 45383 | B7: 12.2374 | C7: 18.0837 | D7: 28.1178 | E7: 38.9042 | F7: 51.0897 | G7: 9.17 | H7: 15.05 | I7: 26.65 | J7: 40 | K7: 56.68 | L7: 100 | M7: 100 | N7: 100 | O7: 100 | P7: 100
A8: 45413 | B8: 9.3637 | C8: 14.9964 | D8: 27.5572 | E8: 40.1971 | F8: 53.8349 | G8: 7.86 | H8: 13.85 | I8: 27.5 | J8: 40.93 | K8: 58.04 | L8: 100 | M8: 100 | N8: 100 | O8: 100 | P8: 100
A9: 45444 | B9: 9.3576 | C9: 15.3494 | D9: 27.6383 | E9: 40.628 | F9: 55.0916 | G9: 9.4 | H9: 15.99 | I9: 28.93 | J9: 42.2 | K9: 58.15 | L9: 100 | M9: 100 | N9: 100 | O9: 100 | P9: 100
A10: 45474 | B10: 10.3039 | C10: 15.9009 | D10: 26.5934 | E10: 37.9379 | F10: 51.2233 | G10: 9.95 | H10: 15.72 | I10: 27.25 | J10: 39.54 | K10: 54.63 | L10: 100 | M10: 100 | N10: 100 | O10: 100 | P10: 100
A11: Members
A12: 2023-24 | B12: 35.9 | C12: 47.49 | D12: 68.79 | E12: 81.44 | F12: 90.03 | G12: 25.48 | H12: 38.59 | I12: 59.21 | J12: 75.72 | K12: 88.71 | L12: 100 | M12: 100 | N12: 100 | O12: NA | P12: NA
A13: 2024-25$ | B13: 42.16 | C13: 54.35 | D13: 72.5 | E13: 82.57 | F13: 91.02 | G13: 26.63 | H13: 41.04 | I13: 62.13 | J13: 77.74 | K13: 89.99 | L13: 100 | M13: 100 | N13: 100 | O13: NA | P13: NA
A14: 45383 | B14: 41.94 | C14: 55.09 | D14: 72.36 | E14: 82.17 | F14: 90.43 | G14: 26.45 | H14: 40.93 | I14: 62.12 | J14: 77.93 | K14: 90.04 | L14: 100 | M14: 100 | N14: 100 | O14: NA | P14: NA
A15: 45413 | B15: 42.1 | C15: 55.03 | D15: 72.75 | E15: 83.54 | F15: 91.32 | G15: 25.89 | H15: 40.27 | I15: 63.09 | J15: 78.84 | K15: 90.59 | L15: 100 | M15: 100 | N15: 100 | O15: NA | P15: NA
A16: 45444 | B16: 40.5 | C16: 52.95 | D16: 72.8 | E16: 83.86 | F16: 91.79 | G16: 27.1 | H16: 40.9 | I16: 61.81 | J16: 77.59 | K16: 90.1 | L16: 100 | M16: 100 | N16: 100 | O16: NA | P16: NA
A17: 45474 | B17: 43.94 | C17: 56.73 | D17: 74.59 | E17: 83.77 | F17: 91.69 | G17: 27.38 | H17: 42.38 | I17: 61.95 | J17: 77.21 | K17: 89.53 | L17: 100 | M17: 100 | N17: 100 | O17: NA | P17: NA
A19: Notes: 1. Data for Top N scrips has been compiled for all markets except Auction market & Retail Debt Market and includes series EQ, BE,BT, BL and IL.
A20: $ indicates as on July 31, 2024
A21: Source: BSE, NSE and MSEI.

Sheet 31
A1: Table 31: Settlement Statistics for Cash Segment of ICCL
A2: Year / Month | B2: No. of Trades(Lakh) | C2: Traded Quantity (Lakh) | D2: Delivered Quantity (Lakh) | E2: Percent of Delivered Quantity to Traded Quantity | F2: Turnover (₹ crore) | G2: Delivered Value (₹ crore) | H2: Percent of Delivered Value to Total Turnover | I2: Delivered Quantity in Demat Mode (Lakh) | J2: Percent of Demat Delivered Quantity to Total Delivered Quantity | K2: Delivered Value in Demat Mode (₹ crore) | L2: Percent of Demat Delivered Value to Total Delivered Value | M2: Short Delivery (Auctioned quantity) (Lakh) | N2: Percent of Short Delivery to Delivery Quantity | O2: Funds Pay-in (₹ crore) | P2: Securities Pay-in (crore) | Q2: Settlement Guarantee Fund (₹ crore)
A3: 2023-24 | B3: 9980.6111 | C3: 2519145.3 | D3: 597537.51 | E3: 23.719851 | F3: 3458333.7 | G3: 699412.77 | H3: 20.223982 | I3: 597537.43 | J3: 99.999987 | K3: 699412.77 | L3: 100 | M3: 1014.2349 | N3: 0.16973578 | O3: 158274 | P3: 700419.1 | Q3: 385.35
A4: 2024-25$ | B4: =SUM(B5:B8) -> 4333.4492 | C4: =SUM(C5:C8) -> 1017447.7 | D4: =SUM(D5:D8) -> 269601.28 | E4: =D4/C4*100 -> 26.497803 | F4: =SUM(F5:F8) -> 1637322 | G4: =SUM(G5:G8) -> 338138.57 | H4: =G4/F4*100 -> 20.651929 | I4: =SUM(I5:I8) -> 269601.28 | J4: =I4/D4*100 -> 100 | K4: =SUM(K5:K8) -> 338138.57 | L4: =K4/G4*100 -> 100 | M4: =SUM(M5:M8) -> 166.85267 | N4: =M4/D4*100 -> 0.061888678 | O4: =SUM(O5:O8) -> 73790.365 | P4: =SUM(P5:P8) -> 338532.52 | Q4: =INDEX(Q5:Q8,COUNT(Q5:Q8)) -> 397.41
A5: 45383 | B5: 899.8 | C5: 244703.9 | D5: 61106.7 | E5: 24.97169 | F5: 322563 | G5: 65643 | H5: 20.350443 | I5: 61106.7 | J5: 100 | K5: 65643 | L5: 100 | M5: 36.9 | N5: 0.060386177 | O5: 10723 | P5: 65728 | Q5: 388.39
A6: 45413 | B6: 966.54923 | C6: 218716.79 | D6: 59194.742 | E6: 27.064562 | F6: 348357.36 | G6: 75625.272 | H6: 21.709107 | I6: 59194.742 | J6: 100 | K6: 75625.272 | L6: 100 | M6: 36.9 | N6: 0.062336618 | O6: 17091.93 | P6: 75803.256 | Q6: 390.68
A7: 45444 | B7: 1136.3883 | C7: 257986.49 | D7: 67401.841 | E7: 26.126113 | F7: 455683.61 | G7: 96898.294 | H7: 21.26438 | I7: 67401.841 | J7: 100 | K7: 96898.294 | L7: 100 | M7: 36.85267 | N7: 0.054676059 | O7: 25741.095 | P7: 96971.006 | Q7: 393.35
A8: 45474 | B8: 1330.7116 | C8: 296040.5 | D8: 81898 | E8: 27.664458 | F8: 510718 | G8: 99972 | H8: 19.574795 | I8: 81898 | J8: 100 | K8: 99972 | L8: 100 | M8: 56.2 | N8: 0.068621944 | O8: 20234.34 | P8: 100030.26 | Q8: 397.41
A9: $ indicates as on July 31, 2024
A10: Source: ICCL.

Sheet 32
A1: Table 32: Settlement Statistics for Cash Segment of NSCCL
A2: Year / Month | B2: No. of Trades(Lakh) | C2: Traded Quantity (Lakh) | D2: Delivered Quantity (Lakh) | E2: Percent of Delivered Quantity to Traded Quantity | F2: Turnover (₹ crore) | G2: Delivered Value (₹ crore) | H2: Percent of Delivered Value to Total Turnover | I2: Delivered Quantity in Demat Mode (Lakh) | J2: Percent of Demat Delivered Quantity to Total Delivered Quantity | K2: Delivered Value in Demat Mode (₹ crore) | L2: Percent of Demat Delivered Value to Total Delivered Value | M2: Short Delivery (Auctioned quantity) (Lakh) | N2: Percent of Short Delivery to Delivery Quantity | O2: Funds Pay-in (₹ crore) | P2: Securities Pay-in (crore) | Q2: Settlement Guarantee Fund (₹ crore)
A3: 2023-24 | B3: 69487.827 | C3: 11268719 | D3: 2344344.2 | E3: 20.803999 | F3: 21748414 | G3: 5504035.5 | H3: 25.307755 | I3: 2341440.8 | J3: 99.876152 | K3: 5498635.6 | L3: 99.901892 | M3: 2903.4312 | N3: 0.12384833 | O3: 1303158.1 | P3: 5504035.5 | Q3: 765.52
A4: 2024-25$ | B4: =SUM(B5:B8) -> 34895.798 | C4: =SUM(C5:C8) -> 4780871.9 | D4: =SUM(D5:D8) -> 1050215 | E4: =D4/C4*100 -> 21.967018 | F4: =SUM(F5:F8) -> 11386065 | G4: =SUM(G5:G8) -> 2747927.4 | H4: =G4/F4*100 -> 24.134126 | I4: =SUM(I5:I8) -> 1049081.5 | J4: =I4/D4*100 -> 99.892071 | K4: =SUM(K5:K8) -> 2746673.1 | L4: =K4/G4*100 -> 99.954355 | M4: =SUM(M5:M8) -> 1133.4857 | N4: =M4/D4*100 -> 0.10792892 | O4: =SUM(O5:O8) -> 634262.11 | P4: =SUM(P5:P8) -> 2747927.4 | Q4: =INDEX(Q5:Q8,COUNT(Q5:Q8)) -> 836.15
A5: 45383 | B5: 7195.4276 | C5: 1101489.7 | D5: 246083.11 | E5: 22.340936 | F5: 2285452.9 | G5: 562380.62 | H5: 24.606966 | I5: 245951.9 | J5: 99.946683 | K5: 562055.17 | L5: 99.946683 | M5: 131.20477 | N5: 0.053345703 | O5: 131968.62 | P5: 562380.62 | Q5: 775.22
A6: 45413 | B6: 8145.329 | C6: 1012222.7 | D6: 233019.57 | E6: 23.020582 | F6: 2543832.8 | G6: 617866.57 | H6: 24.288804 | I6: 232681.21 | J6: 100 | K6: 617521.93 | L6: 100 | M6: 338.35321 | N6: 0.14541492 | O6: 130262.41 | P6: 617866.57 | Q6: 819.86
A7: 45444 | B7: 9477.56 | C7: 1310108.9 | D7: 286125.69 | E7: 21.84 | F7: 3235067.4 | G7: 804129.5 | H7: 24.86 | I7: 285849.81 | J7: 100 | K7: 803773.09 | L7: 100 | M7: 275.88 | N7: 0.1 | O7: 215176.39 | P7: 804129.5 | Q7: 827.71
A8: 45474 | B8: 10077.482 | C8: 1357050.5 | D8: 284986.63 | E8: 21.000443 | F8: 3321712.1 | G8: 763550.68 | H8: 22.98666 | I8: 284598.58 | J8: 100 | K8: 763322.9 | L8: 100 | M8: 388.04771 | N8: 0.13634914 | O8: 156854.69 | P8: 763550.68 | Q8: 836.15
A10: Settlement Statistics for settlement type N, excluding CM Series IL & BL
A11: $ indicates as on July 31, 2024
A12: Source: NSCCL

Sheet 33
A1: Table 33: Settlement Statistics for Cash Segment of MSE Clearing
A2: Year / Month | B2: No. of Trades(Lakh) | C2: Traded Quantity (Lakh) | D2: Delivered Quantity (Lakh) | E2: Percent of Delivered Quantity to Traded Quantity | F2: Turnover (₹ crore) | G2: Delivered Value (₹ crore) | H2: Percent of Delivered Value to Total Turnover | I2: Delivered Quantity in Demat Mode (Lakh) | J2: Percent of Demat Delivered Quantity to Total Delivered Quantity | K2: Delivered Value in Demat Mode (₹ crore) | L2: Percent of Demat Delivered Value to Total Delivered Value | M2: Funds Pay-in (₹ crore) | N2: Securities Pay-in (₹ crore) | O2: Settlement Guarantee Fund(₹ crore)
A3: 2023-24 | B3: NA | C3: NA | D3: NA | E3: NA | F3: NA | G3: NA | H3: NA | I3: NA | J3: NA | K3: NA | L3: NA | M3: NA | N3: NA | O3: NA
A4: 2024-25$ | B4: NA | C4: NA | D4: NA | E4: NA | F4: NA | G4: NA | H4: NA | I4: NA | J4: NA | K4: NA | L4: NA | M4: NA | N4: NA | O4: NA
A5: 45383 | B5: NA | C5: NA | D5: NA | E5: NA | F5: NA | G5: NA | H5: NA | I5: NA | J5: NA | K5: NA | L5: NA | M5: NA | N5: NA | O5: NA
A6: 45413 | B6: NA | C6: NA | D6: NA | E6: NA | F6: NA | G6: NA | H6: NA | I6: NA | J6: NA | K6: NA | L6: NA | M6: NA | N6: NA | O6: NA
A7: 45444 | B7: NA | C7: NA | D7: NA | E7: NA | F7: NA | G7: NA | H7: NA | I7: NA | J7: NA | K7: NA | L7: NA | M7: NA | N7: NA | O7: NA
A8: 45474 | B8: NA | C8: NA | D8: NA | E8: NA | F8: NA | G8: NA | H8: NA | I8: NA | J8: NA | K8: NA | L8: NA | M8: NA | N8: NA | O8: NA
A10: Source: MSE Clearing
A11: $ indicates as on July 31, 2024
D12: ``

Sheet 34
A1: Table 34: Trends in Equity Derivatives Segment at BSE
A2: Month/ Year | B2: No. of Trading Days | C2: Index Futures | E2: Stock Futures | G2: Index Options | M2: Stock Options | S2: Total Turnover | V2: Open Interest at the end of the day
G3: Calls | J3: Puts | M3: Calls | P3: Puts | S3: No. of Contracts | T3: Turnover (₹ crore)
C4: No. of Contracts | D4: Turnover (₹ crore) | E4: No. of Contracts | F4: Turnover (₹ crore) | G4: No. of Contracts | H4: Turnover (₹ crore) | J4: No. of Contracts | K4: Turnover (₹ crore) | M4: No. of Contracts | N4: Turnover (₹ crore) | P4: No. of Contracts | Q4: Turnover (₹ crore) | V4: No. of contracts | W4: Value (₹ crore)
H5: Premium | I5: Notional | K5: Premium | L5: Notional | N5: Premium | O5: Notional | Q5: Premium | R5: Notional | T5: Premium* | U5: Notional
A6: 1 | B6: 2 | C6: 3 | D6: 4 | E6: 6 | F6: 8 | G6: 9 | H6: 10 | I6: 11 | J6: 12 | K6: 13 | L6: 14 | M6: 15 | N6: 16 | O6: 17 | P6: 18 | Q6: 19 | R6: 20 | S6: 21 | T6: 22 | U6: 24 | V6: 25 | W6: 26
A7: 2023-24 | B7: 246 | C7: 281532 | D7: 20247.139 | E7: 1 | F7: 0.09417 | G7: 5800012712 | H7: 259453.91 | I7: 4.1431652e+08 | J7: 5499653676 | K7: 233206.68 | L7: 3.8849862e+08 | M7: 0 | N7: 0 | O7: 0 | P7: 0 | Q7: 0 | R7: 0 | S7: 11299947921 | T7: 512907.82 | U7: 8.0283538e+08 | V7: 2183095.5 | W7: 161229.47 | X7: =U7/B7 -> 3263558.5
A8: 2024-25$ | B8: =SUM(B9:B12) -> 83 | C8: =SUM(C9:C12) -> 171691 | D8: =SUM(D9:D12) -> 13536.094 | E8: =SUM(E9:E12) -> 4148 | F8: =SUM(F9:F12) -> 316.13314 | G8: =SUM(G9:G12) -> 5515905104 | H8: =SUM(H9:H12) -> 309832.98 | I8: =SUM(I9:I12) -> 4.3871889e+08 | ... U8: =SUM(U9:U12) -> 8.4987842e+08 | V8: =INDEX(V9:V12,COUNT(V9:V12)) -> 386890 | W8: =INDEX(W9:W12,COUNT(W9:W12)) -> 31854.73 | X8: =U8/B8 -> 10239499
A9: 45383 | B9: 20 | C9: 43584 | D9: 3336.667 | E9: 0 | F9: 0 | G9: 1136394739 | H9: 59762.224 | I9: 87127144 | J9: 1087904500 | K9: 57625.139 | L9: 82368154 | M9: 0 | N9: 0 | O9: 0 | P9: 0 | Q9: 0 | R9: 0 | S9: 2224342823 | T9: 120724.03 | U9: 1.6949864e+08 | V9: 293730 | W9: 22345.473 | X9: =U9/B9 -> 8474931.8
A10: 45413 | B10: 22 | C10: 33975 | D10: 2552.1349 | E10: 0 | F10: 0 | G10: 1480962413 | H10: 78074.341 | I10: 1.1313537e+08 | J10: 1413930789 | K10: 80786.208 | L10: 1.0660427e+08 | M10: 0 | N10: 0 | O10: 0 | P10: 0 | Q10: 0 | R10: 0 | S10: 2894927177 | T10: 161412.68 | U10: 2.1974219e+08 | V10: 150694 | W10: 12462.15 | X10: =U10/B10 -> 9988281.5
A11: 45444 | B11: 19 | C11: 34978 | D11: 2723.8138 | E11: 0 | F11: 0 | G11: 1346324635 | H11: 85283.051 | I11: 1.0822484e+08 | J11: 1242473794 | K11: 75332.358 | L11: 98148144 | M11: 1 | N11: 0.09405 | O11: 0.00055 | P11: 0 | Q11: 0 | R11: 0 | S11: 2588833408 | T11: 163339.22 | U11: 2.0637571e+08 | V11: 318510 | W11: 28044.048 | X11: =U11/B11 -> 10861880
A12: 45474 | B12: 22 | C12: 59154 | D12: 4923.4786 | E12: 4148 | F12: 316.13314 | G12: 1552223317 | H12: 86713.362 | I12: 1.3023154e+08 | J12: 1498086409 | K12: 77721.036 | L12: 1.2402507e+08 | M12: 185 | N12: 0.131217 | O12: 15.357917 | P12: 235 | Q12: 0.19669162 | R12: 20.241842 | S12: 3050373448 | T12: 169674.34 | U12: 2.5426188e+08 | V12: 386890 | W12: 31854.73 | X12: =U12/B12 -> 11557358
A14: Note:
A15: Notional turnover is inclusive of the premium turnover
A16: *includes futures turnover
A17: $ indicates as on July 31, 2024
A18: Source: BSE.

Sheet 35
A1: Table 35: Trends in Equity Derivatives Segment at NSE
A2: Month/ Year | B2: No. of Trading Days | C2: Index Futures | E2: Stock Futures | G2: Index Options | M2: Stock Options | S2: Total Turnover | V2: Open Interest at the end of the day
G3: Calls | J3: Puts | M3: Calls | P3: Puts | S3: No. of Contracts | T3: Turnover (₹ crore)
C4: No. of Contracts | D4: Turnover (₹ crore) | E4: No. of Contracts | F4: Turnover (₹ crore) | G4: No. of Contracts | H4: Turnover (₹ crore) | J4: No. of Contracts | K4: Turnover (₹ crore) | M4: No. of Contracts | N4: Turnover (₹ crore) | P4: No. of Contracts | Q4: Turnover (₹ crore) | V4: No. of contracts | W4: Value (` crore)
H5: Premium | I5: Notional | K5: Premium | L5: Notional | N5: Premium | O5: Notional | Q5: Premium | R5: Notional | T5: Premium* | U5: Notional
A6: 1 | B6: 2 | C6: 3 | D6: 4 | E6: 6 | F6: 8 | G6: 9 | H6: 10 | I6: 11 | J6: 12 | K6: 13 | L6: 14 | M6: 15 | N6: 16 | O6: 17 | P6: 18 | Q6: 19 | R6: 20 | S6: 21 | T6: 22 | U6: 23 | V6: 24 | W6: 25
A7: 2023-24 | B7: 246 | C7: 85826189 | D7: 7417117.3 | E7: 325399952 | F7: 25546966 | G7: 47921898390 | H7: 7126932.3 | I7: 4.061453e+09 | J7: 45730172862 | K7: 6692632.1 | L7: 3.8062382e+09 | M7: 775801808 | N7: 1000523.2 | O7: 64095047 | P7: 361845516 | Q7: 377506.7 | R7: 28016744 | S7: 95200943894 | T7: 48161679 | U7: 7.9927672e+09 | V7: 15039231 | W7: 1304406.6
A8: 2024-25$ | B8: =SUM(B9:B12) -> 83 | C8: =SUM(C9:C12) -> 48187301 | D8: =SUM(D9:D12) -> 3308165 | E8: =SUM(E9:E12) -> 176525117 | F8: =SUM(F9:F12) -> 14117603 | G8: =SUM(G9:G12) -> 20956979541 | H8: =SUM(H9:H12) -> 2701000.7 | I8: =SUM(I9:I12) -> 1.5586601e+09 | ... U8: =SUM(U9:U12) -> 3.0281823e+09 | V8: =INDEX(V9:V12,COUNT(V9:V12)) -> 27757631 | W8: =INDEX(W9:W12,COUNT(W9:W12)) -> 1925117.7
A9: 45383 | B9: 20 | C9: 7887086 | D9: 693063.85 | E9: 36869594 | F9: 3158915 | G9: 4259527124 | H9: 573007.9 | I9: 3.6437103e+08 | J9: 4078207900 | K9: 511594.34 | L9: 3.4286634e+08 | M9: 76010605 | N9: 113516.1 | O9: 6933927 | P9: 35324034 | Q9: 42426.62 | R9: 2987417.8 | S9: 8493826343 | T9: 5092523.9 | U9: 7.2101069e+08 | V9: 25024548 | W9: 1610978.1 | X9: =U9/B9 -> 36050534 | Y9: ='34'!X9 -> 8474931.8 | Z9: =X9+Y9 -> 44525466
A10: 45413 | B10: 22 | C10: 12867642 | D10: 806652.3 | E10: 44730139 | F10: 3464429.9 | G10: 5522370837 | H10: 638840.15 | I10: 3.752949e+08 | J10: 5124124253 | K10: 645947.84 | L10: 3.4006161e+08 | M10: 92044531 | N10: 134430.55 | O10: 7732031.7 | P10: 42409057 | Q10: 52182.763 | R10: 3302662.4 | S10: 10838546459 | T10: 5742483.5 | U10: 7.3066229e+08 | V10: 21048035 | W10: 1403628.4 | X10: =U10/B10 -> 33211922 | Y10: ='34'!X10 -> 9988281.5 | Z10: =X10+Y10 -> 43200204
A11: 45444 | B11: 19 | C11: 15202595 | D11: 983344.44 | E11: 46464820 | F11: 3662528.4 | G11: 5311283074 | H11: 803979.06 | I11: 3.8523333e+08 | J11: 4822496239 | K11: 682328.71 | L11: 3.373817e+08 | M11: 94203160 | N11: 139043.34 | O11: 7978189.7 | P11: 40640021 | Q11: 52326.559 | R11: 3198611.4 | S11: 10330289909 | T11: 6323550.5 | U11: 7.384377e+08 | V11: 26690224 | W11: 1903259.7 | X11: =U11/B11 -> 38865142 | Y11: ='34'!X11 -> 10861880 | Z11: =X11+Y11 -> 49727022
A12: 45474 | B12: 22 | C12: 12229978 | D12: 825104.4 | E12: 48460564 | F12: 3831730.1 | G12: 5863798506 | H12: 685173.56 | I12: 4.3376087e+08 | J12: 5376202748 | K12: 627022.93 | L12: 3.8772644e+08 | M12: 101628963 | N12: 142829.51 | O12: 8366184.7 | P12: 46600482 | Q12: 55047.444 | R12: 3561346.2 | S12: 11448921241 | T12: 1510073.4 | U12: 8.3807167e+08 | V12: 27757631 | W12: 1925117.7 | X12: =U12/B12 -> 38094167 | Y12: ='34'!X12 -> 11557358 | Z12: =X12+Y12 -> 49651525
A14: Note:
A15: Notional turnover is inclusive of the premium turnover
A16: *includes futures turnover
A17: $ indicates as on July 31, 2024
A18: Source: NSE.

Sheet 36
A1: Table 36: Settlement Statistics in Equity Derivatives Segment at BSE and NSE (₹ crore)
A2: Year/ Month | B2: BSE | I2: NSE
B3: Index/Stock Futures | E3: Index/Stock Options | G3: Total | H3: Settlement Gurantee Fund | I3: Index/Stock Futures | K3: Index/Stock Options | M3: Total | N3: Settlement Gurantee Fund
B4: MTM Settlement | C4: Final Settlement | D4: Physical Settlement | E4: Premium Settlement | F4: Exercise Settlement | I4: MTM Settlement | J4: Final Settlement | K4: Premium Settlement | L4: Exercise Settlement
A5: 2023-24 | B5: 6005.4689 | C5: 164.23793 | D5: - | E5: 3919.1982 | F5: 819.87672 | G5: 10908.782 | H5: 100.92 | I5: 239700.5 | J5: 3940.7346 | K5: 112155.92 | L5: 24024.774 | M5: 379821.93 | N5: 4264.49
A6: 2024-25$ | B6: =SUM(B7:B10) -> 3012.7567 | C6: =SUM(C7:C10) -> 40.778381 | D6: - | E6: =SUM(E7:E10) -> 1943.7134 | F6: =SUM(F7:F10) -> 877.34051 | G6: =SUM(G7:G10) -> 5874.5891 | H6: =INDEX(H7:H10,COUNT(H7:H10)) -> 107.15 | I6: 121066.23 | J6: 1647.0343 | K6: 40221.467 | L6: 12544.36 | M6: 175479.09 | N6: 7759.44
A7: 45383 | B7: 1065.2008 | C7: 6.8701904 | D7: 0 | E7: 402.05086 | F7: 204.05946 | G7: 1678.1813 | H7: 102.32 | I7: 24836.539 | J7: 435.98307 | K7: 11915.183 | L7: 3958.2465 | M7: 41145.952 | N7: 4293.95
A8: 45413 | B8: 391.62876 | C8: 7.5643721 | D8: 0 | E8: 287.96326 | F8: 192.80092 | G8: 879.95731 | H8: 104.35 | I8: 37390.64 | J8: 862.45 | K8: 14393.78 | L8: 3302.45 | M8: 55949.32 | N8: 4379.67
A9: 45444 | B9: 1113.9646 | C9: 9.5482689 | D9: 0 | E9: 882.94681 | F9: 296.06176 | G9: 2302.5215 | H9: 105.62 | I9: 58839.047 | J9: 348.60119 | K9: 13912.504 | L9: 5283.6636 | M9: 78383.816 | N9: 7759.44
A10: 45474 | B10: 441.96254 | C10: 16.795549 | D10: 0 | E10: 370.75249 | F10: 184.41837 | G10: 1013.929 | H10: 107.15 | I10: 34038.46 | J10: 270.26 | K10: 12522.08 | L10: 3257.71 | M10: 50088.51 | N10: 7872.74
A12: Note: Revised data is at clearing member level on net basis
A13: Source: BSE and NSE
A14: $ indicates as on July 31, 2024

Sheet 37
A1: Table 37: Category-wise Share of Turnover & Open Interest in Equity Derivative Segment of BSE
A2: Year/Month | B2: Percentage Share in Turnover | G2: Percentage Share in Open Interest
B3: Pro | C3: FPIs | D3: Mutual Funds | E3: Banks | F3: Others | G3: Pro | H3: FPIs | I3: Mutual Funds | J3: Banks | K3: Others
A4: 2023-24 | B4: 68.718277 | C4: 1.8481793 | D4: 0 | E4: 0 | F4: 29.433544 | G4: 18.311076 | H4: 0 | I4: 0 | J4: 0 | K4: 81.688924
A5: 2024-25$ | B5: 70.637457 | C5: 1.248735 | D5: 0 | E5: 0 | F5: 28.113808 | G5: =INDEX(G6:G9,COUNT(G6:G9)) -> 33.457484 | H5: =INDEX(H6:H9,COUNT(H6:H9)) -> 0 | I5: =INDEX(I6:I9,COUNT(I6:I9)) -> 0 | J5: =INDEX(J6:J9,COUNT(J6:J9)) -> 0 | K5: =INDEX(K6:K9,COUNT(K6:K9)) -> 66.542516
A6: 45383 | B6: 70.756086 | C6: 1.3804805 | D6: 0 | E6: 0 | F6: 27.863434 | G6: 33.470143 | H6: 0.0004407468 | I6: 0 | J6: 0 | K6: 66.529416
A7: 45413 | B7: 70.010853 | C7: 1.1681408 | D7: 0 | E7: 0 | F7: 28.821006 | G7: 38.257288 | H7: 0 | I7: 0 | J7: 0 | K7: 61.742712
A8: 45444 | B8: 71.207214 | C8: 1.2263451 | D8: 0 | E8: 0 | F8: 27.56644 | G8: 29.797654 | H8: 0.053192726 | I8: 0 | J8: 0 | K8: 70.149153
A9: 45474 | B9: 72.424866 | C9: 1.1803424 | D9: 0 | E9: 0 | F9: 26.394792 | G9: 33.457484 | H9: 0 | I9: 0 | J9: 0 | K9: 66.542516
A11: Source: BSE.
A12: $ indicates as on July 31, 2024

Sheet 38
A1: Table 38: Category-wise Share of Turnover & Open Interest in Equity Derivative Segment of NSE
A2: Year/Month | B2: Percentage Share in Turnover | G2: Percentage Share in Open Interest
B3: Pro | C3: FPIs | D3: Mutual Funds | E3: Banks | F3: Others | G3: Pro | H3: FPIs | I3: Mutual Funds | J3: Banks | K3: Others
A4: 2023-24 | B4: 59.72 | C4: 6 | D4: 0.03 | E4: 0 | F4: 34.25 | G4: 22.74 | H4: 20.55 | I4: 8.4 | J4: 0 | K4: 48.31
A5: 2024-25$ | B5: 58.88 | C5: 7.07 | D5: 0.04 | E5: 0 | F5: 34.01 | G5: =INDEX(G6:G9,COUNT(G6:G9)) -> 18.62 | H5: =INDEX(H6:H9,COUNT(H6:H9)) -> 18.77 | I5: =INDEX(I6:I9,COUNT(I6:I9)) -> 6.79 | J5: =INDEX(J6:J9,COUNT(J6:J9)) -> 0 | K5: =INDEX(K6:K9,COUNT(K6:K9)) -> 55.81
A6: 45383 | B6: 58.53 | C6: 7.66 | D6: 0.04 | E6: 0 | F6: 33.76 | G6: 20.49 | H6: 18.71 | I6: 6.83 | J6: 0 | K6: 53.97
A7: 45413 | B7: 59.47 | C7: 6.96 | D7: 0.04 | E7: 0 | F7: 33.52 | G7: 20.46 | H7: 23.88 | I7: 8.77 | J7: 0 | K7: 46.89
A8: 45444 | B8: 58.62 | C8: 6.6 | D8: 0.05 | E8: 0 | F8: 34.73 | G8: 19.31 | H8: 17.84 | I8: 6.46 | J8: 0 | K8: 56.39
A9: 45474 | B9: 59.88 | C9: 6.53 | D9: 0.04 | E9: 0 | F9: 33.55 | G9: 18.62 | H9: 18.77 | I9: 6.79 | J9: 0 | K9: 55.81
A11: Source: NSE.
A12: $ indicates as on July 31, 2024

Sheet 39
A1: Table 39: Instrument-wise Turnover in Index Derivatives at BSE
A2: Turnover Share (in Percentage)
A3: Year/Month | B3: BSE 30 SENSEX | C3: BSE SENSEX 50 | D3: BSE BANKEX | E3: BSE OIL & GAS INDEX | F3: BSE TECK INDEX | G3: BSE 100 | H3: HANG SENG Index Futures | I3: MICEX Index Futures | J3: FTSE/JSE Top 40 Futures | K3: IBOVESPA Futures
A4: 2023-24 | B4: 100 | C4: 0.00012745229 | D4: 0.0063109315 | E4: 0 | F4: 0 | G4: 0 | H4: 0 | I4: 0 | J4: 0 | K4: 0
A5: 2024-25$ | B5: 73.86 | C5: 0 | D5: 26.14 | E5: 0 | F5: 0 | G5: 0 | H5: 0 | I5: 0 | J5: 0 | K5: 0
A6: 45383 | B6: 69.02 | C6: 0 | D6: 30.98 | E6: 0 | F6: 0 | G6: 0 | H6: 0 | I6: 0 | J6: 0 | K6: 0
A7: 45413 | B7: 77.45 | C7: 0 | D7: 22.55 | E7: 0 | F7: 0 | G7: 0 | H7: 0 | I7: 0 | J7: 0 | K7: 0
A8: 45444 | B8: 74.03 | C8: 0 | D8: 25.97 | E8: 0 | F8: 0 | G8: 0 | H8: 0 | I8: 0 | J8: 0 | K8: 0
A9: 45474 | B9: 67.16595 | C9: 0 | D9: 32.83405 | E9: 0 | F9: 0 | G9: 0 | H9: 0 | I9: 0 | J9: 0 | K9: 0
A11: Source: BSE.
A12: $ indicates as on July 31, 2024

Sheet 40
A1: Table 40: Instrument-wise Turnover in Index Derivatives at NSE
A2: Year/Month | B2: Turnover Share (in Percentage)
B3: NIFTY | C3: BANKNIFTY | D3: FINNIFTY | E3: MIDCPNIFTY
A4: 2023-24 | B4: 33.43 | C4: 45.18 | D4: 17.6 | E4: 3.79
A5: 2024-25$ | B5: 36.16 | C5: 41.54 | D5: 15.75 | E5: 6.54
A6: 45383 | B6: 36.08 | C6: 41.13 | D6: 16.36 | E6: 6.44
A7: 45413 | B7: 39.17 | C7: 39.2 | D7: 15.19 | E7: 6.42
A8: 45444 | B8: 33.26 | C8: 44.25 | D8: 15.7 | E8: 6.77
A9: 45474 | B9: 30.18 | C9: 43.21 | D9: 17.61 | E9: 8.98
A11: Source: NSE.
A12: $ indicates as on July 31, 2024

Sheet 41
A1: Table 41: Trends in Currency Derivatives Segment at BSE
A2: Year/ Month | B2: No. of Trading Days | C2: Currency Futures | E2: Currency Options | I2: Total | K2: Open Interest at the end of the Month
E3: Call | G3: Put
C4: No. of Contracts | D4: Turnover (₹ crore) | E4: No. of Contracts | F4: Turnover (₹ crore) | G4: No. of Contracts | H4: Turnover (₹ crore) | I4: No. of Contracts | J4: Turnover (₹ crore) | K4: No. of Contracts | L4: Value (₹ crore)
A5: 2023-24 | B5: 241 | C5: 264230072 | D5: 2189493.6 | E5: 10072828 | F5: 83584.35 | G5: 8811787 | H5: 72737.362 | I5: 283114687 | J5: 2345815.3 | K5: 1158785 | L5: 9668.9115
A6: 2024-25$ | B6: =SUM(B7:B10) -> 79 | C6: =SUM(C7:C10) -> 3684521 | D6: =SUM(D7:D10) -> 30766.296 | E6: =SUM(E7:E10) -> 20623 | F6: =SUM(F7:F10) -> 172.3007 | G6: =SUM(G7:G10) -> 22107 | H6: =SUM(H7:H10) -> 183.5957 | I6: =SUM(I7:I10) -> 3727251 | J6: =SUM(J7:J10) -> 31122.193 | K6: =INDEX(K7:K10,COUNT(K7:K10)) -> 535 | L6: =INDEX(L7:L10,COUNT(L7:L10)) -> 4.480304
A7: 45383 | B7: 18 | C7: 3150904 | D7: 26310.401 | E7: 20623 | F7: 172.3007 | G7: 22107 | H7: 183.5957 | I7: 3193634 | J7: 26666.297 | K7: 252685 | L7: 2111.5294
A8: 45413 | B8: 20 | C8: 240852 | D8: 2011.5062 | E8: 0 | F8: 0 | G8: 0 | H8: 0 | I8: 240852 | J8: 2011.5062 | K8: 9076 | L8: 75.601991
A9: 45444 | B9: 19 | C9: 271760 | D9: 2268.5629 | E9: 0 | F9: 0 | G9: 0 | H9: 0 | I9: 271760 | J9: 2268.5629 | K9: 45810 | L9: 382.30003
A10: 45474 | B10: 22 | C10: 21005 | D10: 175.8263 | E10: 0 | F10: 0 | G10: 0 | H10: 0 | I10: 21005 | J10: 175.8263 | K10: 535 | L10: 4.480304
A12: Source: BSE
A13: $ indicates as on July 31, 2024

Sheet 42
A1: Table 42: Trends in Currency Derivatives Segment at NSE
A2: Year/ Month | B2: No. of Trading Days | C2: Currency Futures | E2: Currency Options | I2: Total | K2: Open Interest at the end of Month
C3: No. of Contracts | D3: Turnover (₹ crore) | E3: Call | G3: Put | I3: No. of Contracts | J3: Turnover (₹ crore) | K3: No. of Contracts | L3: Value (₹ crore)
E4: No. of Contracts | F4: Turnover (₹ crore) | G4: No. of Contracts | H4: Turnover (₹ crore)
A5: 2023-24 | B5: 241 | C5: 851902719 | D5: 7201742 | E5: 1738285961 | F5: 14436935 | G5: 1632032548 | H5: 13505361 | I5: 4222221228 | J5: 35144038 | K5: 17804703 | L5: 165247.09
A6: 2024-25$ | B6: =SUM(B7:B10) -> 79 | C6: =SUM(C7:C10) -> 56930211 | D6: =SUM(D7:D10) -> 477507.37 | E6: =SUM(E7:E10) -> 10526774 | F6: =SUM(F7:F10) -> 88297.796 | G6: =SUM(G7:G10) -> 9337116 | H6: =SUM(H7:H10) -> 77657.499 | I6: =SUM(I7:I10) -> 76794101 | J6: =SUM(J7:J10) -> 643462.66 | K6: =INDEX(K7:K10,COUNT(K7:K10)) -> 1332388 | L6: =INDEX(L7:L10,COUNT(L7:L10)) -> 11081.408
A7: 45383 | B7: 18 | C7: 25887006 | D7: 217438.37 | E7: 9600292 | F7: 80511.67 | G7: 8858247 | H7: 73676.57 | I7: 44345545 | J7: 371626.6 | K7: 4205161 | L7: 34682.3
A8: 45413 | B8: 20 | C8: 12571143 | D8: 105150.5 | E8: 429828 | F8: 3605.5657 | G8: 266533 | H8: 2215.5393 | I8: 13267504 | J8: 110971.61 | K8: 3064185 | L8: 25354.245
A9: 45444 | B9: 19 | C9: 13057459 | D9: 109312.06 | E9: 310279 | F9: 2612.15 | G9: 158451 | H9: 1315.65 | I9: 13526189 | J9: 113239.86 | K9: 2882251 | L9: 23813.799
A10: 45474 | B10: 22 | C10: 5414603 | D10: 45606.44 | E10: 186375 | F10: 1568.41 | G10: 53885 | H10: 449.74 | I10: 5654863 | J10: 47624.59 | K10: 1332388 | L10: 11081.408
A12: Notes: 1. Trading Value :- For Futures, Value of contract = Traded Qty*Traded Price. 2. For Options, Value of contract = Traded Qty*(Strike Price+Traded Premium)
A13: Source: NSE.
A14: $ indicates as on July 31, 2024

Sheet 43
A1: Table 43: Trends in Currency Derivatives Segment at MSEI
A2: Year/ Month | B2: No. of Trading Days | C2: Currency Futures | E2: Currency Options | I2: Total | K2: Open Interest at the end of Month
C3: No. of Contracts | D3: Turnover (₹ crore) | E3: Call | G3: Put | I3: No. of Contracts | J3: Turnover (₹ crore) | K3: No. of Contracts | L3: Value (₹ crore)
E4: No. of Contracts | F4: Turnover (₹ crore) | G4: No. of Contracts | H4: Turnover (₹ crore)
A5: 2023-24 | B5: 241 | C5: 29862428 | D5: 247738.04 | E5: 0 | F5: 0 | G5: 0 | H5: 0 | I5: 29862428 | J5: 247738.04 | K5: 103180 | L5: 861.50117
A6: 2024-25$ | B6: =SUM(B7:B10) -> 79 | C6: =SUM(C7:C10) -> 855475 | D6: =SUM(D7:D10) -> 7141.135 | E6: =SUM(E7:E10) -> 0 | F6: =SUM(F7:F10) -> 0 | G6: =SUM(G7:G10) -> 0 | H6: =SUM(H7:H10) -> 0 | I6: =SUM(I7:I10) -> 855475 | J6: =SUM(J7:J10) -> 7140.9305 | K6: =INDEX(K7:K10,COUNT(K7:K10)) -> 0 | L6: =INDEX(L7:L10,COUNT(L7:L10)) -> 0
A7: 45383 | B7: 18 | C7: 636475 | D7: 5312.0763 | E7: 0 | F7: 0 | G7: 0 | H7: 0 | I7: 636475 | J7: 5312.0763 | K7: 40175 | L7: 335.53159
A8: 45413 | B8: 20 | C8: 120000 | D8: 1001.7 | E8: 0 | F8: 0 | G8: 0 | H8: 0 | I8: 120000 | J8: 1001.7 | K8: 4 | L8: 0.033414
A9: 45444 | B9: 19 | C9: 78000 | D9: 651.57425 | E9: 0 | F9: 0 | G9: 0 | H9: 0 | I9: 78000 | J9: 651.57425 | K9: 28000 | L9: 233.961
A10: 45474 | B10: 22 | C10: 21000 | D10: 175.7845 | E10: 0 | F10: 0 | G10: 0 | H10: 0 | I10: 21000 | J10: 175.58 | K10: 0 | L10: 0
A12: Source: MSEI
A13: $ indicates as on July 31, 2024

Sheet 44
A1: Table 44: Settlement Statistics of Currency Derivatives Segment (₹ crore)
A2: Year/ Month | B2: BSE | F2: Total | G2: NSE | K2: Total | L2: MSEI | P2: Total
B3: Currency Futures | D3: Currency Options | G3: Currency Futures | I3: Currency Options | L3: Currency Futures | N3: Currency Options
B4: MTM Settlement | C4: Final Settlement | D4: Premium Settlement | E4: Exercise Settlement | G4: MTM Settlement | H4: Final Settlement | I4: Premium Settlement | J4: Exercise Settlement | L4: MTM Settlement | M4: Final Settlement | N4: Premium Settlement | O4: Exercise Settlement
A5: 2023-24 | B5: 6550.62 | C5: 194.57 | D5: 9296.52 | E5: 381.98 | F5: 16423.69 | G5: 6645.7643 | H5: 209.98747 | I5: 2068.4298 | J5: 745.28977 | K5: 9669.4714 | L5: NA | M5: NA | N5: NA | O5: NA | P5: NA
A6: 2024-25$ | B6: =SUM(B7:B10) -> 1536.87 | C6: =SUM(C7:C10) -> 41.03 | D6: =SUM(D7:D10) -> 150.65 | E6: =SUM(E7:E10) -> 17.79 | F6: =SUM(F7:F10) -> 1746.34 | G6: =SUM(G7:G10) -> 1243.4815 | H6: =SUM(H7:H10) -> 32.703442 | I6: =SUM(I7:I10) -> 152.2969 | ... K6: =SUM(K7:K10) -> 1451.0505 | L6: NA | M6: NA | N6: NA | O6: NA | P6: NA
A7: 45383 | B7: 399.36 | C7: 2.65 | D7: 147.27 | E7: 16.29 | F7: 565.57 | G7: 290.54981 | H7: 1.2335245 | I7: 146.26018 | J7: 17.952042 | K7: 455.99556 | L7: NA | M7: NA | N7: NA | O7: NA | P7: NA
A8: 45413 | B8: 345.68 | C8: 20.85 | D8: 2.33 | E8: 1.27 | F8: 370.13 | G8: 303.24493 | H8: 18.722499 | I8: 3.3531595 | J8: 3.7566815 | K8: 329.07727 | L8: NA | M8: NA | N8: NA | O8: NA | P8: NA
A9: 45444 | B9: 608.74 | C9: 16.01 | D9: 0.56 | E9: 0.15 | F9: 625.46 | G9: 498.90203 | H9: 11.680054 | I9: 1.720201 | J9: 0.61476663 | K9: 512.91705 | L9: NA | M9: NA | N9: NA | O9: NA | P9: NA
A10: 45474 | B10: 183.09 | C10: 1.52 | D10: 0.49 | E10: 0.08 | F10: 185.18 | G10: 150.78474 | H10: 1.0673644 | I10: 0.96335125 | J10: 0.2451919 | K10: 153.06065 | L10: NA | M10: NA | N10: NA | O10: NA | P10: NA
A12: Source: BSE, NSE and MSEI.
A13: NA - Not Available - In view of interoperability of the clearing corporations, this data will be available with the Clearing Corporations
A14: $ indicates as on July 31, 2024

Sheet 45
A1: Table 45: Instrument-wise Turnover in Currency Derivatives Segment of BSE
A2: Year/Month | B2: Turnover (₹ crore) | I2: Open Interest as on last day of the month (in lots)
B3: USDINR | C3: EURINR | D3: GBPINR | E3: JPYINR | F3: EURUSD | G3: GBPUSD | H3: USDJPY | I3: USDINR | J3: EURINR | K3: GBPINR | L3: JPYINR | M3: EURUSD | N3: GBPUSD | O3: USDJPY
A4: 2023-24 | B4: 2288114.6 | C4: 14552.658 | D4: 34351.928 | E4: 8795.9715 | F4: 0.087103065 | G4: 0 | H4: 0.084343625 | I4: 1146547 | J4: 1361 | K4: 7470 | L4: 3407 | M4: 0 | N4: 0 | O4: 0
A5: 2024-25$ | B5: =SUM(B6:B9) -> 30839.647 | C5: =SUM(C6:C9) -> 109.89555 | D5: =SUM(D6:D9) -> 130.21486 | E5: =SUM(E6:E9) -> 42.435428 | F5: =SUM(F6:F9) -> 0 | G5: =SUM(G6:G9) -> 0 | H5: =SUM(H6:H9) -> 0 | I5: =INDEX(I6:I9,COUNT(I6:I9)) -> 535 | J5: =INDEX(J6:J9,COUNT(J6:J9)) -> 0 | K5: =INDEX(K6:K9,COUNT(K6:K9)) -> 0 | L5: =INDEX(L6:L9,COUNT(L6:L9)) -> 0 | M5: =INDEX(M6:M9,COUNT(M6:M9)) -> 0 | N5: =INDEX(N6:N9,COUNT(N6:N9)) -> 0 | O5: =INDEX(O6:O9,COUNT(O6:O9)) -> 0
A6: 45383 | B6: 26383.752 | C6: 109.89555 | D6: 130.21486 | E6: 42.435428 | F6: 0 | G6: 0 | H6: 0 | I6: 252110 | J6: 17 | K6: 548 | L6: 10 | M6: 0 | N6: 0 | O6: 0
A7: 45413 | B7: 2011.5061 | C7: 0 | D7: 0 | E7: 0 | F7: 0 | G7: 0 | H7: 0 | I7: 9076 | J7: 0 | K7: 0 | L7: 0 | M7: 0 | N7: 0 | O7: 0
A8: 45444 | B8: 2268.5628 | C8: 0 | D8: 0 | E8: 0 | F8: 0 | G8: 0 | H8: 0 | I8: 45810 | J8: 0 | K8: 0 | L8: 0 | M8: 0 | N8: 0 | O8: 0
A9: 45474 | B9: 175.82632 | C9: 0 | D9: 0 | E9: 0 | F9: 0 | G9: 0 | H9: 0 | I9: 535 | J9: 0 | K9: 0 | L9: 0 | M9: 0 | N9: 0 | O9: 0
A11: Source: BSE
A12: $ indicates as on July 31, 2024

Sheet 46
A1: Table 46: Instrument-wise Turnover in Currency Derivatives of NSE
A2: Year/Month | B2: Turnover ( ₹ crore) | I2: Open Interest as on last day of the month ( in lots)
B3: USDINR | C3: EURINR | D3: GBPINR | E3: JPYINR | F3: EURUSD | G3: GBPUSD | H3: USDJPY | I3: USDINR | J3: EURINR | K3: GBPINR | L3: JPYINR | M3: EURUSD | N3: GBPUSD | O3: USDJPY
A4: 2023-24 | B4: 33624479 | C4: 482803.1 | D4: 887082.6 | E4: 142697.11 | F4: 3473.45 | G4: 2765.37 | H4: 737.51 | I4: 17252112 | J4: 158115 | K4: 260489 | L4: 133270 | M4: 306 | N4: 373 | O4: 38
A5: 2024-25$ | B5: =SUM(B6:B9) -> 618168.13 | C5: =SUM(C6:C9) -> 8266.31 | D5: =SUM(D6:D9) -> 13090.95 | E5: =SUM(E6:E9) -> 2375.9 | F5: =SUM(F6:F9) -> 602.72 | G5: =SUM(G6:G9) -> 895.34 | H5: =SUM(H6:H9) -> 63.29 | I5: =INDEX(I6:I9,COUNT(I6:I9)) -> 1261707 | J5: =INDEX(J6:J9,COUNT(J6:J9)) -> 21945 | K5: =INDEX(K6:K9,COUNT(K6:K9)) -> 29722 | L5: =INDEX(L6:L9,COUNT(L6:L9)) -> 16987 | M5: =INDEX(M6:M9,COUNT(M6:M9)) -> 981 | N5: =INDEX(N6:N9,COUNT(N6:N9)) -> 813 | O5: =INDEX(O6:O9,COUNT(O6:O9)) -> 233
A6: 45383 | B6: 354714.26 | C6: 5457.25 | D6: 9130.51 | E6: 1761.07 | F6: 120.69 | G6: 427.2 | H6: 15.61 | I6: 4135879 | J6: 22073 | K6: 15433 | L6: 10464 | M6: 1904 | N6: 19090 | O6: 318
A7: 45413 | B7: 108114.93 | C7: 1005.53 | D7: 1120.1 | E7: 203.68 | F7: 125.51 | G7: 393.48 | H7: 8.38 | I7: 3018383 | J7: 18716 | K7: 17914 | L7: 5104 | M7: 2907 | N7: 941 | O7: 220
A8: 45444 | B8: 110875.45 | C8: 930.84 | D8: 1128.03 | E8: 83.59 | F8: 169.57 | G8: 31.06 | H8: 21.32 | I8: 2858464 | J8: 12750 | K8: 6616 | L8: 2378 | M8: 909 | N8: 287 | O8: 847
A9: 45474 | B9: 44463.49 | C9: 872.69 | D9: 1712.31 | E9: 327.56 | F9: 186.95 | G9: 43.6 | H9: 17.98 | I9: 1261707 | J9: 21945 | K9: 29722 | L9: 16987 | M9: 981 | N9: 813 | O9: 233
A11: Source: NSE.
A12: $ indicates as on July 31, 2024

Sheet 47
A1: Table 47: Instrument-wise Turnover in Currency Derivative Segment of MSEI
A2: Year/Month | B2: Turnover (₹ crore) | F2: Open Interest as on last day of the month (in lots)
B3: USDINR | C3: EURINR | D3: GBPINR | E3: JPYINR | F3: USDINR | G3: EURINR | H3: GBPINR | I3: JPYINR
A4: 2023-24 | B4: 247087.8 | C4: 41.063919 | D4: 553.48742 | E4: 55.695218 | F4: 103178 | G4: 0 | H4: 8 | I4: 0
A5: 2024-25$ | B5: =SUM(B6:B9) -> 7141.135 | C5: =SUM(C6:C9) -> 0 | D5: =SUM(D6:D9) -> 0 | E5: =SUM(E6:E9) -> 0 | F5: =INDEX(F6:F9,COUNT(F6:F9)) -> 0 | G5: =IFERROR(INDEX(G6:G9,COUNT(G6:G9)), "0") -> 0 | H5: =IFERROR(INDEX(H6:H9,COUNT(H6:H9)), "0") -> 0 | I5: =IFERROR(INDEX(I6:I9,COUNT(I6:I9)), "0") -> 0
A6: 45383 | B6: 5312.0763 | C6: 0 | D6: 0 | E6: 0 | F6: 40175 | G6: - | H6: - | I6: -
A7: 45413 | B7: 1001.7 | C7: 0 | D7: 0 | E7: 0 | F7: 4 | G7: 0 | H7: 0 | I7: 0
A8: 45444 | B8: 651.57425 | C8: 0 | D8: 0 | E8: 0 | F8: 28000 | G8: 0 | H8: 0 | I8: 0
A9: 45474 | B9: 175.7845 | C9: 0 | D9: 0 | E9: 0 | F9: 0 | G9: 0 | H9: 0 | I9: 0
A11: Source: MSEI
A12: $ indicates as on July 31, 2024

Sheet 48
A1: Table 48: Maturity-wise Turnover in Currency Derivative Segment of BSE (₹ crore)
A2: Year/Month | B2: Currency Futures | G2: Currency Options
B3: Weekly | C3: 1 Month | D3: 2 Months | E3: 3 Months | F3: > 3 Months | G3: Weekly | H3: 1 Month | I3: 2 Months | J3: 3 Months | K3: > 3 Months
A4: 2023-24 | B4: 265155.59 | C4: 1582715.4 | D4: 323528.37 | E4: 14354.015 | F4: 3740.241 | G4: 87232.275 | H4: 51139.151 | I4: 16606.64 | J4: 1343.6427 | K4: 0
A5: 2024-25$ | B5: =SUM(B6:B9) -> 425.1149 | C5: =SUM(C6:C9) -> 223203.36 | D5: =SUM(D6:D9) -> 5922.6467 | E5: =SUM(E6:E9) -> 186.8305 | F5: =SUM(F6:F9) -> 167.4592 | G5: =SUM(G6:G9) -> 91.472 | H5: =SUM(H6:H9) -> 264.4076 | I5: =SUM(I6:I9) -> 0.0168 | ... K5: =SUM(K6:K9) -> 0
A6: 45383 | B6: 425.1149 | C6: 24202.962 | D6: 1328.1263 | E6: 186.7387 | F6: 167.4592 | G6: 91.472 | H6: 264.4076 | I6: 0.0168 | J6: 0 | K6: 0
A7: 45413 | B7: 0 | C7: 196923.91 | D7: 4226.71 | E7: 0 | F7: 0 | G7: 0 | H7: 0 | I7: 0 | J7: 0 | K7: 0
A8: 45444 | B8: 0 | C8: 1900.6691 | D8: 367.8104 | E8: 0.0834 | F8: 0 | G8: 0 | H8: 0 | I8: 0 | J8: 0 | K8: 0
A9: 45474 | B9: 0 | C9: 175.8179 | D9: 0 | E9: 0.0084 | F9: 0 | G9: 0 | H9: 0 | I9: 0 | J9: 0 | K9: 0
A11: Source: BSE
A12: $ indicates as on July 31, 2024

Sheet 49
A1: Table 49: Maturity-wise Turnover in Currency Derivative Segment of NSE (₹ crore)
A2: Year/Month | B2: Currency Futures | G2: Currency Options
B3: Weekly | C3: 1 Month | D3: 2 Months | E3: 3 Months | F3: > 3 Months | G3: Weekly | H3: 1 Month | I3: 2 Months | J3: 3 Months | K3: > 3 Months
A4: 2023-24 | B4: 619188.16 | C4: 4685370.8 | D4: 1501948.9 | E4: 222220.97 | F4: 173012.63 | G4: 19093761 | H4: 7358692.8 | I4: 1360063.1 | J4: 122684.1 | K4: 7094.0754
A5: 2024-25$ | B5: =SUM(B6:B9) -> 31836.108 | C5: =SUM(C6:C9) -> 352480.74 | D5: =SUM(D6:D9) -> 82472.6 | E5: =SUM(E6:E9) -> 4190.5516 | F5: =SUM(F6:F9) -> 6527.3618 | G5: =SUM(G6:G9) -> 57217.539 | H5: =SUM(H6:H9) -> 90327.776 | I5: =SUM(I6:I9) -> 14459.973 | ... K5: =SUM(K6:K9) -> 406.35108
A6: 45383 | B6: 2881.8392 | C6: 160682.56 | D6: 45518.748 | E6: 2917.7947 | F6: 5437.4272 | G6: 54900.825 | H6: 82105.088 | I6: 13265.002 | J6: 3541.6721 | K6: 375.64348
A7: 45413 | B7: 28953.808 | C7: 75037.493 | D7: 125.46981 | E7: 531.0179 | F7: 502.71215 | G7: 2253.3844 | H7: 3540.1048 | I7: 0 | J7: 0 | K7: 27.615788
A8: 45444 | B8: 0.041729 | C8: 83575.053 | D8: 25076.66 | E8: 389.94101 | F8: 270.36146 | G8: 55.232899 | H8: 3220.9741 | I8: 647.45904 | J8: 1.04307 | K8: 3.0918145
A9: 45474 | B9: 0.4190375 | C9: 33185.636 | D9: 11751.723 | E9: 351.79797 | F9: 316.86099 | G9: 8.096835 | H9: 1461.6091 | I9: 547.5121 | J9: 0.9352975 | K9: 0
A11: The weekly contracts for EUR-INR, GBP-INR and JPY-INR futures and options were introduced on December 7, 2020 and the weekly USD-INR futures contracts were launched at NSE from October 11, 2021.
A12: $ indicates as on July 31, 2024
A13: Source: NSE.

Sheet 50
A1: Table 50: Maturity-wise Turnover in Currency Derivative Segment of MSEI (₹ crore)
A2: Year/Month | B2: Currency Futures | G2: Currency Options
B3: Weekly | C3: 1 Month | D3: 2 Months | E3: 3 Months | F3: > 3 Months | G3: Weekly | H3: 1 Month | I3: 2 Months | J3: 3 Months | K3: > 3 Months
A4: 2023-24 | B4: 14.802291 | C4: 145944.96 | D4: 72897.092 | E4: 28876.608 | F4: 4.5848877 | G4: 0 | H4: 0 | I4: 0 | J4: 0 | K4: 0
A5: 2024-25$ | B5: =SUM(B6:B9) -> 0.7835895 | C5: =SUM(C6:C9) -> 4984.0877 | D5: =SUM(D6:D9) -> 2156.1634 | E5: =SUM(E6:E9) -> 0.100318 | F5: =SUM(F6:F9) -> 0 | G5: =SUM(G6:G9) -> 0 | H5: =SUM(H6:H9) -> 0 | I5: =SUM(I6:I9) -> 0 | ... K5: =SUM(K6:K9) -> 0
A6: 45383 | B6: 0.7835895 | C6: 3389.297 | D6: 1921.8954 | E6: 0.100318 | F6: 0 | G6: 0 | H6: 0 | I6: 0 | J6: 0 | K6: 0
A7: 45413 | B7: 0 | C7: 1001.7 | D7: 0 | E7: 0 | F7: 0 | G7: 0 | H7: 0 | I7: 0 | J7: 0 | K7: 0
A8: 45444 | B8: 0 | C8: 417.30625 | D8: 234.268 | E8: 0 | F8: 0 | G8: 0 | H8: 0 | I8: 0 | J8: 0 | K8: 0
A9: 45474 | B9: 0 | C9: 175.7845 | D9: 0 | E9: 0 | F9: 0 | G9: 0 | H9: 0 | I9: 0 | J9: 0 | K9: 0
A11: Source: MSEI
A12: $ indicates as on July 31, 2024

Sheet 51
A1: Table 51: Trading Statistics of Interest Rate Futures at BSE, NSE and MSEI (Value in ₹ crore)
A2: Year/ Month | B2: No. of Trading Days | C2: BSE | G2: NSE | K2: MSEI
C3: Interest Rate Futures | E3: Open Interest at the end of | G3: Interest Rate Futures | I3: Open Interest at the end of | K3: Interest RateFutures | M3: Open Interest at the end of
C4: No. of Contracts | D4: Traded Value | E4: No. of Contracts | F4: Value | G4: No. of Contracts | H4: Traded Value | I4: No. of Contracts | J4: Value | K4: No. of Contracts | L4: Traded Value | M4: No. of Contracts | N4: Value
A5: 2023-24 | B5: 240 | C5: 1443270 | D5: 28700.029 | E5: 1000 | F5: 20.14314 | G5: 1471765 | H5: 29570.77 | I5: 36097 | J5: 720.7763 | K5: - | L5: - | M5: - | N5: -
A6: 2024-25$ | B6: =SUM(B7:B10) -> 79 | C6: =SUM(C7:C10) -> 0 | D6: =SUM(D7:D10) -> 0 | E6: =INDEX(E7:E10,COUNT(E7:E10)) -> 0 | F6: =INDEX(F7:F10,COUNT(F7:F10)) -> 0 | G6: =SUM(G7:G10) -> 398839 | H6: =SUM(H7:H10) -> 8028.15 | I6: =INDEX(I7:I10,COUNT(I7:I10)) -> 39082 | J6: =INDEX(J7:J10,COUNT(J7:J10)) -> 784.4836 | K6: - | L6: - | M6: - | N6: -
A7: 45383 | B7: 18 | C7: 0 | D7: 0 | E7: 0 | F7: 0 | G7: 88690 | H7: 1772.13 | I7: 39210 | J7: 775.5221 | K7: - | L7: - | M7: - | N7: -
A8: 45413 | B8: 20 | C8: 0 | D8: 0 | E8: 0 | F8: 0 | G8: 111208 | H8: 2238.99 | I8: 39430 | J8: 787.3349 | K8: - | L8: - | M8: - | N8: -
A9: 45444 | B9: 19 | C9: 0 | D9: 0 | E9: 0 | F9: 0 | G9: 110642 | H9: 2231.21 | I9: 39728 | J9: 793.4221 | K9: - | L9: - | M9: - | N9: -
A10: 45474 | B10: 22 | C10: 0 | D10: 0 | E10: 0 | F10: 0 | G10: 88299 | H10: 1785.82 | I10: 39082 | J10: 784.4836 | K10: - | L10: - | M10: - | N10: -
A12: Source: BSE, NSE and MSEI
A13: $ indicates as on July 31, 2024

Sheet 52
A1: Table 52: Settlement Statistics in Interest Rate Futures at BSE, NSE and MSEI (₹ crore)
A2: Year/ Month | B2: BSE | D2: NSE | F2: MSEI
B3: MTM Settlement | C3: Physical Delivery Settlement | D3: MTM Settlement | E3: Physical Delivery Settlement | F3: MTM Settlement | G3: Physical Delivery Settlement
A4: 2023-24 | B4: 135.67189 | C4: 2.021788 | D4: 388.70098 | E4: 5.0480749 | F4: 0 | G4: 0
A5: 2024-25$ | B5: =SUM(B6:B9) -> 17.158323 | C5: =SUM(C6:C9) -> 0.03131 | D5: =SUM(D6:D9) -> 62.503867 | E5: =SUM(E6:E9) -> 0.29807918 | F5: =SUM(F6:F9) -> 0 | G5: =SUM(G6:G9) -> 0
A6: 45383 | B6: 0.512308 | C6: 0 | D6: 16.106141 | E6: 0.09585918 | F6: 0 | G6: 0
A7: 45413 | B7: 2.030088 | C7: 0 | D7: 18.213195 | E7: 0.0249168 | F7: 0 | G7: 0
A8: 45444 | B8: 10.538827 | C8: 0.016325 | D8: 19.767966 | E8: 0.01985234 | F8: 0 | G8: 0
A9: 45474 | B9: 4.0771 | C9: 0.014985 | D9: 8.4165655 | E9: 0.15745086 | F9: NA | G9: -
A11: Source: NSE, BSE and MSEI
A12: $ indicates as on July 31, 2024

Sheet 53
A1: Table 53: Trends in Foreign Portfolio Investment
A2: Year / Month | B2: Gross Purchase (₹ crore) | C2: Gross Sales (₹ crore) | D2: Net Investment (₹ crore) | E2: Net Investment (US $ mn.) | F2: Cumulative Net Investment (US $ mn.)
A3: 2023-24 | B3: 3617496.7 | C3: 3278432 | D3: 339064.62 | E3: 41044.09 | F3: 300808.43
A4: 2024-25$ | B4: =SUM(B5:B8) -> 1704170.9 | C4: =SUM(C5:C8) -> 1642788.3 | D4: =SUM(D5:D8) -> 61382.6 | E4: =SUM(E5:E8) -> 7361.35 | F4: =F3+E4 -> 308169.78
A5: 45383 | B5: 360879.1 | C5: 377139.12 | D5: -16260.02 | E5: -1944.68 | F5: =F3+E5 -> 298863.75
A6: 45413 | B6: 371456.14 | C6: 384367 | D6: -12910.86 | E6: -1540.86 | F6: 297322.89
A7: 45444 | B7: 535577.62 | C7: 493820.18 | D7: 41757.44 | E7: 5007.18 | F7: 302330.07
A8: 45474 | B8: 436258.05 | C8: 387462.01 | D8: 48796.04 | E8: 5839.71 | F8: =F7+E8 -> 308169.78
A9: Source: NSDL, CDSL
A10: $ indicates as on July 31, 2024

Sheet 54
A1: Table 54: Notional Value of Offshore Derivative Instruments (ODIs) compared to Assets Under Custody (AUC) of FPIs (₹ crore)
A2: Year / Month | B2: Notional value of ODIs on Equity, Debt , Hybrid securities & Derivatives (₹ crore) | C2: Notional value of ODIs on Equity, Debt , Hybrid securities excluding Derivatives (₹ crore) | D2: Assets Under Custody of FPIs (₹ crore) | E2: Notional value of ODIs on Equity, Debt & Hybrid securities including Derivatives as % of Assets Under Custody of FPIs | F2: Notional value of ODIs on Equity, Debt and Hybrid securities excluding Derivatives as % of Assets Under Custody of FPIs
A3: 2023-24 | B3: 149119.92 | C3: 149119.92 | D3: 6953988 | E3: 2.1443798 | F3: 2.1443798
A4: 2023-24
A5: 45383 | B5: To be updated
A6: 45443
A7: 45473
A8: 45504
A9: Notes: 1. Figures are compiled based on reports submitted by FPIs/deemed FPIs issuing ODIs. 2. AUC Figures are compiled on the basis of reports submitted by custodians & does not includes positions taken by FPIs in derivatives. 3. The total value of ODIs excludes the unhedged positions & portfolio hedging positions taken by the FPIs issuing ODIs.
A10: $ indicates as on March 31, 2024
A11: Source: NSDL.

Sheet 55
A1: Table 55: Assets under the Custody of Custodians (Amount in ₹ crore)
A3: Client | B3: FPIs | D3: Foreign Depositories | F3: FDI | H3: FVCI | J3: OCBs | L3: NRIs | N3: Mutual Funds | P3: Corporates | R3: Banks | T3: Insurance Companies | V3: Local Pension Funds | X3: Financial Institutions | Z3: Others | AB3: Total
B4: No. | C4: Amount | D4: No. | E4: Amount | F4: No. | G4: Amount | H4: No. | I4: Amount | J4: No. | K4: Amount | L4: No. | M4: Amount | N4: No. | O4: Amount | P4: No. | Q4: Amount | R4: No. | S4: Amount | T4: No. | U4: Amount | V4: No. | W4: Amount | X4: No. | Y4: Amount | Z4: No. | AA4: Amount | AB4: No. | AC4: Amount
A5: 2023-24 | B5: 11365 | C5: 6953987.7 | D5: 9 | E5: 526941.28 | F5: 3382 | G5: 2723152.5 | H5: 234 | I5: 40878.49 | J5: 23 | K5: 627.4 | L5: 2071 | M5: 6760.93 | N5: 1563 | O5: 4702435.4 | P5: 1677 | Q5: 315572.77 | R5: 88 | S5: 786385.51 | T5: 811 | U5: 3691165.7 | V5: 141 | W5: 1149735.9 | X5: 21 | Y5: 47547.05 | Z5: 63193 | AA5: 2284017.5 | AB5: 84578 | AC5: 23229208
A6: 2024-25$ | B6: =INDEX(B7:B18,COUNT(B7:B18)) -> 11667 | C6: =INDEX(C7:C18,COUNT(C7:C18)) -> 8038981.5 | D6: =INDEX(D7:D18,COUNT(D7:D18)) -> 9 | E6: =INDEX(E7:E18,COUNT(E7:E18)) -> 585683.86 | F6: =INDEX(F7:F18,COUNT(F7:F18)) -> 3575 | G6: =INDEX(G7:G18,COUNT(G7:G18)) -> 3099751.2 | H6: =INDEX(H7:H18,COUNT(H7:H18)) -> 236 | I6: =INDEX(I7:I18,COUNT(I7:I18)) -> 44482.11 | ... AC6: =INDEX(AC7:AC18,COUNT(AC7:AC18)) -> 26665628
A7: 45383 | B7: 11430 | C7: 7155781.9 | D7: 9 | E7: 543626.87 | F7: 3429 | G7: 2817729.1 | H7: 236 | I7: 42437.18 | J7: 23 | K7: 686.7 | L7: 2154 | M7: 7243.41 | N7: 1564 | O7: 4960090.8 | P7: 1782 | Q7: 322224.53 | R7: 88 | S7: 770469.53 | T7: 814 | U7: 3784190.5 | V7: 141 | W7: 1169293.6 | X7: 21 | Y7: 48302.44 | Z7: 66377 | AA7: 2340309.3 | AB7: 88068 | AC7: 23962386
A8: =EOMONTH(A7,1) -> 45443 | B8: 11503 | C8: 7187455.1 | D8: 9 | E8: 537469.1 | F8: 3487 | G8: 2878459.1 | H8: 233 | I8: 42225.45 | J8: 23 | K8: 638.35 | L8: 2285 | M8: 7384.54 | N8: 1573 | O8: 5052831.2 | P8: 1866 | Q8: 331318.31 | R8: 88 | S8: 763526.05 | T8: 817 | U8: 3809804.2 | V8: 141 | W8: 1189654.7 | X8: 21 | Y8: 47610.45 | Z8: 70642 | AA8: 2366320.3 | AB8: 92688 | AC8: 24214697
A9: =EOMONTH(A8,1) -> 45473 | B9: 11619 | C9: 7708847.7 | D9: 9 | E9: 584958.61 | F9: 3535 | G9: 3001809.4 | H9: 233 | I9: 44218.74 | J9: 23 | K9: 711.9 | L9: 2390 | M9: 8059.06 | N9: 1625 | O9: 5387836.5 | P9: 1984 | Q9: 339672.66 | R9: 88 | S9: 773244.52 | T9: 820 | U9: 3953337 | V9: 141 | W9: 1220904.6 | X9: 21 | Y9: 47410.63 | Z9: 75335 | AA9: 2461801.4 | AB9: =SUM(B9,D9,F9,H9,J9,L9,N9,P9,R9,T9,V9,X9,Z9) -> 97823 | AC9: =SUM(C9,E9,G9,I9,K9,M9,O9,Q9,S9,U9,W9,Y9,AA9) -> 25532813
A10: =EOMONTH(A9,1) -> 45504 | B10: 11667 | C10: 8038981.5 | D10: 9 | E10: 585683.86 | F10: 3575 | G10: 3099751.2 | H10: 236 | I10: 44482.11 | J10: 23 | K10: 793.66 | L10: 2596 | M10: 8752.2 | N10: 1630 | O10: 5689542.2 | P10: 2130 | Q10: 353510.43 | R10: 88 | S10: 840458.03 | T10: 821 | U10: 4124262.9 | V10: 141 | W10: 1253223.1 | X10: 21 | Y10: 54323.68 | Z10: 80934 | AA10: 2571863.4 | AB10: 103871 | AC10: 26665628
A11: =EOMONTH(A10,1) -> 45535
A12: =EOMONTH(A11,1) -> 45565
A13: =EOMONTH(A12,1) -> 45596
A14: =EOMONTH(A13,1) -> 45626
A15: =EOMONTH(A14,1) -> 45657
A16: =EOMONTH(A15,1) -> 45688
A17: =EOMONTH(A16,1) -> 45716
A18: =EOMONTH(A17,1) -> 45747
A19: Notes:
A20: "Others" include Portfolio managers, partnership firms, trusts, depository receipt issues, AIFs, FCCB, HUFs, Brokers etc.
A21: Source: Custodians.
A22: $ indicates as on July 31, 2024

Sheet 56
A1: Table 56: Cumulative Sectoral Investment of Foreign Venture Capital Investors (FVCI) (₹ crore)
A2: Sectors of Economy | B2: As at the end of
B3: 44621 | C3: 44713 | D3: 44805 | E3: 44896 | F3: 44986 | G3: 45078 | H3: 45170 | I3: 45261 | J3: 45352 | K3: 45444
A4: Information technology | B4: 3261 | C4: 3110 | D4: 3176 | E4: 3176 | F4: 3448 | G4: 2300 | H4: 2072 | I4: 2138 | J4: 2040 | K4: 1953
A5: Telecommunications | B5: 166 | C5: 133 | D5: 166 | E5: 57 | F5: 166 | G5: 271 | H5: 136 | I5: 461 | J5: 494 | K5: 166
A6: Pharmaceuticals | B6: 824 | C6: 687 | D6: 687 | E6: 656 | F6: 656 | G6: 656 | H6: 564 | I6: 658 | J6: 658 | K6: 606
A7: Biotechnology | B7: 0 | C7: 0 | D7: 0 | E7: 0 | F7: 0 | G7: 0 | H7: 45 | I7: 0 | J7: 0 | K7: 0
A8: Media/ Entertainment | B8: 594 | C8: 547 | D8: 581 | E8: 213 | F8: 219 | G8: 219 | H8: 187 | I8: 180 | J8: 219 | K8: 219
A9: Services Sector | B9: 1505 | C9: 213 | D9: 206 | E9: 197 | F9: 1416 | G9: 2066 | H9: 2106 | I9: 1899 | J9: 1649 | K9: 1355
A10: Industrial Products | B10: 42 | C10: 12 | D10: 42 | E10: 12 | F10: 12 | G10: 632 | H10: 316 | I10: 188 | J10: 188 | K10: 44
A11: Others | B11: 39570 | C11: 35000 | D11: 39239 | E11: 37132 | F11: 42369 | G11: 37055 | H11: 42119 | I11: 41728 | J11: 48673 | K11: 48854
A12: Total | B12: =SUM(B4:B11) -> 45962 | C12: =SUM(C4:C11) -> 39702 | D12: =SUM(D4:D11) -> 44097 | E12: =SUM(E4:E11) -> 41443 | F12: =SUM(F4:F11) -> 48286 | G12: =SUM(G4:G11) -> 43199 | H12: =SUM(H4:H11) -> 47545 | I12: =SUM(I4:I11) -> 47252 | ... K12: =SUM(K4:K11) -> 53197
A13: Source: SEBI

Sheet 57
A1: Table 57: Trends in Resource Mobilization by Mutual Funds (₹ crore)
A2: Year / Month | B2: Gross Mobilisation | E2: Redemption/Repurchase | H2: Net Inflow/ Outflow | K2: Assets at the End of Period
B3: Pvt. Sector | C3: Public Sector | D3: Total | E3: Pvt. Sector | F3: Public Sector | G3: Total | H3: Pvt. Sector | I3: Public Sector | J3: Total
A4: 2023-24 | B4: 8841564.9 | C4: 2606649.9 | D4: 11448215 | E4: 8532666.8 | F4: 2560846.6 | G4: 11093513 | H4: 308898.01 | I4: 45803.317 | J4: 354701.32 | K4: 5340194.7
A5: 2024-25$ | B5: =SUM(B6:B9) -> 3499098.1 | C5: =SUM(C6:C9) -> 896270.39 | D5: =SUM(D6:D9) -> 4395368.5 | E5: =SUM(E6:E9) -> 3079448.4 | F5: =SUM(F6:F9) -> 820763.15 | G5: =SUM(G6:G9) -> 3900211.6 | H5: =SUM(H6:H9) -> 419649.72 | I5: =SUM(I6:I9) -> 75507.24 | J5: =SUM(J6:J9) -> 495156.96 | K5: =INDEX(K6:K9,COUNT(K6:K9)) -> 6496653.1
A6: 45383 | B6: 881430.03 | C6: 233054.32 | D6: =B6+C6 -> 1114484.3 | E6: 681885.24 | F6: 193366.3 | G6: =E6+F6 -> 875251.55 | H6: 199544.78 | I6: 39688.017 | J6: =H6+I6 -> 239232.8 | K6: 5725898
A7: =EOMONTH(A6,1) -> 45443 | B7: 792839.23 | C7: 195701.4 | D7: 988540.62 | E7: 690962.67 | F7: 187060.95 | G7: 878023.61 | H7: 101876.56 | I7: 8640.4482 | J7: 110517.01 | K7: 5891160.5
A8: =EOMONTH(A7,1) -> 45473 | B8: 836611.86 | C8: 222192.46 | D8: 1058804.3 | E8: 878194.62 | F8: 224246.29 | G8: 1102440.9 | H8: -41582.761 | I8: -2053.8284 | J8: -43636.589 | K8: 6115581.9
A9: =EOMONTH(A8,1) -> 45504 | B9: 988217.02 | C9: 245322.21 | D9: 1233539.2 | E9: 828405.88 | F9: 216089.61 | G9: 1044495.5 | H9: 159811.14 | I9: 29232.603 | J9: 189043.74 | K9: 6496653.1
A10: $ indicates as on July 31, 2024
A11: Source: SEBI.

Sheet 58
A1: Table 58: Scheme-wise Statistics of Mutual Funds
A2: Sr. No. | B2: Scheme Category | C2: 2023-24 | I2: 2024-25$
C3: No. of Schemes as on March 31, 2024 | D3: No of Folios as on March 31, 2024 | E3: Funds Mobilized for the Period (Since April 01, 2023 to March 31, 2024) (₹ crore) | F3: Repurchase/ Redemption for the period (Since April 01, 2023 to March 31, 2024) (₹ crore) | G3: Net Inflow (+ve)/ Outflow (-ve) for the period (Since April 01, 2023 to March 31, 2024) (₹ crore) | H3: Net Assets Under Management as on March 31, 2024 | I3: No.of Schemes as on July 31, 2024 | J3: No.of Folios as on July 31, 2024 | K3: Funds Mobilised for the Period (since April 01, 2024 to July 31, 2024) in Rs. cr | L3: Repurchase/Redemption for the period (since April 01, 2024 to July 31, 2024) in Rs. cr | M3: Net Inflow(ve) / Outflow(-ve) for the period (since April 01, 2024 to July 31, 2024 ) in Rs. cr | N3: Net Asset under Management as on July 31, 2024 in Rs. cr
A4: A | B4: Open ended Schemes
A5: I | B5: Income/Debt Oriented Schemes
A6: 1 | B6: Overnight Fund | C6: 32 | D6: 694136 | E6: 1211968.5 | F6: 1220143.5 | G6: -8174.98 | H6: 89223.42 | I6: 35 | J6: 873876 | K6: 1794412.9 | L6: 1787264 | M6: 7148.9343 | N6: 70482.172
A7: 2 | B7: Liquid Fund | C7: 36 | D7: 1778066 | E7: 999037.64 | F7: 919129.54 | G7: 79908.1 | H7: 419555.59 | I7: 36 | J7: 1782584 | K7: 1559599.6 | L7: 1441267.9 | M7: 118331.73 | N7: 493493.47
A8: 3 | B8: Ultra Short Duration Fund | C8: 25 | D8: 637819 | E8: 59136.16 | F8: 42774.83 | G8: 16361.34 | H8: 97161.26 | I8: 24 | J8: 632446 | K8: 96816.274 | L8: 78184.265 | M8: 18632.009 | N8: 104537.99
A9: 4 | B9: Low Duration Fund | C9: 21 | D9: 930843 | E9: 33319.94 | F9: 22751.68 | G9: 10568.26 | H9: 99019.05 | I9: 20 | J9: 843900 | K9: 60225.129 | L9: 47905.019 | M9: 12320.109 | N9: 105025.55
A10: 5 | B10: Money Market Fund | C10: 22 | D10: 428088 | E10: 96873.87 | F10: 67354.83 | G10: 29519.05 | H10: 140034.52 | I10: 23 | J10: 433155 | K10: 230427.47 | L10: 149743.29 | M10: 80684.178 | N10: 234400.74
A11: 6 | B11: Short Duration Fund | C11: 25 | D11: 502719 | E11: 10767.11 | F11: 5116.49 | G11: 5650.63 | H11: 99138.83 | I11: 23 | J11: 438664 | K11: 20988.196 | L11: 17019.011 | M11: 3969.1855 | N11: 105624.05
A12: 7 | B12: Medium Duration Fund | C12: 15 | D12: 254975 | E12: 1120.4 | F12: 1451.46 | G12: -331.05 | H12: 27349.41 | I12: 15 | J12: 217360 | K12: 736.6699 | L12: 2532.6493 | M12: -1795.9794 | N12: 24830.584
A13: 8 | B13: Medium to Long Duration Fund | C13: 12 | D13: 106555 | E13: 1286.59 | F13: 522.3 | G13: 764.29 | H13: 9883.62 | I13: 12 | J13: 98618 | K13: 709.68827 | L13: 437.35407 | M13: 272.3342 | N13: 11052.023
A14: 9 | B14: Long Duration Fund | C14: 7 | D14: 47668 | E14: 324.97 | F14: 175.95 | G14: 149.01 | H14: 9183.13 | I14: 9 | J14: 69014 | K14: 2699.5533 | L14: 569.21552 | M14: 2130.3378 | N14: 15324.77
A15: 10 | B15: Dynamic Bond Fund | C15: 22 | D15: 232991 | E15: 1509.09 | F15: 1294.8 | G15: 214.29 | H15: 30210.27 | I15: 22 | J15: 216166 | K15: 3236.4019 | L15: 2667.0005 | M15: 569.4014 | N15: 33069.712
A16: 11 | B16: Corporate Bond Fund | C16: 21 | D16: 610771 | E16: 8656.28 | F16: 7429.74 | G16: 1226.54 | H16: 135476.04 | I16: 21 | J16: 538313 | K16: 21046.396 | L16: 18575.502 | M16: 2470.8941 | N16: 154280.13
A17: 12 | B17: Credit Risk Fund | C17: 15 | D17: 238230 | E17: 288.98 | F17: 1252.67 | G17: -963.68 | H17: 24324.52 | I17: 14 | J17: 193899 | K17: 175.49361 | L17: 2096.1525 | M17: -1920.6589 | N17: 21789.598
... A21: 16 | B21: Floater Fund | C21: 13 | D21: 232214 | E21: 13357.49 | F21: 9977.63 | G21: 3379.85 | H21: 58174.5 | I21: 13 | J21: 205947 | K21: 7816.8266 | L21: 7426.2232 | M21: 390.60332 | N21: 53349.189
B22: Sub total - I | C22: 316 | D22: 7207400 | E22: 2442887 | F22: 2304386.1 | G22: 138500.92 | H22: 1347482.6 | I22: 315 | J22: 7016744 | K22: 3816565.3 | L22: 3572149.9 | M22: 244415.47 | N22: 1544181.2
A24: II | B24: Growth/Equity Oriented Schemes
A25: 17 | B25: Multi Cap Fund | C25: 19 | D25: 4281290 | E25: 5316.09 | F25: 4270.59 | G25: 1045.49 | H25: 78415.3 | I25: 26 | J25: 7364238 | K25: 24799.319 | L25: 7637.4032 | M25: 17161.916 | N25: 168365.86
A26: 18 | B26: Large Cap Fund | C26: 31 | D26: 12937115 | E26: 9006.39 | F26: 12365.66 | G26: -3359.26 | H26: 259583.23 | I26: 31 | J26: 14357880 | K26: 22891.015 | L26: 20229.752 | M26: 2661.2636 | N26: 361031.14
A27: 19 | B27: Large & Mid Cap Fund | C27: 26 | D27: 7986403 | E27: 9033.54 | F27: 6014.88 | G27: 3018.66 | H27: 148217.8 | I27: 29 | J27: 10077659 | K27: 22161.145 | L27: 11590.844 | M27: 10570.301 | N27: 257266.5
A28: 20 | B28: Mid Cap Fund | C28: 29 | D28: 11049628 | E28: 12644.72 | F28: 7909.58 | G28: 4735.14 | H28: 218145.99 | I28: 29 | J28: 16029834 | K28: 27009.275 | L28: 18438.447 | M28: 8570.8278 | N28: 378543.82
A29: 21 | B29: Small Cap Fund | C29: 24 | D29: 12267299 | E29: 16076.07 | F29: 5139.37 | G29: 10936.69 | H29: 168434.34 | I29: 28 | J29: 20962913 | K29: 26886.141 | L29: 17580.085 | M29: 9306.0565 | N29: 313488.17
A30: 22 | B30: Dividend Yield Fund | C30: 9 | D30: 752821 | E30: 1394.39 | F30: 584.84 | G30: 809.55 | H30: 16236.99 | I30: 9 | J30: 991819 | K30: 3603.966 | L30: 1666.4992 | M30: 1937.4667 | N30: 30683.972
A31: 23 | B31: Value Fund/Contra Fund | C31: 23 | D31: 4936198 | E31: 6433.32 | F31: 3320.92 | G31: 3112.4 | H31: 104685.73 | I31: 23 | J31: 7016092 | K31: 15545.849 | L31: 7956.9536 | M31: 7588.8958 | N31: 185631.54
A32: 24 | B32: Focused Fund | C32: 27 | D32: 5232806 | E32: 4795.54 | F32: 6888.55 | G32: -2093.01 | H32: 109698.37 | I32: 28 | J32: 5071314 | K32: 9019.1429 | L32: 10560.612 | M32: -1541.4692 | N32: 148161.6
A33: 25 | B33: Sectoral/Thematic Funds | C33: 130 | D33: 13344178 | E33: 13411.02 | F33: 12506.16 | G33: 904.86 | H33: 196178.06 | I33: 174 | J33: 24786304 | K33: 95976.429 | L33: 30858.883 | M33: 65117.545 | N33: 421112.35
A34: 26 | B34: ELSS | C34: 43 | D34: 15301801 | E34: 4541.69 | F34: 5459.99 | G34: -918.31 | H34: 171034.5 | I34: 42 | J34: 16463700 | K34: 8308.0587 | L34: 9784.9082 | M34: -1476.8495 | N34: 249506.99
A35: 27 | B35: Flexi Cap Fund | C35: 36 | D35: 12784279 | E35: 11599.9 | F35: 11434.04 | G35: 165.86 | H35: 272743.18 | I35: 39 | J35: 15377119 | K35: 32741.432 | L35: 21301.684 | M35: 11439.748 | N35: 420165.96
B36: Sub total - II | C36: 397 | D36: 100873818 | E36: 94252.68 | F36: 75894.57 | G36: 18358.08 | H36: 1743373.5 | I36: 458 | J36: 138498872 | K36: 288941.77 | L36: 157606.07 | M36: 131335.7 | N36: 2933957.9
A38: III | B38: Hybrid Schemes
A39: 28 | B39: Conservative Hybrid Fund | C39: 20 | D39: 519553 | E39: 1094.69 | F39: 1165.98 | G39: -71.29 | H39: 24158.37 | I39: 19 | J39: 545408 | K39: 1875.8638 | L39: 2087.8594 | M39: -211.99559 | N39: 28307.356
A40: 29 | B40: Balanced Hybrid Fund/Aggressive Hybrid Fund | C40: 31 | D40: 5291966 | E40: 5628.26 | F40: 7445.59 | G40: -1817.33 | H40: 166686.76 | I40: 31 | J40: 5518271 | K40: 11727.108 | L40: 11423.166 | M40: 303.94258 | N40: 221973.32
A41: 30 | B41: Dynamic Asset Allocation/Balanced Advantage | C41: 29 | D41: 4430919 | E41: 9637.68 | F41: 10680.04 | G41: -1042.36 | H41: 204997.12 | I41: 33 | J41: 4770961 | K41: 21898.867 | L41: 16833.394 | M41: 5065.4732 | N41: 279986.07
A42: 31 | B42: Multi Asset Allocation | C42: 13 | D42: 1139849 | E42: 3726.78 | F42: 1220.27 | G42: 2506.52 | H42: 31148.94 | I42: 24 | J42: 2426363 | K42: 17225.581 | L42: 4173.7781 | M42: 13051.802 | N42: 89592.735
A43: 32 | B43: Arbitrage Fund | C43: 26 | D43: 435281 | E43: 29686.63 | F43: 15965.01 | G43: 13721.62 | H43: 80625.37 | I43: 27 | J43: 532819 | K43: 111423.8 | L43: 69913.11 | M43: 41510.693 | N43: 189349.31
A44: 33 | B44: Equity Savings Fund | C44: 22 | D44: 362326 | E44: 2495.87 | F44: 1771.98 | G44: 723.89 | H44: 17888.92 | I44: 22 | J44: 431125 | K44: 10529.556 | L44: 6105.0692 | M44: 4424.487 | N44: 35571.779
B45: Sub total - III | C45: 141 | D45: 12179894 | E45: 52269.91 | F45: 38248.87 | G45: 14021.04 | H45: 525505.48 | I45: 156 | J45: 14224947 | K45: 174680.78 | L45: 110536.38 | M45: 64144.402 | N45: 844780.57
A47: IV | B47: Solution Oriented Schemes
A48: 34 | B48: Retirement Fund | C48: 26 | D48: 2774489 | E48: 701.19 | F48: 435.96 | G48: 265.23 | H48: 20199.11 | I48: 29 | J48: 2936417 | K48: 1676.6284 | L48: 829.55707 | M48: 847.07134 | N48: 29903.394
A49: 35 | B49: Childrens' Fund | C49: 10 | D49: 2933164 | E49: 336.48 | F49: 182.65 | G49: 153.83 | H49: 15887.98 | I49: 11 | J49: 3002653 | K49: 624.31497 | L49: 348.6296 | M49: 275.68537 | N49: 22086.809
B50: Sub total - IV | C50: 36 | D50: 5707653 | E50: 1037.67 | F50: 618.62 | G50: 419.06 | H50: 36087.08 | I50: 40 | J50: 5939070 | K50: 2300.9434 | L50: 1178.1867 | M50: 1122.7567 | N50: 51990.203
A52: V | B52: Other Schemes
A53: 36 | B53: Index Funds | C53: 185 | D53: 4495761 | E53: 9475.47 | F53: 10125.17 | G53: -649.69 | H53: 175468.04 | I53: 225 | J53: 9735676 | K53: 40010.16 | L53: 15904.248 | M53: 24105.912 | N53: 258148.5
A54: 37 | B54: GOLD ETFs | C54: 13 | D54: 4752363 | E54: 605.99 | F54: 308.01 | G54: 297.97 | H54: 22339.39 | I54: 17 | J54: 5527649 | K54: 3757.8824 | L54: 1262.6257 | M54: 2495.2567 | N54: 34455.147
A55: 38 | B55: Other ETFs | C55: 161 | D55: 12124531 | E55: 28829.61 | F55: 14113.07 | G55: 14716.54 | H55: 538872.99 | I55: 201 | J55: 15490196 | K55: 68121.525 | L55: 36763.525 | M55: 31357.999 | N55: 777300.87
A56: 39 | B56: Fund of funds investing overseas | C56: 50 | D56: 1348079 | E56: 781.08 | F56: 1656.37 | G56: -875.29 | H56: 23869.39 | I56: 55 | J56: 1427286 | K56: 911.06342 | L56: 2330.3861 | M56: -1419.3226 | N56: 25179.631
B57: Sub total - V | C57: 409 | D57: 22720734 | E57: 39692.15 | F57: 26202.62 | G57: 13489.53 | H57: 760549.8 | I57: 498 | J57: 32180807 | K57: 112800.63 | L57: 56260.786 | M57: 56539.845 | N57: 1095084.1
B59: Total A-Open ended Schemes | C59: 1299 | D59: 148689499 | E59: 2630139.4 | F59: 2445350.8 | G59: 184788.63 | H59: 4412998.4 | I59: 1467 | J59: 197860440 | K59: 4395289.5 | L59: 3897731.3 | M59: 497558.18 | N59: 6469994
A61: B | B61: Close Ended Schemes
A62: I | B62: Income/Debt Oriented Schemes
A63: i | B63: Fixed Term Plan | C63: 92 | D63: 134471 | E63: 102.64 | F63: 4850.99 | G63: -4748.35 | H63: 19564.33 | I63: 79 | J63: 67816 | K63: 0 | L63: 1087.9927 | M63: -1087.9927 | N63: 15301.736
A64: ii | B64: Capital Protection Oriented Schemes | C64: 3 | D64: 2883 | E64: 0 | F64: 533.65 | G64: -533.65 | H64: 119.12 | I64: 0 | J64: 0 | K64: 0 | L64: 0 | M64: 0 | N64: 0
A65: iii | B65: Infrastructure Debt Fund | C65: 7 | D65: 52 | E65: 0 | F65: 0 | G65: 0 | H65: 2055.17 | I65: 4 | J65: 30 | K65: 0 | L65: 606.48123 | M65: -606.48123 | N65: 1057.921
A66: iv | B66: Other Debt | C66: 0 | D66: 0 | E66: 0 | F66: 0 | G66: 0 | H66: 0 | I66: 1 | J66: 203433 | K66: 79.03 | L66: 306.57 | M66: -227.54 | N66: 5482.19
B67: Sub total | C67: 102 | D67: 137406 | E67: 102.64 | F67: 5384.64 | G67: -5282 | H67: 21738.61 | I67: 84 | J67: 271279 | K67: 79.03 | L67: 2001.0439 | M67: -1922.0139 | N67: 21841.847
A69: II | B69: Growth/Equity Oriented Schemes
A70: i | B70: ELSS | C70: 19 | D70: 292193 | E70: 0 | F70: 93.94 | G70: -93.94 | H70: 3723.64 | I70: 18 | J70: 272196 | K70: 0 | L70: 121.13402 | M70: -121.13402 | N70: 4654.9514
A71: ii | B71: Others | C71: 5 | D71: 9876 | E71: 0 | F71: 1837.48 | G71: -1837.48 | H71: 479.58 | I71: 0 | J71: 0 | K71: 0 | L71: 0 | M71: 0 | N71: 0
B72: Sub total | C72: 24 | D72: 302069 | E72: 0 | F72: 1931.42 | G72: -1931.42 | H72: 4203.22 | I72: 18 | J72: 272196 | K72: 0 | L72: 121.13402 | M72: -121.13402 | N72: 4654.9514
A74: III | B74: Other Schemes | C74: 0 | D74: 0 | E74: 0 | F74: 0 | G74: 0 | H74: 0 | I74: 0 | J74: 0 | K74: 0 | L74: 0 | M74: 0 | N74: 0
B76: Total B -Close ended Schemes | C76: 126 | D76: 439475 | E76: 102.64 | F76: 7316.05 | G76: -7213.41 | H76: 25941.83 | I76: 102 | J76: 543475 | K76: 79.03 | L76: 2122.1779 | M76: -2043.1479 | N76: 26496.798
A78: C | B78: Interval Schemes
A79: I | B79: Income/Debt Oriented Schemes | C79: 12 | D79: 2734 | E79: 11.01 | F79: 753.31 | G79: -742.3 | H79: 246.94 | I79: 12 | J79: 2379 | K79: 0.022348423 | L79: 358.08568 | M79: -358.06333 | N79: 162.25405
A81: II | B81: Growth Oriented Schemes | C81: 0 | D81: 0 | E81: 0 | F81: 0 | G81: 0 | H81: 0 | I81: 0 | J81: 0 | K81: 0 | L81: 0 | M81: 0 | N81: 0
A83: III | B83: Other Schemes | C83: 0 | D83: 0 | E83: 0 | F83: 0 | G83: 0 | H83: 0 | I83: 0 | J83: 0 | K83: 0 | L83: 0 | M83: 0 | N83: 0
B85: Total C -Interval Schemes | C85: 12 | D85: 2734 | E85: 11.01 | F85: 753.31 | G85: -742.3 | H85: 246.94 | I85: 12 | J85: 2379 | K85: 0.022348423 | L85: 358.08568 | M85: -358.06333 | N85: 162.25405
B87: Grand Total (A+B+C) | C87: 1437 | D87: 149131708 | E87: 2630253.1 | F87: 2453420.1 | G87: 176832.92 | H87: 4439187.2 | I87: 1581 | J87: 198406294 | K87: 4395368.5 | L87: 3900211.6 | M87: 495156.96 | N87: 6496653.1
B89: Fund of Funds Scheme (Domestic)** | C89: 76 | D89: 1870167 | E89: 2720.01 | F89: 4622.68 | G89: -1902.68 | H89: 67690.49 | I89: 83 | J89: 2494316 | K89: 5946.2969 | L89: 5265.3663 | M89: 680.93062 | N89: 81929.543
A90: Notes:
A91: No.of schemes also includes serial plans.
A92: $ indicates upto July 31 of respective year
A93: Data in respect Fund of Funds Domestic is shown for information only. The same is included in the respective underlying schemes.
A94: Source: SEBI.

Sheet 59
A1: Table 59: Trends in Transactions on Stock Markets by Mutual Funds (₹ crore)
A2: Year / Month | B2: Equity | E2: Debt | H2: Total
B3: Gross Purchases | C3: Gross Sales | D3: Net Purchases /Sales | E3: Gross Purchases | F3: Gross Sales | G3: Net Purchases /Sales | H3: Gross Purchases | I3: Gross Sales | J3: Net Purchases /Sales
A4: 2023-24 | B4: 1689869.2 | C4: 1489137 | D4: 200732.11 | E4: 1900513.2 | F4: 2096290.5 | G4: -195777.35 | H4: 3590382.3 | I4: 3585427.6 | J4: 4954.76
A5: 2024-25$ | B5: =SUM(B6:B9) -> 969655.53 | C5: =SUM(C6:C9) -> 835417.81 | D5: =SUM(D6:D9) -> 134237.72 | E5: =SUM(E6:E9) -> 599562.47 | F5: =SUM(F6:F9) -> 644508.75 | G5: =SUM(G6:G9) -> -44946.28 | H5: =SUM(H6:H9) -> 1569218 | I5: =SUM(I6:I9) -> 1479926.6 | J5: =SUM(J6:J9) -> 89291.44
A6: 45383 | B6: 206765.05 | C6: 173941.35 | D6: =B6-C6 -> 32823.7 | E6: 141518.3 | F6: 126989.36 | G6: =E6-F6 -> 14528.94 | H6: =B6+E6 -> 348283.35 | I6: =C6+F6 -> 300930.71 | J6: =D6+G6 -> 47352.64
A7: =EOMONTH(A6,1) -> 45443 | B7: 250702.03 | C7: 202603.02 | D7: 48099.01 | E7: 181627.12 | F7: 225723.47 | G7: -44096.35 | H7: =B7+E7 -> 432329.15 | I7: =C7+F7 -> 428326.49 | J7: =D7+G7 -> 4002.66
A8: =EOMONTH(A7,1) -> 45473 | B8: 286508.1 | C8: 258282.46 | D8: 28225.64 | E8: 177883.69 | F8: 182683.28 | G8: -4799.59 | H8: =B8+E8 -> 464391.79 | I8: =C8+F8 -> 440965.74 | J8: =D8+G8 -> 23426.05
A9: =EOMONTH(A8,1) -> 45504 | B9: 225680.35 | C9: 200590.98 | D9: 25089.37 | E9: 98533.36 | F9: 109112.64 | G9: -10579.28 | H9: 324213.71 | I9: 309703.62 | J9: 14510.09
A11: This data is compiled on the basis of reports submitted to SEBI by custodians.
A12: Source: SEBI
A13: $ indicates as on July 31, 2024

Sheet 60
A1: Table 60: Assets Managed by Portfolio Managers
A2: Year / Month | B2: June, 2024 | G2: June, 2023
A3: Particulars | B3: Discretionary# | C3: Non-Discretionary | D3: Co-Investment | E3: Advisory | F3: Total | G3: Discretionary | H3: Non-Discretionary | I3: Co-Investment | J3: Advisory** | K3: Total
A4: No. of Clients | B4: 164154 | C4: 5518 | D4: 326 | E4: 1417 | F4: 171415 | G4: 137987 | H4: 4048 | I4: 54 | J4: 1786 | K4: 143875
A5: AUM (₹ crore)
A6: Listed Equity | B6: 352229.62 | C6: 40301.656 | D6: 0 | E6: 0 | F6: 392531.28 | G6: 268738.79 | H6: 23962.665 | I6: 0 | J6: 0 | K6: 292701.45
A7: Unlisted Equity | B7: 1059.7136 | C7: 604.75525 | D7: 1241.04 | E7: 0 | F7: 2905.5089 | G7: 915.69401 | H7: 296.93548 | I7: 411.02 | J7: 0 | K7: 1623.6495
A8: Plain Debt Listed | B8: 2421783.1 | C8: 185803.14 | D8: 0 | E8: 0 | F8: 2607586.2 | G8: 2090210.3 | H8: 145788.36 | I8: 0 | J8: 0 | K8: 2235998.7
A9: Plain Debt Unlisted | B9: 41309.925 | C9: 213.20073 | D9: 376.26 | E9: 0 | F9: 41899.385 | G9: 22213.093 | H9: 139.47 | I9: 86.12 | J9: 0 | K9: 22438.683
A10: Structured Debt Listed | B10: 651.44784 | C10: 865.68085 | D10: 0 | E10: 0 | F10: 1517.1287 | G10: 1389.57 | H10: 1158.33 | I10: 0 | J10: 0 | K10: 2547.9
A11: Structured Debt Unlisted | B11: 77.98 | C11: 10.9 | D11: 577.12 | E11: 0 | F11: 666 | G11: 73.24 | H11: 29.6 | I11: 0 | J11: 0 | K11: 102.84
A12: Derivatives- Equity | B12: 283.32001 | C12: 0 | D12: 0 | E12: 0 | F12: 283.32001 | G12: 232.39242 | H12: 0 | I12: 0 | J12: 0 | K12: 232.39242
A13: Derivatives- Commodity | B13: -1.69 | C13: 0 | D13: 0 | E13: 0 | F13: -1.69 | G13: -0.04 | H13: 0 | I13: 0 | J13: 0 | K13: 0
A14: Derivatives- Others | B14: -0.10999 | C14: 2.02928 | D14: 0 | E14: 0 | F14: 1.91929 | G14: 0 | H14: 0 | I14: 0 | J14: 0 | K14: 0
A15: Mutual Funds | B15: 80240.603 | C15: 53649.158 | D15: 0 | E15: 0 | F15: 133889.76 | G15: 31063.699 | H15: 24571.421 | I15: 1.71 | J15: 0 | K15: 55636.83
A16: Others | B16: 16443.602 | C16: 5819.7489 | D16: 58.61 | E16: 0 | F16: 22321.961 | G16: 12525.719 | H16: 23603.677 | I16: 0.05 | J16: 0 | K16: 36129.446
A17: Total* | B17: 2914077.5 | C17: 287270.27 | D17: 2253.03 | E17: 295168.54 | F17: 3498769.3 | G17: 2427362.5 | H17: 219550.46 | I17: 498.9 | J17: 224298.3 | K17: 2871710.2
A18: Notes:
A19: 1. **Value of Assets for which Advisory Services are being given. | F19: =F17/10^5 -> 34.987693
A20: 2. #Of the June , 2023 AUM, Rs.21,28,202/- Crores are contributed by funds from EPFO/PFs.
A21: 3. Of the June , 2024 AUM, Rs.24,93,200/- Crores are contributed by funds from EPFO/PFs.
A22: 4. The above data is as per submissions made by 420 Nos. of PMS on the SI Portal till July 31, 2024.
F25: 2914078 | G25: 287270 | H25: 2253 | I25: 295169 | J25: =SUM(F25:I25) -> 3498770 | K25: =J25/10^5 -> 34.9877
F26: 2421328 | G26: 213929 | H26: 499 | I26: 214426 | J26: =SUM(F26:I26) -> 2850182 | K26: =J26/10^5 -> 28.50182
K27: =((K25/K26)-1)*100 -> 22.75602

Sheet 61 
A1: Table 61: Progress Report of NSDL & CDSL (Listed Companies)
A2: Parameter | B2: Unit | C2: NSDL (at the end of the period) | H2: CDSL (at the end of the period)
C3: 45504 | D3: 45444 | E3: 45138 | F3: % Change during the year | G3: % Change during the month | H3: 45444 | I3: 45413 | J3: 45078 | K3: % Change during the year | L3: % Change during the month
A4: Number of companies signed up to make their shares available for dematerialization | B4: Number | C4: 6059 | D4: 6017 | E4: 5861 | F4: =IFERROR((C4/E4-1)*100,"-") -> 3.3782631 | G4: =IFERROR((C4/D4-1)*100,"-") -> 0.69802227 | H4: 6443 | I4: 6409 | J4: 6102 | K4: =IFERROR((H4/J4-1)*100,"-") -> 5.5883317 | L4: =IFERROR((H4/I4-1)*100,"-") -> 0.53050398
A5: Number of Depository Participants (registered) | B5: Number | C5: 285 | D5: 285 | E5: 284 | F5: =IFERROR((C5/E5-1)*100,"-") -> 0.35211268 | G5: =IFERROR((C5/D5-1)*100,"-") -> 0 | H5: 572 | I5: 573 | J5: 588 | K5: =IFERROR((H5/J5-1)*100,"-") -> -2.7210884 | L5: =IFERROR((H5/I5-1)*100,"-") -> -0.17452007
A6: Number of Clearing Corporations (connected) | B6: Number | C6: 5 | D6: 5 | E6: 4 | F6: =IFERROR((C6/E6-1)*100,"-") -> 25 | G6: =IFERROR((C6/D6-1)*100,"-") -> 0 | H6: 3 | I6: 3 | J6: 3 | K6: =IFERROR((H6/J6-1)*100,"-") -> 0 | L6: =IFERROR((H6/I6-1)*100,"-") -> 0
A7: Number of Investors Accounts | B7: Lakh | C7: 372.03971 | D7: 367.93916 | E7: 327.63591 | F7: =IFERROR((C7/E7-1)*100,"-") -> 13.552788 | G7: =IFERROR((C7/D7-1)*100,"-") -> 1.1144641 | H7: 1296.3306 | I7: 1254.944 | J7: 907.32 | K7: =IFERROR((H7/J7-1)*100,"-") -> 42.874687 | L7: =IFERROR((H7/I7-1)*100,"-") -> 3.2978825
A8: Quantity of Shares Dematerialized | B8: Crore | C8: 75406.845 | D8: 74579.778 | E8: 68795.515 | F8: =IFERROR((C8/E8-1)*100,"-") -> 9.6101179 | G8: =IFERROR((C8/D8-1)*100,"-") -> 1.1089698 | H8: 36120.661 | I8: 35662.528 | J8: 31642.73 | K8: =IFERROR((H8/J8-1)*100,"-") -> 14.151533 | L8: =IFERROR((H8/I8-1)*100,"-") -> 1.2846353
A9: Value of Shares Dematerialized | B9: ₹ Crore | C9: 39144211 | D9: 37088786 | E9: 26306308 | F9: =IFERROR((C9/E9-1)*100,"-") -> 48.801618 | G9: =IFERROR((C9/D9-1)*100,"-") -> 5.5419062 | H9: 6920262.6 | I9: 6564625.7 | J9: 4152401.4 | K9: =IFERROR((H9/J9-1)*100,"-") -> 66.656879 | L9: =IFERROR((H9/I9-1)*100,"-") -> 5.4174748
A10: Quantity of Securities Dematerialized # | B10: Crore | C10: 87328.493 | D10: 84892.561 | E10: 76150.555 | F10: =IFERROR((C10/E10-1)*100,"-") -> 14.678735 | G10: =IFERROR((C10/D10-1)*100,"-") -> 2.8694296 | H10: 42288.916 | I10: 41552.137 | J10: 36215.52 | K10: =IFERROR((H10/J10-1)*100,"-") -> 16.770147 | L10: =IFERROR((H10/I10-1)*100,"-") -> 1.7731422
A11: Value of Securities Dematerialized # | B11: ₹ Crore | C11: 43660439 | D11: 41483096 | E11: 30314767 | F11: =IFERROR((C11/E11-1)*100,"-") -> 44.023667 | G11: =IFERROR((C11/D11-1)*100,"-") -> 5.2487478 | H11: 7407875.6 | I11: 7029966.9 | J11: 4478940.5 | K11: =IFERROR((H11/J11-1)*100,"-") -> 65.393481 | L11: =IFERROR((H11/I11-1)*100,"-") -> 5.3756831
A12: Quantity of Shares Settled during the Month | B12: Crore | C12: 2922.4368 | D12: 3121.7199 | E12: 2058.8894 | F12: =IFERROR((C12/E12-1)*100,"-") -> 41.942391 | G12: =IFERROR((C12/D12-1)*100,"-") -> -6.3837594 | H12: 5439.6242 | I12: 4594.1011 | J12: 2613.16 | K12: =IFERROR((H12/J12-1)*100,"-") -> 108.16269 | L12: =IFERROR((H12/I12-1)*100,"-") -> 18.404538
A13: Average Quantity of Shares Settled Daily (Quantity of Shares Settled during the Month divided by Actual Settlement Days) | B13: Crore | C13: 132.83804 | D13: 164.30105 | E13: 102.94447 | F13: =IFERROR((C13/E13-1)*100,"-") -> 29.038537 | G13: =IFERROR((C13/D13-1)*100,"-") -> -19.14961 | H13: 247.25565 | I13: 241.79479 | J13: 124.44 | K13: =IFERROR((H13/J13-1)*100,"-") -> 98.694668 | L13: =IFERROR((H13/I13-1)*100,"-") -> 2.2584651
A14: Value of Shares Settled during the Month in Dematerialized Form | B14: ₹ Crore | C14: 1002766.1 | D14: 1135608 | E14: 673375.32 | F14: =IFERROR((C14/E14-1)*100,"-") -> 48.916372 | G14: =IFERROR((C14/D14-1)*100,"-") -> -11.697868 | H14: 683889.96 | I14: 588764.28 | J14: 294708.2 | K14: =IFERROR((H14/J14-1)*100,"-") -> 132.05664 | L14: =IFERROR((H14/I14-1)*100,"-") -> 16.156836
A15: Average Value of Shares Settled Daily (Value of Shares Settled during the Month divided by Actual Settlement Days) | B15: ₹ Crore | C15: 45580.277 | D15: 59768.844 | E15: 33668.766 | F15: =IFERROR((C15/E15-1)*100,"-") -> 35.37852 | G15: =IFERROR((C15/D15-1)*100,"-") -> -23.739068 | H15: 31085.907 | I15: 30987.594 | J15: 14033.72 | K15: =IFERROR((H15/J15-1)*100,"-") -> 121.50868 | L15: =IFERROR((H15/I15-1)*100,"-") -> 0.31726713
... A17: The Ratio of Dematerialized Equity Shares to the total Outstanding Shares Market Value | B17: Percent | C17: 85.3329 | D17: 85.0143 | E17: 85.0517 | F17: =IFERROR((C17/E17-1)*100,"-") -> 0.33062243 | G17: =IFERROR((C17/D17-1)*100,"-") -> 0.37476048 | H17: 15.014396 | I17: 15.021069 | J17: 13.55 | K17: =IFERROR((H17/J17-1)*100,"-") -> 10.807352 | L17: =IFERROR((H17/I17-1)*100,"-") -> -0.044421356
A19: Notes: 1. Shares includes only equity shares.
A20: 2. Securities include common equity shares, preference shares, debenture, MF units, etc.
A21: 3. Quantity and value of shares mentioned are single sided.
A22: 4. #Source for listed securities information: Issuer/ NSE/BSE.
A23: Source: NSDL and CDSL.

Sheet 62
A1: Table 62: Progress of Dematerialisation at NSDL and CDSL (Listed and Unlisted Companies)
A2: Year/ Month | B2: NSDL | G2: CDSL
B3: Number of Companies Available for Dematerialisation | C3: Number of Participants | D3: DPs Locations | E3: Demat Quantity (million securities) | F3: Demat Value (₹ crore) | G3: Number of Companies Available for Dematerialisation | H3: Number of Participants | I3: DPs Locations | J3: Demat Quantity (million securities) | K3: Demat Value (₹ crore)
A4: 2023-24 | B4: 46015 | C4: 281 | D4: 61665 | E4: 3773299.3 | F4: 42344188 | G4: 23060 | H4: 580 | I4: 17487 | J4: 661463.3 | K4: 6420627.6
A5: 2024-25$ | B5: =INDEX(B6:B9,COUNTA(B6:B9)) -> 51301 | C5: =INDEX(C6:C9,COUNTA(C6:C9)) -> 285 | D5: =INDEX(D6:D9,COUNTA(D6:D9)) -> 62525 | E5: =INDEX(E6:E9,COUNTA(E6:E9)) -> 4032001.2 | F5: =INDEX(F6:F9,COUNTA(F6:F9)) -> 49073775 | G5: =INDEX(G6:G9,COUNTA(G6:G9)) -> 25718 | H5: =INDEX(H6:H9,COUNTA(H6:H9)) -> 572 | I5: =INDEX(I6:I9,COUNTA(I6:I9)) -> 17683 | ... K5: =INDEX(K6:K9,COUNTA(K6:K9)) -> 7735271.7
A6: 45383 | B6: 46792 | C6: 282 | D6: 62763 | E6: 3860905.8 | F6: 43957388 | G6: 23560 | H6: 578 | I6: 17644 | J6: 670642.36 | K6: 6922743.3
A7: 45413 | B7: 48397 | C7: 282 | D7: 62492 | E7: 3927366.2 | F7: 44576102 | G7: 24093 | H7: 577 | I7: 17661 | J7: 683554.59 | K7: 6973608.3
A8: 45444 | B8: 49661 | C8: 285 | D8: 62513 | E8: 3982690.8 | F8: 47074465 | G8: 24858 | H8: 573 | I8: 17671 | J8: 689967 | K8: 7350540
A9: 45474 | B9: 51301 | C9: 285 | D9: 62525 | E9: 4032001.2 | F9: 49073775 | G9: 25718 | H9: 572 | I9: 17683 | J9: 703105.48 | K9: 7735271.7
A11: Notes : 1. DPs Locations represents the total service centres.
A12: Source: NSDL and CDSL.
A13: $ indicates as on July 31, 2024

Sheet 63
A1: Table 63: Depository Statistics as on July 31, 2024
A2: Particulars | B2: Unit | C2: Debt | E2: Equity | G2: Others | I2: Total
C3: Listed | D3: Unlisted | E3: Listed | F3: Unlisted | G3: Listed | H3: Unlisted | I3: Listed | J3: Unlisted
A4: NSDL
A5: No.of Issuers debt/Companies(equity) | B5: (numbers) | C5: 803 | D5: 3566 | E5: 6059 | F5: 40148 | G5: 404 | H5: 7900 | I5: 7266 | J5: 51614
A6: No.of Active Instruments | B6: (numbers) | C6: 8479 | D6: 16342 | E6: 6308 | F6: 49181 | G6: 2753 | H6: 59814 | I6: 17540 | J6: 125337
A7: Demat Quantity | B7: (lakhs) | C7: 98987.099 | D7: 2914072 | E7: 7540684.5 | F7: 18387154 | G7: 1093177.7 | H7: 10285931 | I7: 8732849.3 | J7: 31587157
A8: Demat Value | B8: (Rs.Crore) | C8: 3266200.9 | D8: 1464560.9 | E8: 39144211 | F8: 1736494.4 | G8: 1250027.1 | H8: 2212280.5 | I8: 43660439 | J8: 5413335.8
A9: Quantity Settled during the Month* | B9: (Lakh) | C9: 525.4782 | D9: 2523.2648 | E9: 292243.68 | F9: 253.30172 | G9: 10028.156 | H9: 919.14392 | I9: 302797.31 | J9: 3695.7104
A10: Value Settled during the month | B10: (Rs.Crores) | C10: 119305.41 | D10: 35810.333 | E10: 1002766.1 | F10: 1873.5355 | G10: 14342.625 | H10: 328.92051 | I10: 1136414.1 | J10: 38012.789
A11: CDSL
A12: No. of Issuers (Debt) / Companies (Equity) | B12: (numbers) | C12: 670 | D12: 842 | E12: 6443 | F12: 16621 | G12: 2595 | H12: 2249 | I12: 9708 | J12: 19712
A13: No. of Active Instruments | B13: (numbers) | C13: 6997 | D13: 7652 | E13: 6640 | F13: 17120 | G13: 21874 | H13: 21244 | I13: 35511 | J13: 46016
A14: Demat Quantity | B14: (lakh) | C14: 4205.0822 | D14: 194855.23 | E14: 3612066.1 | F14: 2238292.5 | G14: 612620.36 | H14: 369015.49 | I14: 4228891.6 | J14: 2802163.2
A15: Demat Value | B15: (Rs.crore) | C15: 76962.434 | D15: 71873.732 | E15: 6920262.6 | F15: 175419.34 | G15: 410650.57 | H15: 80103.011 | I15: 7407875.6 | J15: 327396.08
A16: Quantity Settled during the Month | B16: (lakh) | C16: 54.14709 | D16: 0 | E16: 543962.35 | F16: 0 | G16: 78405.853 | H16: 0 | I16: 622422.35 | J16: 0
A17: Value Settled during the Month | B17: (Rs.crore) | C17: 495.14878 | D17: 0 | E17: 683889.96 | F17: 0 | G17: 56350.986 | H17: 0 | I17: 740736.1 | J17: 0
A19: Note: The categories included in Others are Preference Shares, Mutual Fund Trace Units, IDRs, AIF,Warrants, PTCs, Treasury Bills, Postal Savings Certificate,CPs, CDs and Government Securities.
A20: *Quanttity and value settled does not include settlement details of Warehouse receipts/commodities.
A21: Source: NSDL and CDSL.

Sheet 64
A1: Table 64: Number of Commodities Permitted and Traded at Exchanges during the Month (July 2024)
A2: Exchanges | B2: Particulars | C2: Futures | I2: Options #
C3: Agriculture | D3: Metals other than Bullion | E3: Bullion | F3: Energy | G3: Gems and Stones | H3: Indices | I3: Agriculture | J3: Metals other than Bullion | K3: Bullion | L3: Energy
A4: NCDEX | B4: Permitted for trading | C4: 18 | D4: 1 | E4: 0 | F4: 0 | G4: 0 | H4: 0 | I4: 1 | J4: 0 | K4: 0 | L4: 0
B5: Contracts floated | C5: 17 | D5: 1 | E5: 0 | F5: 0 | G5: 0 | H5: 0 | I5: 1 | J5: 0 | K5: 0 | L5: 0
B6: Traded | C6: 9 | D6: 0 | E6: 0 | F6: 0 | G6: 0 | H6: 0 | I6: 0 | J6: 0 | K6: 0 | L6: 0
A7: MCX | B7: Permitted for trading | C7: 5 | D7: 6 | E7: 2 | F7: 2 | G7: 0 | H7: 2 | I7: 0 | J7: 2 | K7: 2 | L7: 2
B8: Contracts floated | C8: 3 | D8: 6 | E8: 2 | F8: 2 | G8: 0 | H8: 2 | I8: 0 | J8: 2 | K8: 2 | L8: 2
B9: Traded | C9: 2 | D9: 4 | E9: 2 | F9: 2 | G9: 0 | H9: 1 | I9: 0 | J9: 2 | K9: 2 | L9: 2
A10: BSE | B10: Permitted for trading | C10: 1 | D10: 3 | E10: 2 | F10: 2 | G10: - | H10: - | I10: - | J10: - | K10: 2 | L10: 2 | M10: -
B11: Contracts floated | C11: 1 | D11: 1 | E11: 2 | F11: 2 | G11: - | H11: - | I11: 0 | J11: 0 | K11: 2 | L11: 2 | M11: -
B12: Traded | C12: 0 | D12: 0 | E12: 0 | F12: 0 | G12: - | H12: - | I12: 0 | J12: 0 | K12: 0 | L12: 1 | M12: -
A13: NSE | B13: Permitted for trading | C13: 0 | D13: 5 | E13: 2 | F13: 2 | G13: 0 | H13: NA | I13: 0 | J13: 2 | K13: 2 | L13: 2
B14: Contracts floated | C14: 0 | D14: 5 | E14: 2 | F14: 2 | G14: 0 | H14: NA | I14: 0 | J14: 2 | K14: 2 | L14: 2
B15: Traded | C15: 0 | D15: 0 | E15: 1 | F15: 2 | G15: 0 | H15: NA | I15: 0 | J15: 0 | K15: 1 | L15: 2
A16: Note : 1. All contract variants are considered as one commodity
A17: 2. #Options includes both Options on futures & on goods.
A18: Source: NCDEX, MCX, BSE and NSE

Sheet 65
A1: Table 65: Trends in Commodity Index
A2: Year / Month | B2: MCX iCOMDEX Composite
B3: Open | C3: High | D3: Low | E3: Close | F3: Average of Daily Close #
A4: 2023-24 | B4: 13292.54 | C4: 13741.67 | D4: 12310.21 | E4: 13267.91 | F4: 12889.677
A5: 2024-25$ | B5: =B6 -> 13278.55 | C5: =MAX(C6:C9) -> 15090.4 | D5: =MIN(D6:D9) -> 13278.55 | E5: =INDEX(E6:E9,COUNT(E6:E9)) -> 13673.63 | F5: 14277.177
A6: 45412 | B6: 13278.55 | C6: 14582.28 | D6: 13278.55 | E6: 14033.2 | F6: 14076.074
A7: =EOMONTH(A6,1) -> 45443 | B7: 14032.32 | C7: 15090.4 | D7: 13874.77 | E7: 14416.73 | F7: 14429.577
A8: =EOMONTH(A7,1) -> 45473 | B8: 14419.53 | C8: 14622.21 | D8: 14122.52 | E8: 14289.95 | F8: 14323.131
A9: =EOMONTH(A8,1) -> 45504 | B9: 14288.19 | C9: 14718.18 | D9: 13339.08 | E9: 13673.63 | F9: 14208.22
A11: $ indicates as on Jul 31, 2024
A12: # Average during the period.
A13: Source: MCX

Sheet 66
A1: Table 66: Trends in Commodity Derivatives at MCX
A2: Futures
A3: Year / Month | B3: No.of Trading Days | C3: Agriculture | E3: Bullion | G3: Metals | I3: Energy | K3: iCOMDEX Bullion | M3: iCOMDEX Energy | O3: iCOMDEX Metal | Q3: Total Futures | S3: Open Interest at the end of the Period
C4: No. of Contracts | D4: Turnover (₹ crore) | E4: No. of Contracts | F4: Turnover (₹ crore) | G4: No. of Contracts | H4: Turnover (₹ crore) | I4: No. of Contracts | J4: Turnover (₹ crore) | K4: No. of Contracts | L4: Turnover (₹ crore) | M4: No. of Contracts | N4: Turnover (₹ crore) | O4: No. of Contracts | P4: Turnover (₹ crore) | Q4: No. of Contracts | R4: Turnover (₹ crore) | S4: No. of Contracts | T4: Value (₹ crore)
A5: 2023-24 | B5: 255 | C5: 82469 | D5: 5577.2526 | E5: 74597044 | F5: 3111327.6 | G5: 4940335 | H5: 480373.68 | I5: 55598170 | J5: 1382227 | K5: 100063 | L5: 8057.9922 | M5: 0 | N5: 0 | O5: 0 | P5: 0 | Q5: 135318081 | R5: 4987563.5 | S5: 451907 | T5: 31171.627
A6: 2024-25$ | B6: =SUM(B7:B10) -> 88 | C6: =SUM(C7:C10) -> 22135 | D6: =SUM(D7:D10) -> 1458.9584 | E6: =SUM(E7:E10) -> 29416208 | F6: =SUM(F7:F10) -> 1556636.6 | G6: =SUM(G7:G10) -> 2415187 | H6: =SUM(H7:H10) -> 277895.88 | I6: =SUM(I7:I10) -> 19744739 | ... R6: =SUM(R7:R10) -> 2259500.1 | S6: =INDEX(S7:S10,COUNT(S7:S10)) -> 590662 | T6: =INDEX(T7:T10,COUNT(T7:T10)) -> 34871.473
A7: 45412 | B7: 22 | C7: 4225 | D7: 281.39703 | E7: 7848413 | F7: 394580.82 | G7: 617119 | H7: 61086.893 | I7: 4857825 | J7: 94204.633 | K7: 6892 | L7: 621.72976 | M7: 0 | N7: 0 | O7: 0 | P7: 0 | Q7: =C7+E7+G7+I7+K7+M7+O7 -> 13334474 | R7: =D7+F7+H7+J7+L7+N7+P7 -> 550775.48 | S7: 416142 | T7: 32002.227
A8: 45443 | B8: 23 | C8: 4228 | D8: 425.26852 | E8: 7759810 | F8: 415417.44 | G8: 697917 | H8: 82304.672 | I8: 5496931 | J8: 121120.31 | K8: 5274 | L8: 490.43922 | M8: 0 | N8: 0 | O8: 0 | P8: 0 | Q8: =C8+E8+G8+I8+K8+M8+O8 -> 13964160 | R8: =D8+F8+H8+J8+L8+N8+P8 -> 619758.13 | S8: 413302 | T8: 29504.701
A9: 45473 | B9: 20 | C9: 4738 | D9: 265.23963 | E9: 6880554 | F9: 347004.78 | G9: 545473 | H9: 63962.23 | I9: 4607496 | J9: 106903.35 | K9: 3944 | L9: 365.41082 | M9: 0 | N9: 0 | O9: 0 | P9: 0 | Q9: =C9+E9+G9+I9+K9+M9+O9 -> 12042205 | R9: =D9+F9+H9+J9+L9+N9+P9 -> 518501.01 | S9: 423753 | T9: 29648.298
A10: 45504 | B10: 23 | C10: 8944 | D10: 487.05321 | E10: 6927431 | F10: 399633.57 | G10: 554678 | H10: 70542.084 | I10: 4782487 | J10: 99501.814 | K10: 3294 | L10: 301.01429 | M10: 0 | N10: 0 | O10: 0 | P10: 0 | Q10: 12276834 | R10: 570465.53 | S10: 590662 | T10: 34871.473
F11: =E10+G10+I10+K10 -> 12267890
A12: Options
A13: Year / Month | B13: No.of Trading Days | C13: Bullion | G13: Metals | K13: Energy | O13: Total Options | Q13: Open Interest at the end of the Period
C14: Call Options | E14: Put Options | G14: Call Options | I14: Put Options | K14: Call Options | M14: Put Options | O14: No. of Contracts | P14: Notional Value (₹ crore) | Q14: No. of Contracts | R14: Notional Value (₹ crore)
C15: No. of Contracts | D15: Turnover (₹ crore) | E15: No. of Contracts | F15: Turnover (₹ crore) | G15: No. of Contracts | H15: Turnover (₹ crore) | I15: No. of Contracts | J15: Turnover (₹ crore) | K15: No. of Contracts | L15: Turnover (₹ crore) | M15: No. of Contracts | N15: Turnover (₹ crore)
A16: 2023-24 | B16: 255 | C16: 6090765 | D16: 1250428.8 | E16: 4728746 | F16: 1070077.6 | G16: 18061 | H16: 3262.0538 | I16: 8036 | J16: 1432.2481 | K16: 195172465 | L16: 10858414 | M16: 175391669 | N16: 9484301.4 | O16: 381409742 | P16: 22667916 | Q16: 215961 | R16: 13742.384
A17: 2024-25$ | B17: =SUM(B18:B21) -> 88 | C17: =SUM(C18:C21) -> 5174027 | D17: =SUM(D18:D21) -> 1040353.4 | E17: =SUM(E18:E21) -> 4358961 | F17: =SUM(F18:F21) -> 966938.48 | G17: =SUM(G18:G21) -> 25954 | H17: =SUM(H18:H21) -> 5442.306 | I17: =SUM(I18:I21) -> 11837 | ... P17: =SUM(P18:P21) -> 13457698 | Q17: =INDEX(Q18:Q21,COUNT(Q18:Q21)) -> 325242 | R17: =INDEX(R18:R21,COUNT(R18:R21)) -> 23498.207
A18: 45412 | B18: 22 | C18: 1046002 | D18: 184944.92 | E18: 1225461 | F18: 249899.63 | G18: 5313 | H18: 985.54 | I18: 1681 | J18: 332.64 | K18: 22498827 | L18: 1340705.4 | M18: 19469765 | N18: 1141877 | O18: =C18+E18+G18+I18+K18+M18 -> 44247049 | P18: =D18+F18+H18+J18+L18+N18 -> 2918745.1 | Q18: 231301 | R18: 20974.923
A19: 45443 | B19: 23 | C19: 1003905 | D19: 262297.64 | E19: 918768 | F19: 263394.47 | G19: 5820 | H19: 1285.13 | I19: 3848 | J19: 839.34 | K19: 29146082 | L19: 1547729.2 | M19: 26517179 | N19: 1403775.6 | O19: =C19+E19+G19+I19+K19+M19 -> 57595602 | P19: =D19+F19+H19+J19+L19+N19 -> 3479321.5 | Q19: 251836 | R19: 18997.353
A20: 45473 | B20: 20 | C20: 1808477 | D20: 280385.34 | E20: 1279742 | F20: 201103.64 | G20: 6122 | H20: 1321.6125 | I20: 2158 | J20: 453.29752 | K20: 25989049 | L20: 1405958.7 | M20: 23447060 | N20: 1252851.3 | O20: =C20+E20+G20+I20+K20+M20 -> 52532608 | P20: =D20+F20+H20+J20+L20+N20 -> 3142073.9 | Q20: 231910 | R20: 19628.43
A21: 45504 | B21: 23 | C21: 1315643 | D21: 312725.52 | E21: 934990 | F21: 252540.74 | G21: 8699 | H21: 1850.0235 | I21: 4150 | J21: 862.27333 | K21: 31314291 | L21: 1764100.5 | M21: 27982511 | N21: 1585478.2 | O21: 61560284 | P21: 3917557.2 | Q21: 325242 | R21: 23498.207
A23: $ indicates as on July 31, 2024
A24: Source: MCX
A25: Note: Options Turnover is based on Notional value (i.e. Strike Price + Premium).

Sheet 67
A1: Table 67: Trends in Commodity Derivatives at NCDEX
A2: Year / Month | B2: No.of Trading Days | C2: Futures | M2: Options
C3: Agriculture | E3: Agridex Index | G3: Metal | I3: Total Futures | K3: Open interest at the end of the period | M3: Call options | O3: Put options | Q3: Total Options | S3: Open Interest at the end of the Period
C4: No. of Contracts | D4: Turnover (₹ crore) | E4: No. of Contracts | F4: Turnover (₹ crore) | G4: No. of Contracts | H4: Turnover (₹ crore) | I4: No. of Contracts | J4: Turnover (₹ crore) | K4: No. of Contracts | L4: Value (₹ crore) | M4: No. of Contracts | N4: Turnover (₹ crore) | O4: No. of Contracts | P4: Turnover (₹ crore) | Q4: No. of Contracts | R4: Turnover (₹ crore) | S4: No. of Contracts | T4: Notional Value (₹ crore)
A5: 2023-24 | B5: 244 | C5: 4987448 | D5: 205162.15 | E5: 0 | F5: 0 | G5: 20603 | H5: 940.49365 | I5: 5008051 | J5: 206101.65 | K5: 55916 | L5: 2082 | M5: 283 | N5: 9.886 | O5: 0 | P5: 0 | Q5: 283 | R5: 9.88606 | S5: 0 | T5: 0
A6: 2024-25$ | B6: =SUM(B7:B10) -> 82 | C6: =SUM(C7:C10) -> 1294563 | D6: =SUM(D7:D10) -> 50437 | E6: =SUM(E7:E10) -> 0 | F6: =SUM(F7:F10) -> 0 | G6: =SUM(G7:G10) -> 16 | H6: =SUM(H7:H10) -> 1 | I6: =SUM(I7:I10) -> 1294579 | ... R6: =SUM(R7:R10) -> 416.39022 | S6: =INDEX(S7:S10,COUNT(S6:S10)) -> 0 | T6: =INDEX(T7:T10,COUNT(T6:T10)) -> 0
A7: 45412 | B7: 20 | C7: 342777 | D7: 12983 | E7: 0 | F7: 0 | G7: 16 | H7: 1 | I7: =C7+E7+G7 -> 342793 | J7: =D7+F7+H7 -> 12984 | K7: 51525 | L7: 2081 | M7: 0 | N7: 0 | O7: 0 | P7: 0 | Q7: =M7+O7 -> 0 | R7: =N7+P7 -> 0 | S7: 0 | T7: 0
A8: 45443 | B8: 21 | C8: 325130 | D8: 13163 | E8: 0 | F8: 0 | G8: 0 | H8: 0 | I8: =C8+E8+G8 -> 325130 | J8: =D8+F8+H8 -> 13163 | K8: 51343 | L8: 2103 | M8: 0 | N8: 0 | O8: 0 | P8: 0 | Q8: =M8+O8 -> 0 | R8: =N8+P8 -> 0 | S8: 0 | T8: 0
A9: 45473 | B9: 19 | C9: 274301 | D9: 11020 | E9: 0 | F9: 0 | G9: 0 | H9: 0 | I9: =C9+E9+G9 -> 274301 | J9: =D9+F9+H9 -> 11020 | K9: 50660 | L9: 2093 | M9: 81 | N9: 2.256 | O9: 48 | P9: 1.25927 | Q9: =M9+O9 -> 129 | R9: =N9+P9 -> 3.51527 | S9: 79 | T9: 2.16
A10: 45504 | B10: 22 | C10: 352355 | D10: 13271 | E10: 0 | F10: 0 | G10: 0 | H10: 0 | I10: 352355 | J10: 13271 | K10: 53622 | L10: 2281 | M10: 10195 | N10: 288.734 | O10: 4499 | P10: 124.14034 | Q10: 14694 | R10: 412.87495 | S10: 1057 | T10: 30.56
A11: Source: NCDEX
A12: $ indicates as on July 31, 2024

Sheet 68
A1: Table 68: Trends in Commodity Derivatives at BSE
A2: Futures
A3: Year / Month | B3: No.of Trading Days | C3: Agriculture | E3: Bullion | G3: Base Metal | I3: Energy | K3: Total | M3: Open Interest at the end of the Period
C4: No. of Contracts | D4: Turnover (₹ crore) | E4: No. of Contracts | F4: Turnover (₹ crore) | G4: No. of Contracts | H4: Turnover (₹ crore) | I4: No. of Contracts | J4: Turnover (₹ crore) | K4: No. of Contracts | L4: Turnover (₹ crore) | M4: No. of Contracts | N4: Turnover (₹ crore)
A5: 2023-24 | B5: 254 | C5: 75 | D5: 3.72935 | E5: 0 | F5: 0 | G5: 21 | H5: 1.02971 | I5: 4 | J5: 0.26 | K5: 100 | L5: 5.01906 | M5: - | N5: -
A6: 2024-25$ | B6: =SUM(B7:B10) -> 88 | C6: =SUM(C7:C10) -> 0 | D6: =SUM(D7:D10) -> 0 | E6: =SUM(E7:E10) -> 0 | F6: =SUM(F7:F10) -> 0 | G6: =SUM(G7:G10) -> 0 | H6: =SUM(H7:H10) -> 0 | I6: =SUM(I7:I10) -> 0 | ... L6: =SUM(L7:L10) -> 0 | M6: =INDEX(M7:M10,COUNT(M7:M10)) -> 0 | N6: =INDEX(N7:N10,COUNT(N7:N10)) -> 0
A7: 45412 | B7: 22 | C7: 0 | D7: 0 | E7: 0 | F7: 0 | G7: 0 | H7: 0 | I7: 0 | J7: 0 | K7: =C7+E7+G7+I7 -> 0 | L7: =D7+F7+H7+J7 -> 0 | M7: 0 | N7: 0
A8: 45443 | B8: 23 | C8: 0 | D8: 0 | E8: 0 | F8: 0 | G8: 0 | H8: 0 | I8: 0 | J8: 0 | K8: =C8+E8+G8+I8 -> 0 | L8: =D8+F8+H8+J8 -> 0 | M8: 0 | N8: 0
A9: 45473 | B9: 20 | C9: 0 | D9: 0 | E9: 0 | F9: 0 | G9: 0 | H9: 0 | I9: 0 | J9: 0 | K9: =C9+E9+G9+I9 -> 0 | L9: =D9+F9+H9+J9 -> 0 | M9: 0 | N9: 0
A10: 45504 | B10: 23 | C10: 0 | D10: 0 | E10: 0 | F10: 0 | G10: 0 | H10: 0 | I10: 0 | J10: 0 | K10: 0 | L10: 0 | M10: 0 | N10: 0
A13: Options
A14: Year / Month | B14: No.of Trading Days | C14: Bullion | G14: Energy | K14: Total | M14: Open Interest at the end of the Period
C15: Call Options | E15: Put Options | G15: Call Options | I15: Put Options | K15: No. of Contracts | L15: Turnover (₹ crore) | M15: No. of Contracts | N15: Turnover (₹ crore)
C16: No. of Contracts | D16: Turnover (₹ crore) | E16: No. of Contracts | F16: Turnover (₹ crore) | G16: No. of Contracts | H16: Turnover (₹ crore) | I16: No. of Contracts | J16: Turnover (₹ crore)
A17: 2023-24 | B17: 254 | C17: 0 | D17: 0 | E17: 0 | F17: 0 | G17: 409 | H17: 30.18703 | I17: 8 | J17: 0.56455 | K17: 417 | L17: 30.75158 | M17: 3 | N17: 0.230706
A18: 2024-25$ | B18: =SUM(B19:B22) -> 88 | C18: =SUM(C19:C22) -> 0 | D18: =SUM(D19:D22) -> 0 | E18: =SUM(E19:E22) -> 0 | F18: =SUM(F19:F22) -> 0 | G18: =SUM(G19:G22) -> 139 | H18: =SUM(H19:H22) -> 10.19294 | I18: =SUM(I19:I22) -> 52 | ... L18: =SUM(L19:L22) -> 13.7709 | M18: =INDEX(M19:M22,COUNT(M19:M22)) -> 0 | N18: =INDEX(N19:N22,COUNT(N19:N22)) -> 0
A19: 45412 | B19: 22 | C19: 0 | D19: 0 | E19: 0 | F19: 0 | G19: 29 | H19: 2.235 | I19: 20 | J19: 1.428 | K19: =C19+E19+G19+I19 -> 49 | L19: =D19+F19+H19+J19 -> 3.663 | M19: 4 | N19: 0.31
A20: 45443 | B20: 23 | C20: 0 | D20: 0 | E20: 0 | F20: 0 | G20: 40 | H20: 2.9 | I20: 10 | J20: 0.67 | K20: =C20+E20+G20+I20 -> 50 | L20: =D20+F20+H20+J20 -> 3.57 | M20: 2 | N20: 0.14
A21: 45473 | B21: 20 | C21: 0 | D21: 0 | E21: 0 | F21: 0 | G21: 42 | H21: 2.96609 | I21: 4 | J21: 0.2851 | K21: =C21+E21+G21+I21 -> 46 | L21: =D21+F21+H21+J21 -> 3.25119 | M21: 0 | N21: 0
A22: 45504 | B22: 23 | C22: 0 | D22: 0 | E22: 0 | F22: 0 | G22: 28 | H22: 2.09185 | I22: 18 | J22: 1.19486 | K22: 46 | L22: 3.28671 | M22: 0 | N22: 0
A24: $ indicates as on July 31, 2024
A25: Note: 1. Conversion factor for Brent Crude Oil of Energy segment is 1 Tonne = 7.33 Barrels
A26: Source: BSE

Sheet 69
A1: Table 69: Trends in Commodity Derivatives at NSE
A2: Futures
A3: Year / Month | B3: No.of Trading Days | C3: Agriculture | E3: Bullion | G3: Energy | I3: Metals | K3: Total | M3: Open Interest at the end of the Period
C4: No. of Contracts | D4: Turnover (₹ crore) | E4: No. of Contracts | F4: Turnover (₹ crore) | G4: No. of Contracts | H4: Turnover (₹ crore) | I4: No. of Contracts | J4: Turnover (₹ crore) | K4: No. of Contracts | L4: Turnover (₹ crore) | M4: No. of Contracts | N4: Value (₹ crore)
A5: 2023-24 | B5: 254 | C5: 0 | D5: 0 | E5: 101 | F5: 10.06604 | G5: 111127 | H5: 5419.6784 | I5: 0 | J5: 0 | K5: 111228 | L5: 5429.2207 | M5: 58 | N5: 2.47
A6: 2024-25$ | B6: =SUM(B7:B10) -> 88 | C6: =SUM(C7:C10) -> 0 | D6: =SUM(D7:D10) -> 0 | E6: =SUM(E7:E10) -> 49 | F6: =SUM(F7:F10) -> 12.937352 | G6: =SUM(G7:G10) -> 541 | H6: =SUM(H7:H10) -> 33.497638 | I6: =SUM(I7:I10) -> 0 | ... L6: =SUM(L7:L10) -> 46.43499 | M6: =INDEX(M7:M10,COUNT(M7:M10)) -> 54 | N6: =INDEX(N7:N10,COUNT(N7:N10)) -> 2.39
A7: 45412 | B7: 22 | C7: 0 | D7: 0 | E7: 11 | F7: 2.692833 | G7: 150 | H7: 8.9870375 | I7: 0 | J7: 0 | K7: 161 | L7: 11.67987 | M7: 13 | N7: 1.06
A8: 45443 | B8: 23 | C8: 0 | D8: 0 | E8: 14 | F8: 3.802629 | G8: 134 | H8: 8.83373 | I8: 0 | J8: 0 | K8: 148 | L8: 12.636359 | M8: 25 | N8: 1.81554
A9: 45473 | B9: 20 | C9: 0 | D9: 0 | E9: 10 | F9: 2.70189 | G9: 127 | H9: 8.28687 | I9: 0 | J9: 0 | K9: 137 | L9: 10.98876 | M9: 16 | N9: 1.287753
A10: 45504 | B10: 23 | C10: 0 | D10: 0 | E10: 14 | F10: 3.74 | G10: 130 | H10: 7.39 | I10: 0 | J10: 0 | K10: =C10+E10+G10+I10 -> 144 | L10: =D10+F10+H10+J10 -> 11.13 | M10: 54 | N10: 2.39
A12: Options
A13: Year / Month | B13: No.of Trading Days | C13: Bullion | G13: Energy | K13: Total | M13: Open Interest at the end of the Period
C14: Call Options | E14: Put Options | G14: Call Options | I14: Put Options | K14: No. of Contracts | L14: Turnover (₹ crore) | M14: No. of Contracts | N14: Notional Value (₹ crore)
C15: No. of Contracts | D15: Turnover (₹ crore) | E15: No. of Contracts | F15: Turnover (₹ crore) | G15: No. of Contracts Traded | H15: Turnover (₹ crore) | I15: No. of Contracts Traded | J15: Turnover (₹ crore)
A16: 2023-24 | B16: 254 | C16: 32528 | D16: 3319.1884 | E16: 29940 | F16: 2809.4286 | G16: 1367980 | H16: 97565.7 | I16: 1668686 | J16: 92575.583 | K16: 3099134 | L16: 196270.17 | M16: 439 | N16: 33.00975
A17: 2024-25$ | B17: =SUM(B18:B21) -> 88 | C17: =SUM(C18:C21) -> 8123 | D17: =SUM(D18:D21) -> 2204.0893 | E17: =SUM(E18:E21) -> 6047 | F17: =SUM(F18:F21) -> 1547.9137 | G17: =SUM(G18:G21) -> 2814860 | H17: =SUM(H18:H21) -> 213361.61 | I17: =SUM(I18:I21) -> 2502338 | ... L17: =SUM(L18:L21) -> 366486.67 | M17: =INDEX(M18:M21,COUNT(M18:M21)) -> 937 | N17: =INDEX(N18:N21,COUNT(N18:N21)) -> 63.04
A18: 45412 | B18: 22 | C18: 4206 | D18: 1093.7545 | E18: 2232 | F18: 533.39063 | G18: 469918 | H18: 38033.996 | I18: 1253338 | J18: 75683.183 | K18: 1729694 | L18: 115344.32 | M18: 407 | N18: 28.34
A19: 45443 | B19: 23 | C19: 2462 | D19: 701.7877 | E19: 933 | F19: 243.88474 | G19: 1267891 | H19: 95694.799 | I19: 296748 | J19: 17266.392 | K19: 1568034 | L19: 113906.86 | M19: 799 | N19: 51.811
A20: 45473 | B20: 20 | C20: 449 | D20: 124.54703 | E20: 995 | F20: 261.63832 | G20: 444730 | H20: 31976.811 | I20: 430453 | J20: 25100.49 | K20: 876627 | L20: 57463.486 | M20: 790 | N20: 53.171
A21: 45504 | B21: 23 | C21: 1006 | D21: 284 | E21: 1887 | F21: 509 | G21: 632321 | H21: 47656 | I21: 521799 | J21: 31323 | K21: 1157013 | L21: 79772 | M21: 937 | N21: 63.04
A22: Source: NSE
A23: $ indicates as on July 31, 2024

Sheet 70
A1: Table 70 : Participant-wise Percentage Share of Turnover in Commodity Derivatives Segment
A2: Year | B2: Farmers / FPOs | C2: VCPs/ Hedger | D2: Proprietary Traders | E2: Domestic Financial Institutional Investors | F2: Foreign Participants | G2: Others
A3: MCX
A4: 2023-24 | B4: 1.5620775e-05 | C4: 1.8583843 | D4: 52.098544 | E4: 0.12731866 | F4: 0.83925305 | G4: 45.077417
A5: 2024-25$ | B5: 2.0463922e-05 | C5: 1.4985912 | D5: 53.987148 | E5: 0.061374041 | F5: 1.0688517 | G5: 43.384012
A6: 45383 | B6: 2.0463922e-05 | C6: 1.4985912 | D6: 53.987148 | E6: 0.061374041 | F6: 1.0688517 | G6: 43.384012
A7: 45413 | B7: 2.0736362e-06 | C7: 1.1974089 | D7: 54.182427 | E7: 0.088129784 | F7: 1.0387464 | G7: 43.493287
A8: 45444 | B8: 1.7483594e-05 | C8: 1.2142828 | D8: 53.777688 | E8: 0.057892687 | F8: 1.1848479 | G8: 43.765271
A9: 45474 | B9: 2.0387597e-05 | C9: 1.3796146 | D9: 53.0127 | E9: 0.098134418 | F9: 1.5492222 | G9: 43.960307
A10: NCDEX
A11: 2023-24 | B11: 0.40935803 | C11: 5.3006491 | D11: 36.346197 | E11: 0.07385619 | F11: 0.00078131564 | G11: 57.869159
A12: 2024-25$ | B12: 0.14092679 | C12: 5.9441995 | D12: 31.4673 | E12: 0.062808511 | F12: 0 | G12: 62.384766
A13: 45383 | B13: 0.1928019 | C13: 8.0141967 | D13: 42.517112 | E13: 0.12402963 | F13: 0 | G13: 49.15186
A14: 45413 | B14: 0.089757197 | C14: 3.9023547 | D14: 20.567768 | E14: 0.0024200139 | F14: 0 | G14: 75.437701
A15: 45444 | B15: 0.17309022 | C15: 8.5190442 | D15: 42.3454 | E15: 0 | F15: 0 | G15: 48.962465
A16: 45474 | B16: 0.13690595 | C16: 7.7833383 | D16: 43.974285 | E16: 0 | F16: 0 | G16: 48.10547
A17: BSE
A18: 2023-24 | B18: 0 | C18: 1.5405191 | D18: 6.0151927 | E18: 0 | F18: 0 | G18: 92.444288
A19: 2024-25$ | B19: 0 | C19: 0 | D19: 50 | E19: 0 | F19: 0 | G19: 50
A20: 45383 | B20: 0 | C20: 0 | D20: 50 | E20: 0 | F20: 0 | G20: 50
A21: 45413 | B21: 0 | C21: 0 | D21: 50 | E21: 0 | F21: 0 | G21: 50
A22: 45444 | B22: 0 | C22: 0 | D22: 50 | E22: 0 | F22: 0 | G22: 50
A23: 45474 | B23: 0 | C23: 0 | D23: 50 | E23: 0 | F23: 0 | G23: 50
A24: NSE
A25: 2023-24 | B25: - | C25: 0.0052353497 | D25: 88.170176 | E25: - | F25: 0.011997863 | G25: 11.809894
A26: 2024-25$ | B26: - | C26: - | D26: 87.9 | E26: - | F26: 0.04 | G26: 12.06
A27: 45383 | B27: - | C27: - | D27: 87.3 | E27: - | F27: 0.02 | G27: 12.69
A28: 45413 | B28: - | C28: - | D28: 88.52 | E28: - | F28: 0.06 | G28: 11.42
A29: 45444 | B29: - | C29: - | D29: 88.55 | E29: - | F29: 0 | G29: 11.45
A30: 45474 | B30: - | C30: - | D30: 88.55 | E30: - | F30: 0 | G30: 11.45
A31: Notes :1.''Category of 'others' include clients which do not fall in specific categories mentioned above, clients registered such as retail, HUF, individual proprietary firms, partnership firms, public and private companies, body corporates, etc.
A32: 2. Data on percentage of participants for financial year is average of the monthly share.
A33: Source: MCX, NCDEX, BSE and NSE
A34: $ indicates as on July 31, 2024

Sheet 71
A1: Table 71: Commodity-wise Turnover and Trading Volume at MCX
A2: Exchange & Segment | B2: Commodity Type | C2: Name of the Commodity Contract | D2: Contract Size | E2: No. of contracts | H2: Value (₹ crore) | K2: Quotation | L2: Close Price | N2: Average Daily Open Interest in July-24
E3: 2024-25$ | F3: 45444 | G3: 45474 | H3: 2024-25$ | I3: 45413 | J3: 45444 | L3: 45413 | M3: 45444 | N3: No. of contracts | O3: Values of Contracts (₹ crore)
A4: MCX Futures | B4: Bullion | C4: Gold | D4: 1 'KG | E4: 750679 | F4: 127922 | G4: 221258 | H4: 537074.51 | I4: 91850.437 | J4: 157303.92 | K4: ₹/10 grams | L4: 71582 | M4: 69655 | N4: 21492.043 | O4: 15415.101
C5: Gold Mini | D5: 100 'Grams | E5: 1993972 | F5: 415306 | G5: 506058 | H5: 142621.04 | I5: 29767.705 | J5: 35989.987 | K5: ₹/10 grams | L5: 71602 | M5: 69375 | N5: 26098.435 | O5: 1858.7227
C6: Gold Guinea | D6: 8 'Grams | E6: 252244 | F6: 47052 | G6: 64179 | H6: 1462.6063 | I6: 275.12318 | J6: 370.7139 | K6: ₹/8 grams | L6: 58196 | M6: 56176 | N6: 5446.5652 | O6: 31.403746
C7: Gold Petals | D7: 1 'Gram | E7: 3175380 | F7: 630668 | G7: 809909 | H7: 2250.113 | I7: 449.92682 | J7: 571.2662 | K7: ₹/1 grams | L7: 7114 | M7: 6866 | N7: 76535.652 | O7: 53.964257
C8: Silver | D8: 30 'KGs | E8: 1963205 | F8: 494560 | G8: 460908 | H8: 515198.61 | I8: 133579.4 | J8: 123218.22 | K8: ₹/ KG | L8: 89540 | M8: 83596 | N8: 28094.609 | O8: 7489.2161
C9: Silver Mini | D9: 5 'KGs | E9: 4856107 | F9: 1219814 | G9: 1073916 | H9: 213460.59 | I9: 55246.606 | J9: 48126.973 | K9: ₹/ KG | L9: 89582 | M9: 83659 | N9: 47569 | O9: 2117.2708
C10: Silver Micro | D10: 1 'KGs | E10: 16424621 | F10: 3945232 | G10: 3791203 | H10: 144569.14 | I10: 35835.585 | J10: 34052.479 | K10: ₹/ KG | L10: 89584 | M10: 83634 | N10: 162369.74 | O10: 1453.8455
C11: Total for Bullion | E11: =SUM(E4:E10) -> 29416208 | F11: =SUM(F4:F10) -> 6880554 | G11: =SUM(G4:G10) -> 6927431 | H11: =SUM(H4:H10) -> 1556636.6 | I11: =SUM(I4:I10) -> 347004.78 | J11: =SUM(J4:J10) -> 399633.57
B12: Base Metals | C12: Aluminium | D12: 5 MT | E12: 211206 | F12: 46999 | G12: 45781 | H12: 24539.277 | I12: 5487.8781 | J12: 5072.2926 | K12: ₹/ KG | L12: 230.4 | M12: 214.55 | N12: 4786.3913 | O12: 531.707
C13: Aluminium Mini | D13: 1 MT | E13: 260674 | F13: 55227 | G13: 49457 | H13: 6088.5987 | I13: 1297.9448 | J13: 1099.3672 | K13: ₹/ KG | L13: 231.85 | M13: 215.45 | N13: 2675.3913 | O13: 59.615005
C14: Copper | D14: 2.5 MT | E14: 799095 | F14: 184993 | G14: 234185 | H14: 170735.07 | I14: 39628.064 | J14: 48822.929 | K14: ₹/ KG | L14: 840.5 | M14: 807.4 | N14: 11443.522 | O14: 2371.8461
C15: Lead | D15: 5 MT | E15: 62798 | F15: 14627 | G15: 15119 | H15: 5951.4075 | I15: 1381.0423 | J15: 1422.6587 | K15: ₹/ KG | L15: 189.6 | M15: 188.7 | N15: 673.73913 | O15: 63.44346
C16: Lead Mini | D16: 1 MT | E16: 62488 | F16: 14332 | G16: 12358 | H16: 1185.0511 | I16: 270.92668 | J16: 232.86636 | K16: ₹/ KG | L16: 189.75 | M16: 188.55 | N16: 414.95652 | O16: 7.8238172
C17: Nickel | D17: 1.5 MT | E17: 0 | F17: 0 | G17: 0 | H17: 0 | I17: 0 | J17: 0 | K17: ₹/ KG | L17: 1464.3 | M17: 1380.3 | N17: 0 | O17: 0
C18: Steel Rebar | D18: 5 MT | E18: 0 | F18: 0 | G18: 0 | H18: 0 | I18: 0 | J18: 0 | K18: ₹/ MT | L18: 57930 | M18: 60670 | N18: 0 | O18: 0
C19: Zinc | D19: 5 MT | E19: 418948 | F19: 96276 | G19: 81684 | H19: 53948.847 | I19: 12454.941 | J19: 10819.198 | K19: ₹/ KG | L19: 265.35 | M19: 254.15 | N19: 2753.0435 | O19: 365.61185
C20: Zinc Mini | D20: 1 MT | E20: 599978 | F20: 133019 | G20: 116094 | H20: 15447.632 | I20: 3441.4335 | J20: 3072.7727 | K20: ₹/ KG | L20: 265.3 | M20: 254.15 | N20: 2704.7826 | O20: 71.63349
C21: Total for Base Metals | E21: =SUM(E12:E20) -> 2415187 | F21: =SUM(F12:F20) -> 545473 | G21: =SUM(G12:G20) -> 554678 | H21: =SUM(H12:H20) -> 277895.88 | I21: =SUM(I12:I20) -> 63962.23 | J21: =SUM(J12:J20) -> 70542.084
B22: Agri | C22: Cotton | D22: 25 'Bales (170 kg/ Bale) | E22: - | F22: - | H22: - | I22: - | J22: - | K22: ₹/ 1Bale | L22: NA | M22: NA | N22: 0 | O22: 0
C23: Cotton Candy | D23: 48 'Candy (355.56 kg/ Candy) | H23: 810.75085 | I23: 123.78466 | J23: 203.61205 | K23: ₹/ 1Candy | L23: 58800 | M23: 56860 | N23: 316.65217 | O23: 87.532825
C24: CPO | D24: 10 MT | E24: 2942 | F24: 450 | G24: 756 | H24: 648.20753 | I24: 141.45497 | J24: 283.44115 | K24: ₹/10 KG | L24: 0 | M24: 0 | N24: 0 | O24: 0
C25: Mentha Oil | D25: 360 KGs | E25: 19193 | F25: 4288 | G25: 8188 | H25: 0 | I25: 0 | J25: 0 | K25: ₹/ KG | L25: 916.5 | M25: 976.3 | N25: 821.6087 | O25: 28.425347
C26: Kapas | D26: 4 MT | E26: 0 | F26: 0 | G26: 0 | H26: 0 | I26: 0.03311 | J26: 0 | K26: ₹/20 KG | L26: 1440 | M26: 1440 | N26: 0 | O26: 0
C27: Rubber | D27: 1 MT | E27: - | F27: - | H27: - | I27: - | J27: - | K27: ₹/100 KG | L27: NA | M27: NA | N27: 0 | O27: 0
C28: Total for Agri. | E28: =SUM(E22:E27) -> 22135 | F28: =SUM(F22:F27) -> 4738 | G28: =SUM(G22:G27) -> 8944 | H28: =SUM(H22:H27) -> 1458.9584 | I28: =SUM(I22:I27) -> 265.27274 | J28: =SUM(J22:J27) -> 487.05321
B29: Energy | C29: Crude Oil | D29: 100 barrels | E29: 1760950 | F29: 341711 | G29: 489524 | H29: 118385 | I29: 22219.661 | J29: 32929.234 | K29: ₹/ Barrel | L29: 6805 | M29: 6524 | N29: 8281.6522 | O29: 554.07892
C30: Crude Oil Mini | D30: 10 barrels | E30: 1918481 | F30: 418737 | G30: 507168 | H30: 12872.404 | I30: 2733.1499 | J30: 3398.2503 | K30: ₹/ Barrel | L30: 6806 | M30: 6521 | N30: 7071.2174 | O30: 47.442252
C31: Natural Gas | D31: 1250 mmBtu | E31: 10690315 | F31: 2460635 | G31: 2425416 | H31: 263522.34 | I31: 73643.192 | J31: 56769.623 | K31: ₹/ mmBtu | L31: 217.8 | M31: 172.5 | N31: 48558.043 | O31: 1137.7525
C32: Natural Gas Mini | D32: 250 mmBtu | E32: 5374993 | F32: 1386413 | G32: 1360379 | H32: 26950.36 | I32: 8307.3473 | J32: 6404.706 | K32: ₹/ mmBtu | L32: 218 | M32: 172.6 | N32: 33564.217 | O32: 157.75939
C33: Total for Energy | E33: =SUM(E29:E32) -> 19744739 | F33: =SUM(F29:F32) -> 4607496 | G33: =SUM(G29:G32) -> 4782487 | H33: =SUM(H29:H32) -> 421730.11 | I33: =SUM(I29:I32) -> 106903.35 | J33: =SUM(J29:J32) -> 99501.814
B34: Index | C34: iCOMDEX Bullion | D34: 50 | E34: 19404 | F34: 3944 | G34: 3294 | H34: 1778.5941 | I34: 365.41082 | J34: 301.01429 | K34: ₹/ Unit | L34: 18389 | M34: 17588 | N34: 178.65217 | O34: 16.441198
C35: iCOMDEX Energy | D35: 125 | E35: 0 | F35: 0 | G35: 0 | H35: 0 | I35: 0 | J35: 0 | K35: ₹/ Unit
C36: iCOMDEX Metal | D36: 50 | E36: 0 | F36: 0 | G36: 0 | H36: 0 | I36: 0 | J36: 0 | K36: ₹/ Unit | L36: 17486 | M36: 16779 | N36: 0 | O36: 0
C37: Total for Index Futures | E37: =SUM(E34:E36) -> 19404 | F37: =SUM(F34:F36) -> 3944 | G37: =SUM(G34:G36) -> 3294 | H37: =SUM(H34:H36) -> 1778.5941 | I37: =SUM(I34:I36) -> 365.41082 | J37: =SUM(J34:J36) -> 301.01429
B38: Total MCX Futures | C38: Total MCX Futures | E38: =E11+E21+E28+E33+E37 -> 51617673 | F38: =F11+F21+F28+F33+F37 -> 12042205 | G38: =G11+G21+G28+G33+G37 -> 12276834 | H38: =H11+H21+H28+H33 -> 2257721.6 | I38: =I11+I21+I28+I33 -> 518135.64 | J38: =J11+J21+J28+J33 -> 570164.52
A39: MCX Options | B39: Bullion | C39: Gold | D39: 1 'KG | E39: 1466013 | F39: 162943 | G39: 558215 | H39: 1057612.5 | I39: 118434.8 | J39: 402335.77 | K39: ₹/10 grams | L39: NA | M39: NA | N39: 10314.043 | O39: 7478.3882
C40: Gold Mini | D40: 100 'Grams | E40: 3552115 | F40: 1180655 | G40: 1035211 | H40: 256209.39 | I40: 85093.273 | J40: 74567.747 | K40: ₹/10 grams | L40: NA | M40: NA | N40: 14096 | O40: 1022.1487
C41: Silver | D41: 30 'KGs | E41: 2270279 | F41: 879494 | G41: 257150 | H41: 593470.89 | I41: 238485.02 | J41: 70043.045 | K41: ₹/ 1KG | L41: NA | M41: NA | N41: 11565.304 | O41: 3228.0977
C42: Silver Mini | D42: 5 'KGs | E42: 2244581 | F42: 865127 | G42: 400057 | H42: 99999.124 | I42: 39475.884 | J42: 18319.701 | K42: ₹/ 1KG | L42: NA | M42: NA | N42: 16359.478 | O42: 759.44927
C43: Total for Bullion | E43: =SUM(E39:E42) -> 9532988 | F43: =SUM(F39:F42) -> 3088219 | G43: =SUM(G39:G42) -> 2250633 | H43: =SUM(H39:H42) -> 2007291.9 | I43: =SUM(I39:I42) -> 481488.97 | J43: =SUM(J39:J42) -> 565266.26
B44: Base Metals | C44: Copper | D44: 2.5 MT | E44: 34708 | F44: 7672 | G44: 12446 | H44: 7534.9534 | I44: 1694.7769 | J44: 2658.3408 | K44: ₹/ 1KG | L44: NA | M44: NA | N44: 710.34783 | O44: 152.53925
C45: Nickel | D45: 1.5 MT | E45: 0 | F45: 0 | G45: 0 | H45: 0 | I45: 0 | J45: 0 | K45: ₹/ 1KG | L45: NA | M45: NA | N45: 0 | O45: 0
C46: Zinc | D46: 5 MT | E46: 3083 | F46: 608 | G46: 403 | H46: 394.8994 | I46: 80.133055 | J46: 53.956045 | K46: ₹/ 1KG | L46: NA | M46: NA | N46: 31 | O46: 4.1492689
C47: Total for Base Metals | E47: =SUM(E44:E46) -> 37791 | F47: =SUM(F44:F46) -> 8280 | G47: =SUM(G44:G46) -> 12849 | H47: =SUM(H44:H46) -> 7929.8528 | I47: =SUM(I44:I46) -> 1774.91 | J47: =SUM(J44:J46) -> 2712.2968
B48: Energy | C48: Crude Oil | D48: 100 barrels | E48: 145548657 | F48: 33147105 | G48: 44018215 | H48: 9923793.6 | I48: 2186417.7 | J48: 3015457.3 | K48: ₹/ Barrel | L48: NA | M48: NA | N48: 154397.91 | O48: 10566.701
C49: Crude Oil Mini | D49: 10 barrels | E49: 2701511 | F49: 875057 | G49: 1638381 | H49: 18333.476 | I49: 5829.4739 | J49: 11237.422 | L49: NA | M49: NA | N49: 11380.087 | O49: 78.153914
C50: Natural Gas | D50: 1250 mmBtu | E50: 56845888 | F50: 14971998 | G50: 13143625 | H50: 1493446.4 | I50: 463842.01 | J50: 320455.85 | K50: ₹/ mmBtu | L50: NA | M50: NA | N50: 150324.17 | O50: 4088.6856
C51: Natural Gas Mini | D51: 250 mmBtu | E51: 1268708 | F51: 441949 | G51: 496581 | H51: 6902.3989 | I51: 2720.7839 | J51: 2428.055 | L51: NA | M51: NA | N51: 9234.7826 | O51: 49.998719
C52: Total for Energy | E52: =SUM(E48:E51) -> 206364764 | F52: =SUM(F48:F51) -> 49436109 | G52: =SUM(G48:G51) -> 59296802 | H52: =SUM(H48:H51) -> 11442476 | I52: =SUM(I48:I51) -> 2658810 | J52: =SUM(J48:J51) -> 3349578.7
B53: Total MCX Options | C53: Total MCX Options | E53: =E43+E47+E52 -> 215935543 | F53: =F43+F47+F52 -> 52532608 | G53: =G43+G47+G52 -> 61560284 | H53: =H43+H47+H52 -> 13457698 | I53: =I43+I47+I52 -> 3142073.9 | J53: =J43+J47+J52 -> 3917557.2
A54: $ indicates as on July 31, 2024
A55: Note:
A56: 1. Options includes both 'options on futures' and 'options on goods'
A57: 2. Closing prices have been considered for the 'most active contract' at the end of month
A58: 3. Average Daily OI and Values of Contract have been derived by taking the sum of end of day OI and then dividing by no. of trading days during the month
A59: 4. Options Turnover is based on Notional value.
A60: Source : MCX

Sheet 72
A1: Table 72: Commodity-wise Turnover and Trading Volume at NCDEX
A2: Exchange & Segment | B2: Commodity Type | C2: Name of the Commodity Contract | D2: Symbol | E2: Contract Size | F2: No. of contracts | I2: Value (₹ crore) | L2: Quotation | O2: Average Daily Open Interest in July 2024
D3: Symbol | F3: 2024-25$ | G3: 45444 | H3: 45474 | I3: 2024-25$ | J3: 45444 | K3: 45474 | M3: 45444 | N3: 45474 | O3: No. of Contracts | P3: Values of Contracts ( ₹ crore)
A4: NCDEX Futures | B4: Agri. | C4: Bajra | D4: BAJRA | E4: 10 MT | F4: 0 | G4: 0 | H4: 0 | I4: 0 | J4: 0 | K4: 0 | L4: ₹/ Quintal | M4: 2305 | N4: 2435 | O4: 0 | P4: 0
C5: Barley | D5: BARLEYJPR | E5: 10 MT | F5: 3 | G5: 0 | H5: 0 | I5: 0.06 | J5: 0 | K5: 0 | L5: ₹/ Quintal | M5: 2128 | N5: 2168 | O5: 0 | P5: 0
C6: CASTOROIL | D6: CASTOROIL | E6: 2MT | F6: 0 | G6: 0 | H6: 0 | I6: 0 | J6: 0 | K6: 0 | L6: ₹/ 10 KG | M6: 1175 | N6: 1245 | O6: 0 | P6: 0
C7: Castorseed | D7: CASTOR | E7: 5 MT | F7: 150141 | G7: 25137 | H7: 49126 | I7: 4405.82 | J7: 724.18 | K7: 1491.14 | L7: ₹/ Quintal | M7: 5754 | N7: 6167 | O7: 8640 | P7: 263
C8: Chana | D8: CHANA | E8: 10 MT | F8: 0 | G8: 0 | H8: 0 | I8: 0 | J8: 0 | K8: 0 | L8: ₹/ Quintal | M8: - | N8: - | O8: - | P8: -
C9: Coffee | D9: COFFEE | E9: 1MT | F9: 0 | G9: 0 | H9: 0 | I9: 0 | J9: 0 | K9: 0 | L9: ₹/ Quintal | M9: - | N9: - | O9: - | P9: -
C10: Coriander | D10: DHANIYA | E10: 5 MT | F10: 98639 | G10: 22644 | H10: 24649 | I10: 3666.47 | J10: 842.34 | K10: 892.4 | L10: ₹/ Quintal | M10: 7380 | N10: 7254 | O10: 6387 | P10: 231
C11: Cotton | D11: COTTON | E11: 1MT | F11: 0 | G11: 0 | H11: 0 | I11: 0 | J11: 0 | K11: 0 | L11: ₹/ Bale | M11: 27830 | N11: 27680 | O11: 0 | P11: 0
C12: Cotton seed oil cake | D12: COCUDAKL | E12: 10 MT | F12: 271519 | G12: 64698 | H12: 73747 | I12: 7444.27 | J12: 1780.1 | K12: 2169.85 | L12: ₹/ Quintal | M12: 2854 | N12: 2889 | O12: 6884 | P12: 202
C13: CPO | D13: CPO | E13: 10 MT | F13: 0 | G13: 0 | H13: 0 | I13: 0 | J13: 0 | K13: 0 | L13: ₹/ 10 KG | M13: - | N13: - | O13: - | P13: -
C14: Guar seed | D14: GUARSEED10 | E14: 10 MT | F14: 414604 | G14: 79806 | H14: 115804 | I14: 11313.42 | J14: 2159.66 | K14: 3176.13 | L14: ₹/ Quintal | M14: 5346 | N14: 5661 | O14: 11895 | P14: 325
C15: Guargum | D15: GUARGUM5 | E15: 5 MT | F15: 204182 | G15: 43837 | H15: 56183 | I15: 10988.88 | J15: 2320.59 | K15: 3026.91 | L15: ₹/ Quintal | M15: 10378 | N15: 11217 | O15: 10763 | P15: 577
C16: Groundnut | D16: GROUNDNUT | E16: 5MT | F16: 0 | G16: 0 | H16: 0 | I16: 0 | J16: 0 | K16: 0 | L16: ₹/ Quintal | M16: 6137 | N16: 5876 | O16: 0 | P16: 0
C17: Gur | D17: GUR | E17: 10 MT | F17: 0 | G17: 0 | H17: 0 | I17: 0 | J17: 0 | K17: 0 | L17: ₹/ 40KG | M17: - | N17: - | O17: 0 | P17: -
C18: Isabgol | D18: ISABGOL | E18: 3 MT | F18: 0 | G18: 0 | H18: 0 | I18: 0 | J18: 0 | K18: 0 | L18: ₹/ Quintal | M18: 14560 | N18: 13980 | O18: 0 | P18: 0
C19: Jeera | D19: JEERAMINI | F19: 21 | G19: 0 | H19: 0 | I19: 0.49 | J19: 0 | K19: 0 | M19: 29125 | N19: 26880 | O19: 0 | P19: 0
C20: Jeera | D20: JEERAUNJHA | E20: 3 MT | F20: 52681 | G20: 12987 | H20: 10706 | I20: 4200.94 | J20: 1106.79 | K20: 882.43 | L20: ₹/ Quintal | M20: 29075 | N20: 26835 | O20: 1237 | P20: 102
C21: Kapas | D21: KAPAS | E21: 4 MT | F21: 9694 | G21: 2046 | H21: 2704 | I21: 301.99 | J21: 65.37 | K21: 86.74 | L21: ₹/ 20KG | M21: 1555 | N21: 1531 | O21: 900 | P21: 29
C22: Maize | D22: MAIZE | E22: 10 MT | F22: 0 | G22: 0 | H22: 0 | I22: 0 | J22: 0 | K22: 0 | L22: ₹/ Quintal | M22: 2410 | N22: 2510 | O22: 0 | P22: 0
C23: Refined Soy Oil | D23: SYOREF | E23: 5 MT | F23: 0 | G23: 0 | H23: 0 | I23: 0 | J23: 0 | K23: 0 | L23: ₹/ 10 KG | M23: - | N23: - | O23: 0 | P23: 0
C24: RM seed | D24: RMSEED | E24: 10 MT | F24: 0 | G24: 0 | H24: 0 | I24: 0 | J24: 0 | K24: 0 | L24: ₹/ Quintal | M24: - | N24: - | O24: 0 | P24: 0
C25: Sesameseed | D25: SESAMESEED | E25: 5 MT | F25: 0 | G25: 0 | H25: 0 | I25: 0 | J25: 0 | K25: 0 | L25: ₹/ Quintal | M25: 14360 | N25: 14005 | O25: 0 | P25: 0
C26: Soy bean | D26: SYBEANIDR | E26: 5 MT | F26: 0 | G26: 0 | H26: 0 | I26: 0 | J26: 0 | K26: 0 | L26: ₹/ Quintal | M26: - | N26: - | O26: 0 | P26: 0
C27: Soyameal | D27: SBMEALIDR | E27: 10 MT | F27: 0 | G27: 0 | H27: 0 | I27: 0 | J27: 0 | K27: 0 | L27: ₹/ MT | M27: - | N27: - | O27: 0 | P27: 0
C28: Crude Sunflower Oil | D28: SUNOIL | E28: 5 MT | F28: 2991 | G28: 679 | H28: 609 | I28: 133.72 | J28: 31.52 | K28: 27.85 | M28: 913 | N28: 892 | O28: 174 | P28: 8
C29: Turmeric | D29: TMCFGRNZM | E29: 5 MT | F29: 90088 | G29: 22467 | H29: 18827 | I29: 7981.99 | J29: 1989.49 | K29: 1517.95 | L29: ₹/ Quintal | M29: 16924 | N29: 15858 | O29: 5363 | P29: 430
C30: Wheat | D30: WHEATFAQ | E30: 10 MT | F30: 0 | G30: 0 | H30: 0 | I30: 0 | J30: 0 | K30: 0 | L30: ₹/ Quintal | M30: - | N30: - | O30: - | P30: -
C31: Total for Agri. | F31: 1294563 | G31: 274301 | H31: 352355 | I31: 50438.05 | J31: 11020.04 | K31: 13271.4 | M31: - | N31: - | O31: 52243 | P31: 2167
B32: Metals | C32: Steel Long | D32: STEEL | E32: 10 MT | F32: 16 | G32: 0 | H32: 0 | I32: 0.68 | J32: 0 | K32: 0 | L32: ₹/ MT | M32: 44190 | N32: 43470 | O32: 0 | P32: 0
C33: Total for Metal | F33: =F32 -> 16 | G33: =G32 -> 0 | H33: =H32 -> 0 | I33: =I32 -> 0.68 | J33: =J32 -> 0 | K33: =K32 -> 0 | O33: 0 | P33: 0
B34: Index | C34: AGRIDEX | D34: AGRIDEX | E34: 1 lot | F34: 0 | G34: 0 | H34: 0 | I34: 0 | J34: 0 | K34: 0 | L34: ₹/ Unit | M34: 0 | N34: 0 | O34: 0 | P34: 0
C35: GUAREX | D35: GUAREX | E35: 1 lot | F35: 0 | G35: 0 | H35: 0 | I35: 0 | J35: 0 | K35: 0 | L35: ₹/ Unit | M35: 0 | N35: 0 | O35: 0 | P35: 0
C36: SOYDEX | D36: SOYDEX | E36: 1 lot | F36: 0 | G36: 0 | H36: 0 | I36: 0 | J36: 0 | K36: 0 | L36: ₹/ Unit | M36: 0 | N36: 0 | O36: 0 | P36: 0
C37: Total Index Futures | F37: =SUM(F34:F36) -> 0 | G37: =SUM(G34:G36) -> 0 | H37: =SUM(H34:H36) -> 0 | I37: =SUM(I34:I36) -> 0 | J37: =SUM(J34:J36) -> 0 | K37: =SUM(K34:K36) -> 0 | M37: 0 | O37: 0 | P37: 0
B38: Total NCDEX Futures | C38: Total NCDEX Futures | F38: =F37+F33+F31 -> 1294579 | G38: =G37+G33+G31 -> 274301 | H38: =H37+H33+H31 -> 352355 | I38: =I37+I33+I31 -> 50438.73 | J38: =J37+J33+J31 -> 11020.04 | K38: =K37+K33+K31 -> 13271.4 | M38: - | O38: 49629 | P38: 2167
A39: NCDEX Options | B39: Agri. | C39: Chana | D39: CHANA | E39: 10 MT | F39: 0 | G39: 0 | H39: 0 | I39: 0 | J39: 0 | K39: 0 | L39: ₹/ Quintal | M39: 0 | N39: 0 | O39: - | P39: 0
C40: DHANIYA | D40: DHANIYA | E40: 5 MT | F40: 0 | G40: 0 | H40: 0 | I40: 0 | J40: 0 | K40: 0 | L40: ₹/ Quintal | M40: 0 | N40: 0 | O40: - | P40: 0
C41: Guargum | D41: GUARGUM5 | E41: 5 MT | F41: 0 | G41: 0 | H41: 0 | I41: 0 | J41: 0 | K41: 0 | L41: ₹/ Quintal | M41: 0 | N41: 0 | O41: - | P41: 0
C42: Guarseed | D42: GUARSEED10 | E42: 5 MT | F42: 74.12 | G42: 0.65 | H42: 73.47 | I42: 416.39 | J42: 3.52 | K42: 412.87 | L42: ₹/ Quintal | M42: 0 | N42: 0 | O42: 566 | P42: 0
C43: Jeera | D43: JEERAUNJHA | E43: 3 MT | F43: 0 | G43: 0 | H43: 0 | I43: 0 | J43: 0 | K43: 0 | L43: ₹/ Quintal | M43: 0 | N43: 0 | O43: - | P43: 0
C44: Soybean | D44: SYBEANIDR | E44: 5 MT | F44: 0 | G44: 0 | H44: 0 | I44: 0 | J44: 0 | K44: 0 | L44: ₹/ Quintal | M44: 0 | N44: 0 | O44: - | P44: 0
C45: Maize | D45: MAIZE | E45: 10 MT | F45: 0 | G45: 0 | H45: 0 | I45: 0 | J45: 0 | K45: 0 | L45: ₹/ Quintal | M45: 0 | N45: 0 | O45: - | P45: 0
C46: RM Seed | D46: RMSEED | E46: 10 MT | F46: 0 | G46: 0 | H46: 0 | I46: 0 | J46: 0 | K46: 0 | L46: ₹/ Quintal | M46: 0 | N46: 0 | O46: - | P46: 0
C47: Wheat | D47: WHEATFAQ | E47: 10 MT | F47: 0 | G47: 0 | H47: 0 | I47: 0 | J47: 0 | K47: 0 | L47: ₹/ Quintal | M47: 0 | N47: 0 | O47: - | P47: 0
C48: Turmeric | D48: TMCFGRNZM | E48: 5 MT | F48: 0 | G48: 0 | H48: 0 | I48: 0 | J48: 0 | K48: 0 | L48: ₹/ Quintal | M48: 0 | N48: 0 | O48: - | P48: 0
B49: Total NCDEX Options | C49: Total NCDEX Options | F49: =SUM(F39:F48) -> 74.12 | G49: =SUM(G39:G48) -> 0.65 | H49: =SUM(H39:H48) -> 73.47 | I49: =SUM(I39:I48) -> 416.39 | J49: =SUM(J39:J48) -> 3.52 | K49: =SUM(K39:K48) -> 412.87 | M49: 0 | N49: 0 | O49: 566 | P49: 0
A50: $ indicates as on Jul 31, 2024
A51: Note: 1. AGRIDEX volume are in '000 lots and is not included for computing the total volume in "000 tonnes" .
A52: 2. For Options traded qty is in '000 tons.
A53: Source: NCDEX

Sheet 73
A1: Table 73: Commodity-wise Turnover and Trading Volume at BSE and NSE
A2: Exchange & Segment | B2: Commodity Type | C2: Name of the Commodity Contract | D2: Contract Size | E2: No. of contracts | H2: Value (₹ crore) | K2: Quotation | L2: Close Price | N2: Average Daily Open Interest in July 2024
E3: 2024-25$ | F3: 45444 | G3: 45474 | H3: 2024-25$ | I3: 45444 | J3: 45474 | L3: 45444 | M3: 45474 | N3: No. of Contracts | O3: Values of Contracts (₹ crore)
A4: BSE Futures | B4: Bullion | C4: Gold | D4: 1 KG | E4: 0 | F4: - | G4: - | H4: 0 | I4: - | J4: - | K4: ₹/10 grams | L4: 71716 | M4: 69012 | N4: 0 | O4: 0
C5: Silver | D5: 30 KGs | E5: 0 | F5: - | G5: - | H5: 0 | I5: - | J5: - | K5: ₹/ KG | L5: 87167 | M5: 82871 | N5: 0 | O5: 0
